{
  "type": "Feature",
  "properties": {
    "iso:country": "GB",
    "wof:name": "AB39 2QL",
    "wof:placetype": "postalcode"
  },
  "geometry": {"coordinates":[-2.233226,56.958151],"type":"Point"}
}
