{
  "type": "Feature",
  "properties": {
    "iso:country": "GB",
    "wof:name": "CV47 0NL",
    "wof:placetype": "postalcode"
  },
  "geometry": {"coordinates":[-1.395926,52.252989],"type":"Point"}
}
