{
  "type": "Feature",
  "properties": {
    "iso:country": "GB",
    "wof:name": "IP12 3FD",
    "wof:placetype": "postalcode"
  },
  "geometry": {"coordinates":[1.343737,52.072152],"type":"Point"}
}
