{
  "type": "Feature",
  "properties": {
    "iso:country": "GB",
    "wof:name": "CF5 6FS",
    "wof:placetype": "postalcode"
  },
  "geometry": {"coordinates":[-3.269036,51.508763],"type":"Point"}
}
