{
  "type": "Feature",
  "properties": {
    "iso:country": "GB",
    "wof:name": "MK10 9TT",
    "wof:placetype": "postalcode"
  },
  "geometry": {"coordinates":[-0.719758,52.039618],"type":"Point"}
}
