{
  "type": "Feature",
  "properties": {
    "iso:country": "GB",
    "wof:name": "LE15 6GN",
    "wof:placetype": "postalcode"
  },
  "geometry": {"coordinates":[-0.736251,52.67256],"type":"Point"}
}
