{
  "type": "Feature",
  "properties": {
    "iso:country": "GB",
    "wof:name": "RG14 7WT",
    "wof:placetype": "postalcode"
  },
  "geometry": {"coordinates":[-1.289014,51.396116],"type":"Point"}
}
