{
  "type": "Feature",
  "properties": {
    "iso:country": "GB",
    "wof:name": "CB6 1GU",
    "wof:placetype": "postalcode"
  },
  "geometry": {"coordinates":[0.29967,52.454256],"type":"Point"}
}
