{
  "type": "Feature",
  "properties": {
    "iso:country": "GB",
    "wof:name": "NN7 2QR",
    "wof:placetype": "postalcode"
  },
  "geometry": {"coordinates":[-0.89407,52.155048],"type":"Point"}
}
