{
  "type": "Feature",
  "properties": {
    "iso:country": "GB",
    "wof:name": "WS10 8WE",
    "wof:placetype": "postalcode"
  },
  "geometry": {"coordinates":[-2.051896,52.565559],"type":"Point"}
}
