{
  "type": "Feature",
  "properties": {
    "iso:country": "GB",
    "wof:name": "EX39 5FB",
    "wof:placetype": "postalcode"
  },
  "geometry": {"coordinates":[-4.2982,50.97123],"type":"Point"}
}
