{
  "type": "Feature",
  "properties": {
    "iso:country": "GB",
    "wof:name": "CF62 5DX",
    "wof:placetype": "postalcode"
  },
  "geometry": {"coordinates":[-3.266672,51.395927],"type":"Point"}
}
