{
  "type": "Feature",
  "properties": {
    "iso:country": "GB",
    "wof:name": "NE69 7AD",
    "wof:placetype": "postalcode"
  },
  "geometry": {"coordinates":[-1.745558,55.600604],"type":"Point"}
}
