{
  "type": "Feature",
  "properties": {
    "iso:country": "GB",
    "wof:name": "HR9 7WP",
    "wof:placetype": "postalcode"
  },
  "geometry": {"coordinates":[-2.569295,51.92135],"type":"Point"}
}
