{
  "type": "Feature",
  "properties": {
    "iso:country": "GB",
    "wof:name": "TN27 9DD",
    "wof:placetype": "postalcode"
  },
  "geometry": {"coordinates":[0.695339,51.186419],"type":"Point"}
}
