{
  "type": "Feature",
  "properties": {
    "iso:country": "GB",
    "wof:name": "PE20 3RF",
    "wof:placetype": "postalcode"
  },
  "geometry": {"coordinates":[-0.140407,52.988046],"type":"Point"}
}
