{
  "type": "Feature",
  "properties": {
    "iso:country": "GB",
    "wof:name": "LN11 7BY",
    "wof:placetype": "postalcode"
  },
  "geometry": {"coordinates":[0.018684,53.369732],"type":"Point"}
}
