{
  "type": "Feature",
  "properties": {
    "iso:country": "GB",
    "wof:name": "CM6 1DA",
    "wof:placetype": "postalcode"
  },
  "geometry": {"coordinates":[0.360294,51.8731],"type":"Point"}
}
