{
  "type": "Feature",
  "properties": {
    "iso:country": "GB",
    "wof:name": "CB24 1AQ",
    "wof:placetype": "postalcode"
  },
  "geometry": {"coordinates":[0.059657,52.287711],"type":"Point"}
}
