{
  "type": "Feature",
  "properties": {
    "iso:country": "GB",
    "wof:name": "BS30 8EH",
    "wof:placetype": "postalcode"
  },
  "geometry": {"coordinates":[-2.483022,51.442861],"type":"Point"}
}
