{
  "type": "Feature",
  "properties": {
    "iso:country": "GB",
    "wof:name": "TQ12 1BY",
    "wof:placetype": "postalcode"
  },
  "geometry": {"coordinates":[-3.652403,50.536824],"type":"Point"}
}
