{
  "type": "Feature",
  "properties": {
    "iso:country": "GB",
    "wof:name": "LE7 9NG",
    "wof:placetype": "postalcode"
  },
  "geometry": {"coordinates":[-0.903783,52.643247],"type":"Point"}
}
