{
  "type": "Feature",
  "properties": {
    "iso:country": "GB",
    "wof:name": "DG4 6ED",
    "wof:placetype": "postalcode"
  },
  "geometry": {"coordinates":[-3.922488,55.366875],"type":"Point"}
}
