{
  "type": "Feature",
  "properties": {
    "iso:country": "GB",
    "wof:name": "DE15 9PW",
    "wof:placetype": "postalcode"
  },
  "geometry": {"coordinates":[-1.633508,52.783088],"type":"Point"}
}
