{
  "type": "Feature",
  "properties": {
    "iso:country": "GB",
    "wof:name": "PL19 8FR",
    "wof:placetype": "postalcode"
  },
  "geometry": {"coordinates":[-4.15805,50.549936],"type":"Point"}
}
