{
  "type": "Feature",
  "properties": {
    "iso:country": "GB",
    "wof:name": "SG18 9FW",
    "wof:placetype": "postalcode"
  },
  "geometry": {"coordinates":[-0.268408,52.049072],"type":"Point"}
}
