{
  "type": "Feature",
  "properties": {
    "iso:country": "GB",
    "wof:name": "SN1 4BT",
    "wof:placetype": "postalcode"
  },
  "geometry": {"coordinates":[-1.775094,51.551569],"type":"Point"}
}
