{
  "type": "Feature",
  "properties": {
    "iso:country": "GB",
    "wof:name": "CF23 5LU",
    "wof:placetype": "postalcode"
  },
  "geometry": {"coordinates":[-3.166024,51.502737],"type":"Point"}
}
