{
  "type": "Feature",
  "properties": {
    "iso:country": "GB",
    "wof:name": "CV22 7ZU",
    "wof:placetype": "postalcode"
  },
  "geometry": {"coordinates":[-1.315063,52.35663],"type":"Point"}
}
