{
  "type": "Feature",
  "properties": {
    "iso:country": "GB",
    "wof:name": "HR2 9NG",
    "wof:placetype": "postalcode"
  },
  "geometry": {"coordinates":[-2.840507,52.022088],"type":"Point"}
}
