{
  "type": "Feature",
  "properties": {
    "iso:country": "GB",
    "wof:name": "HA1 4WJ",
    "wof:placetype": "postalcode"
  },
  "geometry": {"coordinates":[-0.353575,51.582249],"type":"Point"}
}
