{
  "type": "Feature",
  "properties": {
    "iso:country": "GB",
    "wof:name": "BN2 4NU",
    "wof:placetype": "postalcode"
  },
  "geometry": {"coordinates":[-0.107662,50.839357],"type":"Point"}
}
