{
  "type": "Feature",
  "properties": {
    "iso:country": "GB",
    "wof:name": "LS21 2FF",
    "wof:placetype": "postalcode"
  },
  "geometry": {"coordinates":[-1.709996,53.916651],"type":"Point"}
}
