{
  "type": "Feature",
  "properties": {
    "iso:country": "GB",
    "wof:name": "BA21 3FZ",
    "wof:placetype": "postalcode"
  },
  "geometry": {"coordinates":[-2.666277,50.956206],"type":"Point"}
}
