{
  "type": "Feature",
  "properties": {
    "iso:country": "GB",
    "wof:name": "EC2M 2AS",
    "wof:placetype": "postalcode"
  },
  "geometry": {"coordinates":[-0.08319,51.518605],"type":"Point"}
}
