{
  "type": "Feature",
  "properties": {
    "iso:country": "GB",
    "wof:name": "CM23 2YJ",
    "wof:placetype": "postalcode"
  },
  "geometry": {"coordinates":[0.143749,51.881491],"type":"Point"}
}
