{
  "type": "Feature",
  "properties": {
    "iso:country": "GB",
    "wof:name": "S61 2FD",
    "wof:placetype": "postalcode"
  },
  "geometry": {"coordinates":[-1.432356,53.462439],"type":"Point"}
}
