{
  "type": "Feature",
  "properties": {
    "iso:country": "GB",
    "wof:name": "L32 1BS",
    "wof:placetype": "postalcode"
  },
  "geometry": {"coordinates":[-2.878848,53.491921],"type":"Point"}
}
