{
  "type": "Feature",
  "properties": {
    "iso:country": "GB",
    "wof:name": "NR7 8UR",
    "wof:placetype": "postalcode"
  },
  "geometry": {"coordinates":[1.345839,52.656291],"type":"Point"}
}
