{
  "type": "Feature",
  "properties": {
    "iso:country": "GB",
    "wof:name": "WD25 9DX",
    "wof:placetype": "postalcode"
  },
  "geometry": {"coordinates":[-0.38088,51.680889],"type":"Point"}
}
