{
  "type": "Feature",
  "properties": {
    "iso:country": "GB",
    "wof:name": "DH3 1FD",
    "wof:placetype": "postalcode"
  },
  "geometry": {"coordinates":[-1.573153,54.901709],"type":"Point"}
}
