{
  "type": "Feature",
  "properties": {
    "iso:country": "GB",
    "wof:name": "G52 4XN",
    "wof:placetype": "postalcode"
  },
  "geometry": {"coordinates":[-4.374811,55.862854],"type":"Point"}
}
