{
  "type": "Feature",
  "properties": {
    "iso:country": "GB",
    "wof:name": "G69 0BE",
    "wof:placetype": "postalcode"
  },
  "geometry": {"coordinates":[-4.093189,55.91569],"type":"Point"}
}
