{
  "type": "Feature",
  "properties": {
    "iso:country": "GB",
    "wof:name": "SA5 7DU",
    "wof:placetype": "postalcode"
  },
  "geometry": {"coordinates":[-3.97021,51.681333],"type":"Point"}
}
