{
  "type": "Feature",
  "properties": {
    "iso:country": "GB",
    "wof:name": "OX12 0GJ",
    "wof:placetype": "postalcode"
  },
  "geometry": {"coordinates":[-1.399597,51.630482],"type":"Point"}
}
