{
  "type": "Feature",
  "properties": {
    "iso:country": "GB",
    "wof:name": "GU10 2BF",
    "wof:placetype": "postalcode"
  },
  "geometry": {"coordinates":[-0.725319,51.191189],"type":"Point"}
}
