{
  "type": "Feature",
  "properties": {
    "iso:country": "GB",
    "wof:name": "KA1 5BT",
    "wof:placetype": "postalcode"
  },
  "geometry": {"coordinates":[-4.45562,55.599764],"type":"Point"}
}
