{
  "type": "Feature",
  "properties": {
    "iso:country": "GB",
    "wof:name": "PL25 4GA",
    "wof:placetype": "postalcode"
  },
  "geometry": {"coordinates":[-4.772648,50.330593],"type":"Point"}
}
