{
  "type": "Feature",
  "properties": {
    "iso:country": "GB",
    "wof:name": "TA18 8FG",
    "wof:placetype": "postalcode"
  },
  "geometry": {"coordinates":[-2.772412,50.869978],"type":"Point"}
}
