{
  "type": "Feature",
  "properties": {
    "iso:country": "GB",
    "wof:name": "SO50 9RZ",
    "wof:placetype": "postalcode"
  },
  "geometry": {"coordinates":[-1.382107,50.961429],"type":"Point"}
}
