{
  "type": "Feature",
  "properties": {
    "iso:country": "GB",
    "wof:name": "NG9 8JP",
    "wof:placetype": "postalcode"
  },
  "geometry": {"coordinates":[-1.269917,52.943618],"type":"Point"}
}
