{
  "type": "Feature",
  "properties": {
    "iso:country": "GB",
    "wof:name": "WA7 1BU",
    "wof:placetype": "postalcode"
  },
  "geometry": {"coordinates":[-2.728194,53.342896],"type":"Point"}
}
