{
  "type": "Feature",
  "properties": {
    "iso:country": "GB",
    "wof:name": "LL58 8DL",
    "wof:placetype": "postalcode"
  },
  "geometry": {"coordinates":[-4.092645,53.263595],"type":"Point"}
}
