{
  "type": "Feature",
  "properties": {
    "iso:country": "GB",
    "wof:name": "MK10 7LT",
    "wof:placetype": "postalcode"
  },
  "geometry": {"coordinates":[-0.669402,52.044895],"type":"Point"}
}
