{
  "type": "Feature",
  "properties": {
    "iso:country": "GB",
    "wof:name": "B97 5EZ",
    "wof:placetype": "postalcode"
  },
  "geometry": {"coordinates":[-1.979522,52.296604],"type":"Point"}
}
