{
  "type": "Feature",
  "properties": {
    "iso:country": "GB",
    "wof:name": "WA12 9AP",
    "wof:placetype": "postalcode"
  },
  "geometry": {"coordinates":[-2.649178,53.448914],"type":"Point"}
}
