{
  "type": "Feature",
  "properties": {
    "iso:country": "GB",
    "wof:name": "IP14 4DA",
    "wof:placetype": "postalcode"
  },
  "geometry": {"coordinates":[1.016683,52.195904],"type":"Point"}
}
