{
  "type": "Feature",
  "properties": {
    "iso:country": "GB",
    "wof:name": "SG4 9JG",
    "wof:placetype": "postalcode"
  },
  "geometry": {"coordinates":[-0.268499,51.94142],"type":"Point"}
}
