{
  "type": "Feature",
  "properties": {
    "iso:country": "GB",
    "wof:name": "EX18 7LZ",
    "wof:placetype": "postalcode"
  },
  "geometry": {"coordinates":[-3.948577,50.906925],"type":"Point"}
}
