{
  "type": "Feature",
  "properties": {
    "iso:country": "GB",
    "wof:name": "WA9 5XH",
    "wof:placetype": "postalcode"
  },
  "geometry": {"coordinates":[-2.741964,53.424868],"type":"Point"}
}
