{
  "type": "Feature",
  "properties": {
    "iso:country": "GB",
    "wof:name": "B78 3BN",
    "wof:placetype": "postalcode"
  },
  "geometry": {"coordinates":[-1.716882,52.630815],"type":"Point"}
}
