{
  "type": "Feature",
  "properties": {
    "iso:country": "GB",
    "wof:name": "CA10 1LW",
    "wof:placetype": "postalcode"
  },
  "geometry": {"coordinates":[-2.669455,54.695904],"type":"Point"}
}
