{
  "type": "Feature",
  "properties": {
    "iso:country": "GB",
    "wof:name": "CW5 8JH",
    "wof:placetype": "postalcode"
  },
  "geometry": {"coordinates":[-2.633064,53.069183],"type":"Point"}
}
