{
  "type": "Feature",
  "properties": {
    "iso:country": "GB",
    "wof:name": "EH41 3FT",
    "wof:placetype": "postalcode"
  },
  "geometry": {"coordinates":[-2.805725,55.951026],"type":"Point"}
}
