{
  "type": "Feature",
  "properties": {
    "iso:country": "GB",
    "wof:name": "NE22 7FF",
    "wof:placetype": "postalcode"
  },
  "geometry": {"coordinates":[-1.544002,55.143635],"type":"Point"}
}
