{
  "type": "Feature",
  "properties": {
    "iso:country": "GB",
    "wof:name": "EX34 7EH",
    "wof:placetype": "postalcode"
  },
  "geometry": {"coordinates":[-4.198383,51.188172],"type":"Point"}
}
