{
  "type": "Feature",
  "properties": {
    "iso:country": "GB",
    "wof:name": "OX2 9SZ",
    "wof:placetype": "postalcode"
  },
  "geometry": {"coordinates":[-1.311235,51.745925],"type":"Point"}
}
