{
  "type": "Feature",
  "properties": {
    "iso:country": "GB",
    "wof:name": "NE61 3FP",
    "wof:placetype": "postalcode"
  },
  "geometry": {"coordinates":[-1.711787,55.180952],"type":"Point"}
}
