{
  "type": "Feature",
  "properties": {
    "iso:country": "GB",
    "wof:name": "S64 5WG",
    "wof:placetype": "postalcode"
  },
  "geometry": {"coordinates":[-1.302568,53.479767],"type":"Point"}
}
