{
  "type": "Feature",
  "properties": {
    "iso:country": "GB",
    "wof:name": "YO7 3RF",
    "wof:placetype": "postalcode"
  },
  "geometry": {"coordinates":[-1.353706,54.220816],"type":"Point"}
}
