{
  "type": "Feature",
  "properties": {
    "iso:country": "GB",
    "wof:name": "GL3 4XX",
    "wof:placetype": "postalcode"
  },
  "geometry": {"coordinates":[-2.161484,51.853503],"type":"Point"}
}
