{
  "type": "Feature",
  "properties": {
    "iso:country": "GB",
    "wof:name": "SN16 9DJ",
    "wof:placetype": "postalcode"
  },
  "geometry": {"coordinates":[-2.056798,51.597088],"type":"Point"}
}
