{
  "type": "Feature",
  "properties": {
    "iso:country": "GB",
    "wof:name": "RH16 2GJ",
    "wof:placetype": "postalcode"
  },
  "geometry": {"coordinates":[-0.076736,51.005483],"type":"Point"}
}
