{
  "type": "Feature",
  "properties": {
    "iso:country": "GB",
    "wof:name": "PA10 2HG",
    "wof:placetype": "postalcode"
  },
  "geometry": {"coordinates":[-4.551507,55.835758],"type":"Point"}
}
