{
  "type": "Feature",
  "properties": {
    "iso:country": "GB",
    "wof:name": "G74 5DX",
    "wof:placetype": "postalcode"
  },
  "geometry": {"coordinates":[-4.23055,55.770073],"type":"Point"}
}
