{
  "type": "Feature",
  "properties": {
    "iso:country": "GB",
    "wof:name": "M32 0HS",
    "wof:placetype": "postalcode"
  },
  "geometry": {"coordinates":[-2.299182,53.452093],"type":"Point"}
}
