{
  "type": "Feature",
  "properties": {
    "iso:country": "GB",
    "wof:name": "MK43 8AL",
    "wof:placetype": "postalcode"
  },
  "geometry": {"coordinates":[-0.648159,52.154013],"type":"Point"}
}
