{
  "type": "Feature",
  "properties": {
    "iso:country": "GB",
    "wof:name": "CA3 0BF",
    "wof:placetype": "postalcode"
  },
  "geometry": {"coordinates":[-2.933032,54.917294],"type":"Point"}
}
