{
  "type": "Feature",
  "properties": {
    "iso:country": "GB",
    "wof:name": "EX16 9FH",
    "wof:placetype": "postalcode"
  },
  "geometry": {"coordinates":[-3.472013,51.018354],"type":"Point"}
}
