{
  "type": "Feature",
  "properties": {
    "iso:country": "GB",
    "wof:name": "NG2 2LQ",
    "wof:placetype": "postalcode"
  },
  "geometry": {"coordinates":[-1.140964,52.940959],"type":"Point"}
}
