{
  "type": "Feature",
  "properties": {
    "iso:country": "GB",
    "wof:name": "EH16 4RY",
    "wof:placetype": "postalcode"
  },
  "geometry": {"coordinates":[-3.120276,55.93454],"type":"Point"}
}
