{
  "type": "Feature",
  "properties": {
    "iso:country": "GB",
    "wof:name": "SW20 8SU",
    "wof:placetype": "postalcode"
  },
  "geometry": {"coordinates":[-0.217384,51.411082],"type":"Point"}
}
