{
  "type": "Feature",
  "properties": {
    "iso:country": "GB",
    "wof:name": "NE40 3QE",
    "wof:placetype": "postalcode"
  },
  "geometry": {"coordinates":[-1.768275,54.976714],"type":"Point"}
}
