{
  "type": "Feature",
  "properties": {
    "iso:country": "GB",
    "wof:name": "CF24 4PH",
    "wof:placetype": "postalcode"
  },
  "geometry": {"coordinates":[-3.175955,51.497846],"type":"Point"}
}
