{
  "type": "Feature",
  "properties": {
    "iso:country": "GB",
    "wof:name": "NE1 8SF",
    "wof:placetype": "postalcode"
  },
  "geometry": {"coordinates":[-1.610646,54.977372],"type":"Point"}
}
