{
  "type": "Feature",
  "properties": {
    "iso:country": "GB",
    "wof:name": "SO50 9RS",
    "wof:placetype": "postalcode"
  },
  "geometry": {"coordinates":[-1.372865,50.958304],"type":"Point"}
}
