{
  "type": "Feature",
  "properties": {
    "iso:country": "GB",
    "wof:name": "IP8 4RN",
    "wof:placetype": "postalcode"
  },
  "geometry": {"coordinates":[1.013811,52.10283],"type":"Point"}
}
