{
  "type": "Feature",
  "properties": {
    "iso:country": "GB",
    "wof:name": "SY3 8TG",
    "wof:placetype": "postalcode"
  },
  "geometry": {"coordinates":[-2.78553,52.711576],"type":"Point"}
}
