{
  "type": "Feature",
  "properties": {
    "iso:country": "GB",
    "wof:name": "DN4 6EJ",
    "wof:placetype": "postalcode"
  },
  "geometry": {"coordinates":[-1.066724,53.501458],"type":"Point"}
}
