{
  "type": "Feature",
  "properties": {
    "iso:country": "GB",
    "wof:name": "CB8 7PY",
    "wof:placetype": "postalcode"
  },
  "geometry": {"coordinates":[0.505568,52.272949],"type":"Point"}
}
