{
  "type": "Feature",
  "properties": {
    "iso:country": "GB",
    "wof:name": "BH16 6BG",
    "wof:placetype": "postalcode"
  },
  "geometry": {"coordinates":[-2.078313,50.75788],"type":"Point"}
}
