{
  "type": "Feature",
  "properties": {
    "iso:country": "GB",
    "wof:name": "IP21 5EQ",
    "wof:placetype": "postalcode"
  },
  "geometry": {"coordinates":[1.24326,52.305005],"type":"Point"}
}
