{
  "type": "Feature",
  "properties": {
    "iso:country": "GB",
    "wof:name": "IP31 3FF",
    "wof:placetype": "postalcode"
  },
  "geometry": {"coordinates":[0.921208,52.286236],"type":"Point"}
}
