{
  "type": "Feature",
  "properties": {
    "iso:country": "GB",
    "wof:name": "WN7 5FS",
    "wof:placetype": "postalcode"
  },
  "geometry": {"coordinates":[-2.529772,53.501942],"type":"Point"}
}
