{
  "type": "Feature",
  "properties": {
    "iso:country": "GB",
    "wof:name": "G43 1AJ",
    "wof:placetype": "postalcode"
  },
  "geometry": {"coordinates":[-4.331231,55.819937],"type":"Point"}
}
