{
  "type": "Feature",
  "properties": {
    "iso:country": "GB",
    "wof:name": "HR4 9RX",
    "wof:placetype": "postalcode"
  },
  "geometry": {"coordinates":[-2.722262,52.06682],"type":"Point"}
}
