{
  "type": "Feature",
  "properties": {
    "iso:country": "GB",
    "wof:name": "MK17 0FN",
    "wof:placetype": "postalcode"
  },
  "geometry": {"coordinates":[-0.869967,51.973341],"type":"Point"}
}
