{
  "type": "Feature",
  "properties": {
    "iso:country": "GB",
    "wof:name": "HD8 0TS",
    "wof:placetype": "postalcode"
  },
  "geometry": {"coordinates":[-1.690899,53.615315],"type":"Point"}
}
