{
  "type": "Feature",
  "properties": {
    "iso:country": "GB",
    "wof:name": "SN2 1FR",
    "wof:placetype": "postalcode"
  },
  "geometry": {"coordinates":[-1.784073,51.571197],"type":"Point"}
}
