{
  "type": "Feature",
  "properties": {
    "iso:country": "GB",
    "wof:name": "IP27 0QS",
    "wof:placetype": "postalcode"
  },
  "geometry": {"coordinates":[0.606329,52.472012],"type":"Point"}
}
