{
  "type": "Feature",
  "properties": {
    "iso:country": "GB",
    "wof:name": "OX7 6QD",
    "wof:placetype": "postalcode"
  },
  "geometry": {"coordinates":[-1.618539,51.881859],"type":"Point"}
}
