{
  "type": "Feature",
  "properties": {
    "iso:country": "GB",
    "wof:name": "WF3 2JS",
    "wof:placetype": "postalcode"
  },
  "geometry": {"coordinates":[-1.547059,53.720695],"type":"Point"}
}
