{
  "type": "Feature",
  "properties": {
    "iso:country": "GB",
    "wof:name": "WR8 9BF",
    "wof:placetype": "postalcode"
  },
  "geometry": {"coordinates":[-2.116621,52.089397],"type":"Point"}
}
