{
  "type": "Feature",
  "properties": {
    "iso:country": "GB",
    "wof:name": "EH16 4WE",
    "wof:placetype": "postalcode"
  },
  "geometry": {"coordinates":[-3.120629,55.924078],"type":"Point"}
}
