{
  "type": "Feature",
  "properties": {
    "iso:country": "GB",
    "wof:name": "WA13 9EF",
    "wof:placetype": "postalcode"
  },
  "geometry": {"coordinates":[-2.460003,53.387924],"type":"Point"}
}
