{
  "type": "Feature",
  "properties": {
    "iso:country": "GB",
    "wof:name": "LN4 3BU",
    "wof:placetype": "postalcode"
  },
  "geometry": {"coordinates":[-0.31561,53.093326],"type":"Point"}
}
