{
  "type": "Feature",
  "properties": {
    "iso:country": "GB",
    "wof:name": "CT9 2RY",
    "wof:placetype": "postalcode"
  },
  "geometry": {"coordinates":[1.404926,51.383951],"type":"Point"}
}
