{
  "type": "Feature",
  "properties": {
    "iso:country": "GB",
    "wof:name": "BH24 2FB",
    "wof:placetype": "postalcode"
  },
  "geometry": {"coordinates":[-1.855035,50.817914],"type":"Point"}
}
