{
  "type": "Feature",
  "properties": {
    "iso:country": "GB",
    "wof:name": "CW5 6XN",
    "wof:placetype": "postalcode"
  },
  "geometry": {"coordinates":[-2.527153,53.074724],"type":"Point"}
}
