{
  "type": "Feature",
  "properties": {
    "iso:country": "GB",
    "wof:name": "AB54 4GE",
    "wof:placetype": "postalcode"
  },
  "geometry": {"coordinates":[-2.837952,57.332918],"type":"Point"}
}
