{
  "type": "Feature",
  "properties": {
    "iso:country": "GB",
    "wof:name": "WS15 3FS",
    "wof:placetype": "postalcode"
  },
  "geometry": {"coordinates":[-1.876388,52.757824],"type":"Point"}
}
