{
  "type": "Feature",
  "properties": {
    "iso:country": "GB",
    "wof:name": "RH2 8FL",
    "wof:placetype": "postalcode"
  },
  "geometry": {"coordinates":[-0.210981,51.223009],"type":"Point"}
}
