{
  "type": "Feature",
  "properties": {
    "iso:country": "GB",
    "wof:name": "YO25 4AF",
    "wof:placetype": "postalcode"
  },
  "geometry": {"coordinates":[-0.333852,54.0402],"type":"Point"}
}
