{
  "type": "Feature",
  "properties": {
    "iso:country": "GB",
    "wof:name": "BB2 2BG",
    "wof:placetype": "postalcode"
  },
  "geometry": {"coordinates":[-2.482288,53.746418],"type":"Point"}
}
