{
  "type": "Feature",
  "properties": {
    "iso:country": "GB",
    "wof:name": "MK4 4EA",
    "wof:placetype": "postalcode"
  },
  "geometry": {"coordinates":[-0.80612,52.002167],"type":"Point"}
}
