{
  "type": "Feature",
  "properties": {
    "iso:country": "GB",
    "wof:name": "HG1 5FH",
    "wof:placetype": "postalcode"
  },
  "geometry": {"coordinates":[-1.535108,53.996291],"type":"Point"}
}
