{
  "type": "Feature",
  "properties": {
    "iso:country": "GB",
    "wof:name": "NE63 9WS",
    "wof:placetype": "postalcode"
  },
  "geometry": {"coordinates":[-1.547409,55.179493],"type":"Point"}
}
