{
  "type": "Feature",
  "properties": {
    "iso:country": "GB",
    "wof:name": "CT16 3QA",
    "wof:placetype": "postalcode"
  },
  "geometry": {"coordinates":[1.262585,51.147388],"type":"Point"}
}
