{
  "type": "Feature",
  "properties": {
    "iso:country": "GB",
    "wof:name": "S41 9RL",
    "wof:placetype": "postalcode"
  },
  "geometry": {"coordinates":[-1.45425,53.266273],"type":"Point"}
}
