{
  "type": "Feature",
  "properties": {
    "iso:country": "GB",
    "wof:name": "TA9 3SP",
    "wof:placetype": "postalcode"
  },
  "geometry": {"coordinates":[-2.983324,51.221843],"type":"Point"}
}
