{
  "type": "Feature",
  "properties": {
    "iso:country": "GB",
    "wof:name": "NP16 5US",
    "wof:placetype": "postalcode"
  },
  "geometry": {"coordinates":[-2.68766,51.647668],"type":"Point"}
}
