{
  "type": "Feature",
  "properties": {
    "iso:country": "GB",
    "wof:name": "MK8 1EH",
    "wof:placetype": "postalcode"
  },
  "geometry": {"coordinates":[-0.813369,52.031066],"type":"Point"}
}
