{
  "type": "Feature",
  "properties": {
    "iso:country": "GB",
    "wof:name": "GL7 5TX",
    "wof:placetype": "postalcode"
  },
  "geometry": {"coordinates":[-1.932394,51.674122],"type":"Point"}
}
