{
  "type": "Feature",
  "properties": {
    "iso:country": "GB",
    "wof:name": "KT17 3FH",
    "wof:placetype": "postalcode"
  },
  "geometry": {"coordinates":[-0.243962,51.337366],"type":"Point"}
}
