{
  "type": "Feature",
  "properties": {
    "iso:country": "GB",
    "wof:name": "CW1 4UL",
    "wof:placetype": "postalcode"
  },
  "geometry": {"coordinates":[-2.46297,53.120575],"type":"Point"}
}
