{
  "type": "Feature",
  "properties": {
    "iso:country": "GB",
    "wof:name": "NE47 8AF",
    "wof:placetype": "postalcode"
  },
  "geometry": {"coordinates":[-2.30685,54.815197],"type":"Point"}
}
