{
  "type": "Feature",
  "properties": {
    "iso:country": "GB",
    "wof:name": "BD23 2DD",
    "wof:placetype": "postalcode"
  },
  "geometry": {"coordinates":[-2.01508,53.9422],"type":"Point"}
}
