{
  "type": "Feature",
  "properties": {
    "iso:country": "GB",
    "wof:name": "TS29 6FA",
    "wof:placetype": "postalcode"
  },
  "geometry": {"coordinates":[-1.424425,54.701739],"type":"Point"}
}
