{
  "type": "Feature",
  "properties": {
    "iso:country": "GB",
    "wof:name": "PO7 6GA",
    "wof:placetype": "postalcode"
  },
  "geometry": {"coordinates":[-1.061459,50.903638],"type":"Point"}
}
