{
  "type": "Feature",
  "properties": {
    "iso:country": "GB",
    "wof:name": "E13 9GJ",
    "wof:placetype": "postalcode"
  },
  "geometry": {"coordinates":[0.039468,51.532039],"type":"Point"}
}
