{
  "type": "Feature",
  "properties": {
    "iso:country": "GB",
    "wof:name": "AL7 1WL",
    "wof:placetype": "postalcode"
  },
  "geometry": {"coordinates":[-0.191238,51.800722],"type":"Point"}
}
