{
  "type": "Feature",
  "properties": {
    "iso:country": "GB",
    "wof:name": "IP14 5PD",
    "wof:placetype": "postalcode"
  },
  "geometry": {"coordinates":[1.102109,52.259549],"type":"Point"}
}
