{
  "type": "Feature",
  "properties": {
    "iso:country": "GB",
    "wof:name": "B70 8AU",
    "wof:placetype": "postalcode"
  },
  "geometry": {"coordinates":[-1.99771,52.523471],"type":"Point"}
}
