{
  "type": "Feature",
  "properties": {
    "iso:country": "GB",
    "wof:name": "CR0 5RD",
    "wof:placetype": "postalcode"
  },
  "geometry": {"coordinates":[-0.071461,51.363763],"type":"Point"}
}
