{
  "type": "Feature",
  "properties": {
    "iso:country": "GB",
    "wof:name": "EN8 8JH",
    "wof:placetype": "postalcode"
  },
  "geometry": {"coordinates":[-0.034132,51.696961],"type":"Point"}
}
