{
  "type": "Feature",
  "properties": {
    "iso:country": "GB",
    "wof:name": "CV3 2DB",
    "wof:placetype": "postalcode"
  },
  "geometry": {"coordinates":[-1.415542,52.392349],"type":"Point"}
}
