{
  "type": "Feature",
  "properties": {
    "iso:country": "GB",
    "wof:name": "SN10 5TE",
    "wof:placetype": "postalcode"
  },
  "geometry": {"coordinates":[-2.026282,51.33098],"type":"Point"}
}
