{
  "type": "Feature",
  "properties": {
    "iso:country": "GB",
    "wof:name": "W2 6EP",
    "wof:placetype": "postalcode"
  },
  "geometry": {"coordinates":[-0.179217,51.519289],"type":"Point"}
}
