{
  "type": "Feature",
  "properties": {
    "iso:country": "GB",
    "wof:name": "DT4 9GX",
    "wof:placetype": "postalcode"
  },
  "geometry": {"coordinates":[-2.481075,50.597442],"type":"Point"}
}
