{
  "type": "Feature",
  "properties": {
    "iso:country": "GB",
    "wof:name": "EX17 3FF",
    "wof:placetype": "postalcode"
  },
  "geometry": {"coordinates":[-3.642215,50.785011],"type":"Point"}
}
