{
  "type": "Feature",
  "properties": {
    "iso:country": "GB",
    "wof:name": "YO10 4FR",
    "wof:placetype": "postalcode"
  },
  "geometry": {"coordinates":[-1.078553,53.938205],"type":"Point"}
}
