{
  "type": "Feature",
  "properties": {
    "iso:country": "GB",
    "wof:name": "LL65 2YZ",
    "wof:placetype": "postalcode"
  },
  "geometry": {"coordinates":[-4.612135,53.277904],"type":"Point"}
}
