{
  "type": "Feature",
  "properties": {
    "iso:country": "GB",
    "wof:name": "FK4 1AW",
    "wof:placetype": "postalcode"
  },
  "geometry": {"coordinates":[-3.881709,56.003514],"type":"Point"}
}
