{
  "type": "Feature",
  "properties": {
    "iso:country": "GB",
    "wof:name": "NN9 5GX",
    "wof:placetype": "postalcode"
  },
  "geometry": {"coordinates":[-0.599833,52.329586],"type":"Point"}
}
