{
  "type": "Feature",
  "properties": {
    "iso:country": "GB",
    "wof:name": "AL1 2DE",
    "wof:placetype": "postalcode"
  },
  "geometry": {"coordinates":[-0.342706,51.743912],"type":"Point"}
}
