{
  "type": "Feature",
  "properties": {
    "iso:country": "GB",
    "wof:name": "SY2 6RJ",
    "wof:placetype": "postalcode"
  },
  "geometry": {"coordinates":[-2.742133,52.687339],"type":"Point"}
}
