{
  "type": "Feature",
  "properties": {
    "iso:country": "GB",
    "wof:name": "ME3 8GN",
    "wof:placetype": "postalcode"
  },
  "geometry": {"coordinates":[0.567234,51.45263],"type":"Point"}
}
