{
  "type": "Feature",
  "properties": {
    "iso:country": "GB",
    "wof:name": "ST10 3BB",
    "wof:placetype": "postalcode"
  },
  "geometry": {"coordinates":[-1.918301,53.000744],"type":"Point"}
}
