{
  "type": "Feature",
  "properties": {
    "iso:country": "GB",
    "wof:name": "M38 9AQ",
    "wof:placetype": "postalcode"
  },
  "geometry": {"coordinates":[-2.42224,53.535916],"type":"Point"}
}
