{
  "type": "Feature",
  "properties": {
    "iso:country": "GB",
    "wof:name": "PE1 1EN",
    "wof:placetype": "postalcode"
  },
  "geometry": {"coordinates":[-0.241462,52.568907],"type":"Point"}
}
