{
  "type": "Feature",
  "properties": {
    "iso:country": "GB",
    "wof:name": "HD7 5AP",
    "wof:placetype": "postalcode"
  },
  "geometry": {"coordinates":[-1.881688,53.622521],"type":"Point"}
}
