{
  "type": "Feature",
  "properties": {
    "iso:country": "GB",
    "wof:name": "GU28 9BA",
    "wof:placetype": "postalcode"
  },
  "geometry": {"coordinates":[-0.638597,51.001464],"type":"Point"}
}
