{
  "type": "Feature",
  "properties": {
    "iso:country": "GB",
    "wof:name": "ME5 0FD",
    "wof:placetype": "postalcode"
  },
  "geometry": {"coordinates":[0.538082,51.365847],"type":"Point"}
}
