{
  "type": "Feature",
  "properties": {
    "iso:country": "GB",
    "wof:name": "SG4 8BS",
    "wof:placetype": "postalcode"
  },
  "geometry": {"coordinates":[-0.286883,51.875825],"type":"Point"}
}
