{
  "type": "Feature",
  "properties": {
    "iso:country": "GB",
    "wof:name": "SK1 3GG",
    "wof:placetype": "postalcode"
  },
  "geometry": {"coordinates":[-2.161359,53.40596],"type":"Point"}
}
