{
  "type": "Feature",
  "properties": {
    "iso:country": "GB",
    "wof:name": "DN3 3AE",
    "wof:placetype": "postalcode"
  },
  "geometry": {"coordinates":[-1.054118,53.535534],"type":"Point"}
}
