{
  "type": "Feature",
  "properties": {
    "iso:country": "GB",
    "wof:name": "CM12 9FX",
    "wof:placetype": "postalcode"
  },
  "geometry": {"coordinates":[0.417589,51.625085],"type":"Point"}
}
