{
  "type": "Feature",
  "properties": {
    "iso:country": "GB",
    "wof:name": "YO7 2AL",
    "wof:placetype": "postalcode"
  },
  "geometry": {"coordinates":[-1.256742,54.215144],"type":"Point"}
}
