{
  "type": "Feature",
  "properties": {
    "iso:country": "GB",
    "wof:name": "ME9 7FY",
    "wof:placetype": "postalcode"
  },
  "geometry": {"coordinates":[0.685642,51.359598],"type":"Point"}
}
