{
  "type": "Feature",
  "properties": {
    "iso:country": "GB",
    "wof:name": "DT2 7RW",
    "wof:placetype": "postalcode"
  },
  "geometry": {"coordinates":[-2.426735,50.820164],"type":"Point"}
}
