{
  "type": "Feature",
  "properties": {
    "iso:country": "GB",
    "wof:name": "BS34 5TN",
    "wof:placetype": "postalcode"
  },
  "geometry": {"coordinates":[-2.587986,51.523513],"type":"Point"}
}
