{
  "type": "Feature",
  "properties": {
    "iso:country": "GB",
    "wof:name": "G22 7UP",
    "wof:placetype": "postalcode"
  },
  "geometry": {"coordinates":[-4.259921,55.898641],"type":"Point"}
}
