{
  "type": "Feature",
  "properties": {
    "iso:country": "GB",
    "wof:name": "LN4 1FA",
    "wof:placetype": "postalcode"
  },
  "geometry": {"coordinates":[-0.471017,53.190606],"type":"Point"}
}
