{
  "type": "Feature",
  "properties": {
    "iso:country": "GB",
    "wof:name": "BL2 1DG",
    "wof:placetype": "postalcode"
  },
  "geometry": {"coordinates":[-2.421044,53.575028],"type":"Point"}
}
