{
  "type": "Feature",
  "properties": {
    "iso:country": "GB",
    "wof:name": "CA10 1SG",
    "wof:placetype": "postalcode"
  },
  "geometry": {"coordinates":[-2.611139,54.657067],"type":"Point"}
}
