{
  "type": "Feature",
  "properties": {
    "iso:country": "GB",
    "wof:name": "OX25 2DG",
    "wof:placetype": "postalcode"
  },
  "geometry": {"coordinates":[-1.112131,51.871279],"type":"Point"}
}
