{
  "type": "Feature",
  "properties": {
    "iso:country": "GB",
    "wof:name": "EH42 1XX",
    "wof:placetype": "postalcode"
  },
  "geometry": {"coordinates":[-2.5326,55.991952],"type":"Point"}
}
