{
  "type": "Feature",
  "properties": {
    "iso:country": "GB",
    "wof:name": "KY15 7BH",
    "wof:placetype": "postalcode"
  },
  "geometry": {"coordinates":[-3.20953,56.25233],"type":"Point"}
}
