{
  "type": "Feature",
  "properties": {
    "iso:country": "GB",
    "wof:name": "TN18 5LQ",
    "wof:placetype": "postalcode"
  },
  "geometry": {"coordinates":[0.558578,51.026582],"type":"Point"}
}
