{
  "type": "Feature",
  "properties": {
    "iso:country": "GB",
    "wof:name": "DD4 9FS",
    "wof:placetype": "postalcode"
  },
  "geometry": {"coordinates":[-2.957912,56.490333],"type":"Point"}
}
