{
  "type": "Feature",
  "properties": {
    "iso:country": "GB",
    "wof:name": "IP14 3GA",
    "wof:placetype": "postalcode"
  },
  "geometry": {"coordinates":[0.966302,52.219729],"type":"Point"}
}
