{
  "type": "Feature",
  "properties": {
    "iso:country": "GB",
    "wof:name": "EC2M 2AT",
    "wof:placetype": "postalcode"
  },
  "geometry": {"coordinates":[-0.083408,51.517889],"type":"Point"}
}
