{
  "type": "Feature",
  "properties": {
    "iso:country": "GB",
    "wof:name": "WA5 3UL",
    "wof:placetype": "postalcode"
  },
  "geometry": {"coordinates":[-2.652633,53.404131],"type":"Point"}
}
