{
  "type": "Feature",
  "properties": {
    "iso:country": "GB",
    "wof:name": "IP6 0HJ",
    "wof:placetype": "postalcode"
  },
  "geometry": {"coordinates":[1.152696,52.099222],"type":"Point"}
}
