{
  "type": "Feature",
  "properties": {
    "iso:country": "GB",
    "wof:name": "SO31 8ND",
    "wof:placetype": "postalcode"
  },
  "geometry": {"coordinates":[-1.311581,50.89198],"type":"Point"}
}
