{
  "type": "Feature",
  "properties": {
    "iso:country": "GB",
    "wof:name": "CH1 6FE",
    "wof:placetype": "postalcode"
  },
  "geometry": {"coordinates":[-2.918833,53.21725],"type":"Point"}
}
