{
  "type": "Feature",
  "properties": {
    "iso:country": "GB",
    "wof:name": "WV6 0LY",
    "wof:placetype": "postalcode"
  },
  "geometry": {"coordinates":[-2.16088,52.595271],"type":"Point"}
}
