{
  "type": "Feature",
  "properties": {
    "iso:country": "GB",
    "wof:name": "SK17 6GP",
    "wof:placetype": "postalcode"
  },
  "geometry": {"coordinates":[-1.911677,53.260951],"type":"Point"}
}
