{
  "type": "Feature",
  "properties": {
    "iso:country": "GB",
    "wof:name": "WA1 1QB",
    "wof:placetype": "postalcode"
  },
  "geometry": {"coordinates":[-2.594715,53.389567],"type":"Point"}
}
