{
  "type": "Feature",
  "properties": {
    "iso:country": "GB",
    "wof:name": "BH16 6FX",
    "wof:placetype": "postalcode"
  },
  "geometry": {"coordinates":[-2.086413,50.729493],"type":"Point"}
}
