{
  "type": "Feature",
  "properties": {
    "iso:country": "GB",
    "wof:name": "NG17 3DR",
    "wof:placetype": "postalcode"
  },
  "geometry": {"coordinates":[-1.251759,53.140325],"type":"Point"}
}
