{
  "type": "Feature",
  "properties": {
    "iso:country": "GB",
    "wof:name": "G74 4XX",
    "wof:placetype": "postalcode"
  },
  "geometry": {"coordinates":[-4.17548,55.765722],"type":"Point"}
}
