{
  "type": "Feature",
  "properties": {
    "iso:country": "GB",
    "wof:name": "DH6 2JH",
    "wof:placetype": "postalcode"
  },
  "geometry": {"coordinates":[-1.40191,54.767089],"type":"Point"}
}
