{
  "type": "Feature",
  "properties": {
    "iso:country": "GB",
    "wof:name": "CM3 2FE",
    "wof:placetype": "postalcode"
  },
  "geometry": {"coordinates":[0.615677,51.771021],"type":"Point"}
}
