{
  "type": "Feature",
  "properties": {
    "iso:country": "GB",
    "wof:name": "RG45 6PX",
    "wof:placetype": "postalcode"
  },
  "geometry": {"coordinates":[-0.78719,51.378313],"type":"Point"}
}
