{
  "type": "Feature",
  "properties": {
    "iso:country": "GB",
    "wof:name": "PE6 0FR",
    "wof:placetype": "postalcode"
  },
  "geometry": {"coordinates":[-0.092886,52.618153],"type":"Point"}
}
