{
  "type": "Feature",
  "properties": {
    "iso:country": "GB",
    "wof:name": "WA15 0NU",
    "wof:placetype": "postalcode"
  },
  "geometry": {"coordinates":[-2.327118,53.36643],"type":"Point"}
}
