{
  "type": "Feature",
  "properties": {
    "iso:country": "GB",
    "wof:name": "M22 9SB",
    "wof:placetype": "postalcode"
  },
  "geometry": {"coordinates":[-2.259536,53.398083],"type":"Point"}
}
