{
  "type": "Feature",
  "properties": {
    "iso:country": "GB",
    "wof:name": "HP5 1EP",
    "wof:placetype": "postalcode"
  },
  "geometry": {"coordinates":[-0.613045,51.704801],"type":"Point"}
}
