{
  "type": "Feature",
  "properties": {
    "iso:country": "GB",
    "wof:name": "DE3 0FR",
    "wof:placetype": "postalcode"
  },
  "geometry": {"coordinates":[-1.548442,52.918455],"type":"Point"}
}
