{
  "type": "Feature",
  "properties": {
    "iso:country": "GB",
    "wof:name": "PE2 8WW",
    "wof:placetype": "postalcode"
  },
  "geometry": {"coordinates":[-0.210489,52.547863],"type":"Point"}
}
