{
  "type": "Feature",
  "properties": {
    "iso:country": "GB",
    "wof:name": "RM16 3DP",
    "wof:placetype": "postalcode"
  },
  "geometry": {"coordinates":[0.398593,51.506422],"type":"Point"}
}
