{
  "type": "Feature",
  "properties": {
    "iso:country": "GB",
    "wof:name": "IP20 0NL",
    "wof:placetype": "postalcode"
  },
  "geometry": {"coordinates":[1.339608,52.399014],"type":"Point"}
}
