{
  "type": "Feature",
  "properties": {
    "iso:country": "GB",
    "wof:name": "CO7 7FZ",
    "wof:placetype": "postalcode"
  },
  "geometry": {"coordinates":[1.000817,51.879467],"type":"Point"}
}
