{
  "type": "Feature",
  "properties": {
    "iso:country": "GB",
    "wof:name": "LE7 9XY",
    "wof:placetype": "postalcode"
  },
  "geometry": {"coordinates":[-1.035504,52.649013],"type":"Point"}
}
