{
  "type": "Feature",
  "properties": {
    "iso:country": "GB",
    "wof:name": "SP6 2RA",
    "wof:placetype": "postalcode"
  },
  "geometry": {"coordinates":[-1.74489,50.959205],"type":"Point"}
}
