{
  "type": "Feature",
  "properties": {
    "iso:country": "GB",
    "wof:name": "DE65 6RZ",
    "wof:placetype": "postalcode"
  },
  "geometry": {"coordinates":[-1.594862,52.878386],"type":"Point"}
}
