{
  "type": "Feature",
  "properties": {
    "iso:country": "GB",
    "wof:name": "WS6 6BG",
    "wof:placetype": "postalcode"
  },
  "geometry": {"coordinates":[-2.013686,52.66284],"type":"Point"}
}
