{
  "type": "Feature",
  "properties": {
    "iso:country": "GB",
    "wof:name": "IP22 1RD",
    "wof:placetype": "postalcode"
  },
  "geometry": {"coordinates":[1.0434,52.354116],"type":"Point"}
}
