{
  "type": "Feature",
  "properties": {
    "iso:country": "GB",
    "wof:name": "M90 5TE",
    "wof:placetype": "postalcode"
  },
  "geometry": {"coordinates":[-2.290401,53.363658],"type":"Point"}
}
