{
  "type": "Feature",
  "properties": {
    "iso:country": "GB",
    "wof:name": "CT18 7UE",
    "wof:placetype": "postalcode"
  },
  "geometry": {"coordinates":[1.166256,51.117564],"type":"Point"}
}
