{
  "type": "Feature",
  "properties": {
    "iso:country": "GB",
    "wof:name": "NW7 3HR",
    "wof:placetype": "postalcode"
  },
  "geometry": {"coordinates":[-0.25506,51.626417],"type":"Point"}
}
