{
  "type": "Feature",
  "properties": {
    "iso:country": "GB",
    "wof:name": "YO61 3RH",
    "wof:placetype": "postalcode"
  },
  "geometry": {"coordinates":[-1.184491,54.12215],"type":"Point"}
}
