{
  "type": "Feature",
  "properties": {
    "iso:country": "GB",
    "wof:name": "NG20 9LT",
    "wof:placetype": "postalcode"
  },
  "geometry": {"coordinates":[-1.137472,53.237338],"type":"Point"}
}
