{
  "type": "Feature",
  "properties": {
    "iso:country": "GB",
    "wof:name": "CO7 0FT",
    "wof:placetype": "postalcode"
  },
  "geometry": {"coordinates":[1.037001,51.812396],"type":"Point"}
}
