{
  "type": "Feature",
  "properties": {
    "iso:country": "GB",
    "wof:name": "DE5 3TT",
    "wof:placetype": "postalcode"
  },
  "geometry": {"coordinates":[-1.403068,53.04042],"type":"Point"}
}
