{
  "type": "Feature",
  "properties": {
    "iso:country": "GB",
    "wof:name": "TS16 0RD",
    "wof:placetype": "postalcode"
  },
  "geometry": {"coordinates":[-1.354187,54.530788],"type":"Point"}
}
