{
  "type": "Feature",
  "properties": {
    "iso:country": "GB",
    "wof:name": "SG10 6JQ",
    "wof:placetype": "postalcode"
  },
  "geometry": {"coordinates":[0.098771,51.85108],"type":"Point"}
}
