{
  "type": "Feature",
  "properties": {
    "iso:country": "GB",
    "wof:name": "SY8 1JU",
    "wof:placetype": "postalcode"
  },
  "geometry": {"coordinates":[-2.70237,52.363327],"type":"Point"}
}
