{
  "type": "Feature",
  "properties": {
    "iso:country": "GB",
    "wof:name": "DT1 3FE",
    "wof:placetype": "postalcode"
  },
  "geometry": {"coordinates":[-2.460211,50.717807],"type":"Point"}
}
