{
  "type": "Feature",
  "properties": {
    "iso:country": "GB",
    "wof:name": "EX6 8AA",
    "wof:placetype": "postalcode"
  },
  "geometry": {"coordinates":[-3.503701,50.689121],"type":"Point"}
}
