{
  "type": "Feature",
  "properties": {
    "iso:country": "GB",
    "wof:name": "BN3 2RP",
    "wof:placetype": "postalcode"
  },
  "geometry": {"coordinates":[-0.173883,50.825753],"type":"Point"}
}
