{
  "type": "Feature",
  "properties": {
    "iso:country": "GB",
    "wof:name": "SP7 8TJ",
    "wof:placetype": "postalcode"
  },
  "geometry": {"coordinates":[-2.19049,51.01714],"type":"Point"}
}
