{
  "type": "Feature",
  "properties": {
    "iso:country": "GB",
    "wof:name": "CH66 7NT",
    "wof:placetype": "postalcode"
  },
  "geometry": {"coordinates":[-2.981744,53.295619],"type":"Point"}
}
