{
  "type": "Feature",
  "properties": {
    "iso:country": "GB",
    "wof:name": "BA2 6BN",
    "wof:placetype": "postalcode"
  },
  "geometry": {"coordinates":[-2.343098,51.389754],"type":"Point"}
}
