{
  "type": "Feature",
  "properties": {
    "iso:country": "GB",
    "wof:name": "N4 1RT",
    "wof:placetype": "postalcode"
  },
  "geometry": {"coordinates":[-0.102584,51.578406],"type":"Point"}
}
