{
  "type": "Feature",
  "properties": {
    "iso:country": "GB",
    "wof:name": "CF15 7UZ",
    "wof:placetype": "postalcode"
  },
  "geometry": {"coordinates":[-3.262656,51.562532],"type":"Point"}
}
