{
  "type": "Feature",
  "properties": {
    "iso:country": "GB",
    "wof:name": "NR34 7LN",
    "wof:placetype": "postalcode"
  },
  "geometry": {"coordinates":[1.719195,52.395156],"type":"Point"}
}
