{
  "type": "Feature",
  "properties": {
    "iso:country": "GB",
    "wof:name": "NE66 3FF",
    "wof:placetype": "postalcode"
  },
  "geometry": {"coordinates":[-1.619785,55.429909],"type":"Point"}
}
