{
  "type": "Feature",
  "properties": {
    "iso:country": "GB",
    "wof:name": "WN8 0HG",
    "wof:placetype": "postalcode"
  },
  "geometry": {"coordinates":[-2.72698,53.542316],"type":"Point"}
}
