{
  "type": "Feature",
  "properties": {
    "iso:country": "GB",
    "wof:name": "HU12 8QN",
    "wof:placetype": "postalcode"
  },
  "geometry": {"coordinates":[-0.215232,53.740501],"type":"Point"}
}
