{
  "type": "Feature",
  "properties": {
    "iso:country": "GB",
    "wof:name": "BN27 3PQ",
    "wof:placetype": "postalcode"
  },
  "geometry": {"coordinates":[0.242704,50.846253],"type":"Point"}
}
