{
  "type": "Feature",
  "properties": {
    "iso:country": "GB",
    "wof:name": "FY5 3UP",
    "wof:placetype": "postalcode"
  },
  "geometry": {"coordinates":[-3.018082,53.866437],"type":"Point"}
}
