{
  "type": "Feature",
  "properties": {
    "iso:country": "GB",
    "wof:name": "SS15 5PS",
    "wof:placetype": "postalcode"
  },
  "geometry": {"coordinates":[0.42351,51.575366],"type":"Point"}
}
