{
  "type": "Feature",
  "properties": {
    "iso:country": "GB",
    "wof:name": "SO51 0DF",
    "wof:placetype": "postalcode"
  },
  "geometry": {"coordinates":[-1.465188,51.005318],"type":"Point"}
}
