{
  "type": "Feature",
  "properties": {
    "iso:country": "GB",
    "wof:name": "CO10 9SS",
    "wof:placetype": "postalcode"
  },
  "geometry": {"coordinates":[0.795379,52.104024],"type":"Point"}
}
