{
  "type": "Feature",
  "properties": {
    "iso:country": "GB",
    "wof:name": "G61 3EG",
    "wof:placetype": "postalcode"
  },
  "geometry": {"coordinates":[-4.313734,55.93146],"type":"Point"}
}
