{
  "type": "Feature",
  "properties": {
    "iso:country": "GB",
    "wof:name": "CV23 1DS",
    "wof:placetype": "postalcode"
  },
  "geometry": {"coordinates":[-1.206434,52.368097],"type":"Point"}
}
