{
  "type": "Feature",
  "properties": {
    "iso:country": "GB",
    "wof:name": "NW9 4ES",
    "wof:placetype": "postalcode"
  },
  "geometry": {"coordinates":[-0.245283,51.593693],"type":"Point"}
}
