{
  "type": "Feature",
  "properties": {
    "iso:country": "GB",
    "wof:name": "GL52 5GR",
    "wof:placetype": "postalcode"
  },
  "geometry": {"coordinates":[-2.040278,51.902015],"type":"Point"}
}
