{
  "type": "Feature",
  "properties": {
    "iso:country": "GB",
    "wof:name": "NG2 4RP",
    "wof:placetype": "postalcode"
  },
  "geometry": {"coordinates":[-1.12203,52.944165],"type":"Point"}
}
