{
  "type": "Feature",
  "properties": {
    "iso:country": "GB",
    "wof:name": "LE1 5AZ",
    "wof:placetype": "postalcode"
  },
  "geometry": {"coordinates":[-1.137808,52.633925],"type":"Point"}
}
