{
  "type": "Feature",
  "properties": {
    "iso:country": "GB",
    "wof:name": "BD20 8EW",
    "wof:placetype": "postalcode"
  },
  "geometry": {"coordinates":[-2.004426,53.900659],"type":"Point"}
}
