{
  "type": "Feature",
  "properties": {
    "iso:country": "GB",
    "wof:name": "CM7 5FW",
    "wof:placetype": "postalcode"
  },
  "geometry": {"coordinates":[0.577575,51.909334],"type":"Point"}
}
