{
  "type": "Feature",
  "properties": {
    "iso:country": "GB",
    "wof:name": "ML7 5TJ",
    "wof:placetype": "postalcode"
  },
  "geometry": {"coordinates":[-3.810535,55.855721],"type":"Point"}
}
