{
  "type": "Feature",
  "properties": {
    "iso:country": "GB",
    "wof:name": "PE20 1PZ",
    "wof:placetype": "postalcode"
  },
  "geometry": {"coordinates":[-0.061858,52.920827],"type":"Point"}
}
