{
  "type": "Feature",
  "properties": {
    "iso:country": "GB",
    "wof:name": "HU12 8TE",
    "wof:placetype": "postalcode"
  },
  "geometry": {"coordinates":[-0.209813,53.755612],"type":"Point"}
}
