{
  "type": "Feature",
  "properties": {
    "iso:country": "GB",
    "wof:name": "PR5 4DF",
    "wof:placetype": "postalcode"
  },
  "geometry": {"coordinates":[-2.669464,53.73787],"type":"Point"}
}
