{
  "type": "Feature",
  "properties": {
    "iso:country": "GB",
    "wof:name": "M12 5NF",
    "wof:placetype": "postalcode"
  },
  "geometry": {"coordinates":[-2.20094,53.467875],"type":"Point"}
}
