{
  "type": "Feature",
  "properties": {
    "iso:country": "GB",
    "wof:name": "MK11 4DL",
    "wof:placetype": "postalcode"
  },
  "geometry": {"coordinates":[-0.84001,52.046518],"type":"Point"}
}
