{
  "type": "Feature",
  "properties": {
    "iso:country": "GB",
    "wof:name": "NR13 4TY",
    "wof:placetype": "postalcode"
  },
  "geometry": {"coordinates":[1.440242,52.634429],"type":"Point"}
}
