{
  "type": "Feature",
  "properties": {
    "iso:country": "GB",
    "wof:name": "NR25 7BB",
    "wof:placetype": "postalcode"
  },
  "geometry": {"coordinates":[1.059516,52.939868],"type":"Point"}
}
