{
  "type": "Feature",
  "properties": {
    "iso:country": "GB",
    "wof:name": "B43 7EY",
    "wof:placetype": "postalcode"
  },
  "geometry": {"coordinates":[-1.912007,52.552233],"type":"Point"}
}
