{
  "type": "Feature",
  "properties": {
    "iso:country": "GB",
    "wof:name": "EX31 3UL",
    "wof:placetype": "postalcode"
  },
  "geometry": {"coordinates":[-4.09149,51.063172],"type":"Point"}
}
