{
  "type": "Feature",
  "properties": {
    "iso:country": "GB",
    "wof:name": "DL7 8NW",
    "wof:placetype": "postalcode"
  },
  "geometry": {"coordinates":[-1.449461,54.335556],"type":"Point"}
}
