{
  "type": "Feature",
  "properties": {
    "iso:country": "GB",
    "wof:name": "CW4 8AB",
    "wof:placetype": "postalcode"
  },
  "geometry": {"coordinates":[-2.346059,53.200202],"type":"Point"}
}
