{
  "type": "Feature",
  "properties": {
    "iso:country": "GB",
    "wof:name": "TR20 9ED",
    "wof:placetype": "postalcode"
  },
  "geometry": {"coordinates":[-5.415942,50.130654],"type":"Point"}
}
