{
  "type": "Feature",
  "properties": {
    "iso:country": "GB",
    "wof:name": "SR7 9AG",
    "wof:placetype": "postalcode"
  },
  "geometry": {"coordinates":[-1.384395,54.818189],"type":"Point"}
}
