{
  "type": "Feature",
  "properties": {
    "iso:country": "GB",
    "wof:name": "PA16 0PW",
    "wof:placetype": "postalcode"
  },
  "geometry": {"coordinates":[-4.822349,55.946342],"type":"Point"}
}
