{
  "type": "Feature",
  "properties": {
    "iso:country": "GB",
    "wof:name": "IG10 4FE",
    "wof:placetype": "postalcode"
  },
  "geometry": {"coordinates":[0.020396,51.652493],"type":"Point"}
}
