{
  "type": "Feature",
  "properties": {
    "iso:country": "GB",
    "wof:name": "CA13 9FR",
    "wof:placetype": "postalcode"
  },
  "geometry": {"coordinates":[-3.365093,54.660323],"type":"Point"}
}
