{
  "type": "Feature",
  "properties": {
    "iso:country": "GB",
    "wof:name": "LN11 0EB",
    "wof:placetype": "postalcode"
  },
  "geometry": {"coordinates":[-0.014179,53.373852],"type":"Point"}
}
