{
  "type": "Feature",
  "properties": {
    "iso:country": "GB",
    "wof:name": "TN22 5HL",
    "wof:placetype": "postalcode"
  },
  "geometry": {"coordinates":[0.181888,50.961564],"type":"Point"}
}
