{
  "type": "Feature",
  "properties": {
    "iso:country": "GB",
    "wof:name": "WR5 1TD",
    "wof:placetype": "postalcode"
  },
  "geometry": {"coordinates":[-2.174686,52.183321],"type":"Point"}
}
