{
  "type": "Feature",
  "properties": {
    "iso:country": "GB",
    "wof:name": "OX9 2AJ",
    "wof:placetype": "postalcode"
  },
  "geometry": {"coordinates":[-0.994078,51.746481],"type":"Point"}
}
