{
  "type": "Feature",
  "properties": {
    "iso:country": "GB",
    "wof:name": "LS2 9BZ",
    "wof:placetype": "postalcode"
  },
  "geometry": {"coordinates":[-1.560011,53.804035],"type":"Point"}
}
