{
  "type": "Feature",
  "properties": {
    "iso:country": "GB",
    "wof:name": "BD14 6EE",
    "wof:placetype": "postalcode"
  },
  "geometry": {"coordinates":[-1.807588,53.786845],"type":"Point"}
}
