{
  "type": "Feature",
  "properties": {
    "iso:country": "GB",
    "wof:name": "SK5 7FT",
    "wof:placetype": "postalcode"
  },
  "geometry": {"coordinates":[-2.160589,53.437421],"type":"Point"}
}
