{
  "type": "Feature",
  "properties": {
    "iso:country": "GB",
    "wof:name": "KY6 3JH",
    "wof:placetype": "postalcode"
  },
  "geometry": {"coordinates":[-3.284542,56.198157],"type":"Point"}
}
