{
  "type": "Feature",
  "properties": {
    "iso:country": "GB",
    "wof:name": "EX20 1GS",
    "wof:placetype": "postalcode"
  },
  "geometry": {"coordinates":[-4.001558,50.738512],"type":"Point"}
}
