{
  "type": "Feature",
  "properties": {
    "iso:country": "GB",
    "wof:name": "PR3 3RB",
    "wof:placetype": "postalcode"
  },
  "geometry": {"coordinates":[-2.595434,53.832895],"type":"Point"}
}
