{
  "type": "Feature",
  "properties": {
    "iso:country": "GB",
    "wof:name": "HD7 4FB",
    "wof:placetype": "postalcode"
  },
  "geometry": {"coordinates":[-1.859798,53.640232],"type":"Point"}
}
