{
  "type": "Feature",
  "properties": {
    "iso:country": "GB",
    "wof:name": "PO21 5FX",
    "wof:placetype": "postalcode"
  },
  "geometry": {"coordinates":[-0.702334,50.801851],"type":"Point"}
}
