{
  "type": "Feature",
  "properties": {
    "iso:country": "GB",
    "wof:name": "CT18 7UD",
    "wof:placetype": "postalcode"
  },
  "geometry": {"coordinates":[1.162811,51.117756],"type":"Point"}
}
