{
  "type": "Feature",
  "properties": {
    "iso:country": "GB",
    "wof:name": "EH19 2AB",
    "wof:placetype": "postalcode"
  },
  "geometry": {"coordinates":[-3.107052,55.876102],"type":"Point"}
}
