{
  "type": "Feature",
  "properties": {
    "iso:country": "GB",
    "wof:name": "SG15 6UW",
    "wof:placetype": "postalcode"
  },
  "geometry": {"coordinates":[-0.263239,52.024376],"type":"Point"}
}
