{
  "type": "Feature",
  "properties": {
    "iso:country": "GB",
    "wof:name": "NG15 6XJ",
    "wof:placetype": "postalcode"
  },
  "geometry": {"coordinates":[-1.222454,53.018756],"type":"Point"}
}
