{
  "type": "Feature",
  "properties": {
    "iso:country": "GB",
    "wof:name": "CO15 6EY",
    "wof:placetype": "postalcode"
  },
  "geometry": {"coordinates":[1.162412,51.799897],"type":"Point"}
}
