{
  "type": "Feature",
  "properties": {
    "iso:country": "GB",
    "wof:name": "SN11 0FW",
    "wof:placetype": "postalcode"
  },
  "geometry": {"coordinates":[-2.004173,51.430954],"type":"Point"}
}
