{
  "type": "Feature",
  "properties": {
    "iso:country": "GB",
    "wof:name": "OX29 7BH",
    "wof:placetype": "postalcode"
  },
  "geometry": {"coordinates":[-1.523834,51.783617],"type":"Point"}
}
