{
  "type": "Feature",
  "properties": {
    "iso:country": "GB",
    "wof:name": "RH12 3XQ",
    "wof:placetype": "postalcode"
  },
  "geometry": {"coordinates":[-0.441987,51.095781],"type":"Point"}
}
