{
  "type": "Feature",
  "properties": {
    "iso:country": "GB",
    "wof:name": "SW19 1PP",
    "wof:placetype": "postalcode"
  },
  "geometry": {"coordinates":[-0.197645,51.416814],"type":"Point"}
}
