{
  "type": "Feature",
  "properties": {
    "iso:country": "GB",
    "wof:name": "NE48 3NX",
    "wof:placetype": "postalcode"
  },
  "geometry": {"coordinates":[-2.167856,55.079231],"type":"Point"}
}
