{
  "type": "Feature",
  "properties": {
    "iso:country": "GB",
    "wof:name": "IG8 7JX",
    "wof:placetype": "postalcode"
  },
  "geometry": {"coordinates":[0.040314,51.603174],"type":"Point"}
}
