{
  "type": "Feature",
  "properties": {
    "iso:country": "GB",
    "wof:name": "RM15 4DJ",
    "wof:placetype": "postalcode"
  },
  "geometry": {"coordinates":[0.25134,51.499107],"type":"Point"}
}
