{
  "type": "Feature",
  "properties": {
    "iso:country": "GB",
    "wof:name": "WN6 0US",
    "wof:placetype": "postalcode"
  },
  "geometry": {"coordinates":[-2.684752,53.591634],"type":"Point"}
}
