{
  "type": "Feature",
  "properties": {
    "iso:country": "GB",
    "wof:name": "DN16 1DE",
    "wof:placetype": "postalcode"
  },
  "geometry": {"coordinates":[-0.628451,53.57712],"type":"Point"}
}
