{
  "type": "Feature",
  "properties": {
    "iso:country": "GB",
    "wof:name": "LE8 8EH",
    "wof:placetype": "postalcode"
  },
  "geometry": {"coordinates":[-1.03931,52.527065],"type":"Point"}
}
