{
  "type": "Feature",
  "properties": {
    "iso:country": "GB",
    "wof:name": "GL56 0NF",
    "wof:placetype": "postalcode"
  },
  "geometry": {"coordinates":[-1.688998,51.993852],"type":"Point"}
}
