{
  "type": "Feature",
  "properties": {
    "iso:country": "GB",
    "wof:name": "CF47 0EW",
    "wof:placetype": "postalcode"
  },
  "geometry": {"coordinates":[-3.372553,51.745534],"type":"Point"}
}
