{
  "type": "Feature",
  "properties": {
    "iso:country": "GB",
    "wof:name": "CW4 7FZ",
    "wof:placetype": "postalcode"
  },
  "geometry": {"coordinates":[-2.353306,53.193142],"type":"Point"}
}
