{
  "type": "Feature",
  "properties": {
    "iso:country": "GB",
    "wof:name": "DL8 2HP",
    "wof:placetype": "postalcode"
  },
  "geometry": {"coordinates":[-1.531475,54.261316],"type":"Point"}
}
