{
  "type": "Feature",
  "properties": {
    "iso:country": "GB",
    "wof:name": "BB11 3HB",
    "wof:placetype": "postalcode"
  },
  "geometry": {"coordinates":[-2.232077,53.781435],"type":"Point"}
}
