{
  "type": "Feature",
  "properties": {
    "iso:country": "GB",
    "wof:name": "BA11 5FN",
    "wof:placetype": "postalcode"
  },
  "geometry": {"coordinates":[-2.306175,51.221609],"type":"Point"}
}
