{
  "type": "Feature",
  "properties": {
    "iso:country": "GB",
    "wof:name": "PO11 9TX",
    "wof:placetype": "postalcode"
  },
  "geometry": {"coordinates":[-0.965494,50.787789],"type":"Point"}
}
