{
  "type": "Feature",
  "properties": {
    "iso:country": "GB",
    "wof:name": "DT3 6GB",
    "wof:placetype": "postalcode"
  },
  "geometry": {"coordinates":[-2.44626,50.642051],"type":"Point"}
}
