{
  "type": "Feature",
  "properties": {
    "iso:country": "GB",
    "wof:name": "RG42 5AN",
    "wof:placetype": "postalcode"
  },
  "geometry": {"coordinates":[-0.760045,51.431011],"type":"Point"}
}
