{
  "type": "Feature",
  "properties": {
    "iso:country": "GB",
    "wof:name": "DN5 9JQ",
    "wof:placetype": "postalcode"
  },
  "geometry": {"coordinates":[-1.161008,53.545185],"type":"Point"}
}
