{
  "type": "Feature",
  "properties": {
    "iso:country": "GB",
    "wof:name": "CA14 4JA",
    "wof:placetype": "postalcode"
  },
  "geometry": {"coordinates":[-3.529677,54.636904],"type":"Point"}
}
