{
  "type": "Feature",
  "properties": {
    "iso:country": "GB",
    "wof:name": "MK42 0PU",
    "wof:placetype": "postalcode"
  },
  "geometry": {"coordinates":[-0.424529,52.112846],"type":"Point"}
}
