{
  "type": "Feature",
  "properties": {
    "iso:country": "GB",
    "wof:name": "SL6 3TB",
    "wof:placetype": "postalcode"
  },
  "geometry": {"coordinates":[-0.789762,51.483341],"type":"Point"}
}
