{
  "type": "Feature",
  "properties": {
    "iso:country": "GB",
    "wof:name": "B42 2GR",
    "wof:placetype": "postalcode"
  },
  "geometry": {"coordinates":[-1.898267,52.524623],"type":"Point"}
}
