{
  "type": "Feature",
  "properties": {
    "iso:country": "GB",
    "wof:name": "FY4 2FJ",
    "wof:placetype": "postalcode"
  },
  "geometry": {"coordinates":[-3.023352,53.776266],"type":"Point"}
}
