{
  "type": "Feature",
  "properties": {
    "iso:country": "GB",
    "wof:name": "NG13 7AE",
    "wof:placetype": "postalcode"
  },
  "geometry": {"coordinates":[-0.961745,52.961293],"type":"Point"}
}
