{
  "type": "Feature",
  "properties": {
    "iso:country": "GB",
    "wof:name": "PE6 8LG",
    "wof:placetype": "postalcode"
  },
  "geometry": {"coordinates":[-0.318747,52.687818],"type":"Point"}
}
