{
  "type": "Feature",
  "properties": {
    "iso:country": "GB",
    "wof:name": "CW3 0FN",
    "wof:placetype": "postalcode"
  },
  "geometry": {"coordinates":[-2.507594,52.996764],"type":"Point"}
}
