{
  "type": "Feature",
  "properties": {
    "iso:country": "GB",
    "wof:name": "PL13 2FF",
    "wof:placetype": "postalcode"
  },
  "geometry": {"coordinates":[-4.526687,50.371929],"type":"Point"}
}
