{
  "type": "Feature",
  "properties": {
    "iso:country": "GB",
    "wof:name": "CB6 1GS",
    "wof:placetype": "postalcode"
  },
  "geometry": {"coordinates":[0.293047,52.45059],"type":"Point"}
}
