{
  "type": "Feature",
  "properties": {
    "iso:country": "GB",
    "wof:name": "WF10 5WL",
    "wof:placetype": "postalcode"
  },
  "geometry": {"coordinates":[-1.39217,53.713288],"type":"Point"}
}
