{
  "type": "Feature",
  "properties": {
    "iso:country": "GB",
    "wof:name": "DH1 3FA",
    "wof:placetype": "postalcode"
  },
  "geometry": {"coordinates":[-1.590614,54.760332],"type":"Point"}
}
