{
  "type": "Feature",
  "properties": {
    "iso:country": "GB",
    "wof:name": "IP21 5JN",
    "wof:placetype": "postalcode"
  },
  "geometry": {"coordinates":[1.270833,52.314416],"type":"Point"}
}
