{
  "type": "Feature",
  "properties": {
    "iso:country": "GB",
    "wof:name": "HD9 2AY",
    "wof:placetype": "postalcode"
  },
  "geometry": {"coordinates":[-1.783731,53.557841],"type":"Point"}
}
