{
  "type": "Feature",
  "properties": {
    "iso:country": "GB",
    "wof:name": "CW9 5NP",
    "wof:placetype": "postalcode"
  },
  "geometry": {"coordinates":[-2.507164,53.262258],"type":"Point"}
}
