{
  "type": "Feature",
  "properties": {
    "iso:country": "GB",
    "wof:name": "B80 7FS",
    "wof:placetype": "postalcode"
  },
  "geometry": {"coordinates":[-1.89712,52.274948],"type":"Point"}
}
