{
  "type": "Feature",
  "properties": {
    "iso:country": "GB",
    "wof:name": "TN21 9BL",
    "wof:placetype": "postalcode"
  },
  "geometry": {"coordinates":[0.252045,50.930435],"type":"Point"}
}
