{
  "type": "Feature",
  "properties": {
    "iso:country": "GB",
    "wof:name": "SW19 2XF",
    "wof:placetype": "postalcode"
  },
  "geometry": {"coordinates":[-0.189003,51.415323],"type":"Point"}
}
