{
  "type": "Feature",
  "properties": {
    "iso:country": "GB",
    "wof:name": "YO8 3QX",
    "wof:placetype": "postalcode"
  },
  "geometry": {"coordinates":[-1.121893,53.819626],"type":"Point"}
}
