{
  "type": "Feature",
  "properties": {
    "iso:country": "GB",
    "wof:name": "B17 0UA",
    "wof:placetype": "postalcode"
  },
  "geometry": {"coordinates":[-1.966118,52.455025],"type":"Point"}
}
