{
  "type": "Feature",
  "properties": {
    "iso:country": "GB",
    "wof:name": "HP22 7DG",
    "wof:placetype": "postalcode"
  },
  "geometry": {"coordinates":[-0.767283,51.831595],"type":"Point"}
}
