{
  "type": "Feature",
  "properties": {
    "iso:country": "GB",
    "wof:name": "WA13 0QJ",
    "wof:placetype": "postalcode"
  },
  "geometry": {"coordinates":[-2.483201,53.38119],"type":"Point"}
}
