{
  "type": "Feature",
  "properties": {
    "iso:country": "GB",
    "wof:name": "CW4 7LX",
    "wof:placetype": "postalcode"
  },
  "geometry": {"coordinates":[-2.386971,53.191877],"type":"Point"}
}
