{
  "type": "Feature",
  "properties": {
    "iso:country": "GB",
    "wof:name": "DA11 7FD",
    "wof:placetype": "postalcode"
  },
  "geometry": {"coordinates":[0.357604,51.420898],"type":"Point"}
}
