{
  "type": "Feature",
  "properties": {
    "iso:country": "GB",
    "wof:name": "RG42 4JG",
    "wof:placetype": "postalcode"
  },
  "geometry": {"coordinates":[-0.777411,51.424962],"type":"Point"}
}
