{
  "type": "Feature",
  "properties": {
    "iso:country": "GB",
    "wof:name": "SK8 1AH",
    "wof:placetype": "postalcode"
  },
  "geometry": {"coordinates":[-2.215426,53.395214],"type":"Point"}
}
