{
  "type": "Feature",
  "properties": {
    "iso:country": "GB",
    "wof:name": "PE14 7AR",
    "wof:placetype": "postalcode"
  },
  "geometry": {"coordinates":[0.185309,52.687401],"type":"Point"}
}
