{
  "type": "Feature",
  "properties": {
    "iso:country": "GB",
    "wof:name": "NR14 8UD",
    "wof:placetype": "postalcode"
  },
  "geometry": {"coordinates":[1.315004,52.609608],"type":"Point"}
}
