{
  "type": "Feature",
  "properties": {
    "iso:country": "GB",
    "wof:name": "GL55 6RQ",
    "wof:placetype": "postalcode"
  },
  "geometry": {"coordinates":[-1.817231,52.070407],"type":"Point"}
}
