{
  "type": "Feature",
  "properties": {
    "iso:country": "GB",
    "wof:name": "G43 2AY",
    "wof:placetype": "postalcode"
  },
  "geometry": {"coordinates":[-4.265861,55.822193],"type":"Point"}
}
