{
  "type": "Feature",
  "properties": {
    "iso:country": "GB",
    "wof:name": "LU2 0TL",
    "wof:placetype": "postalcode"
  },
  "geometry": {"coordinates":[-0.399334,51.892327],"type":"Point"}
}
