{
  "type": "Feature",
  "properties": {
    "iso:country": "GB",
    "wof:name": "RG27 9QU",
    "wof:placetype": "postalcode"
  },
  "geometry": {"coordinates":[-0.948915,51.288165],"type":"Point"}
}
