{
  "type": "Feature",
  "properties": {
    "iso:country": "GB",
    "wof:name": "B38 8RJ",
    "wof:placetype": "postalcode"
  },
  "geometry": {"coordinates":[-1.93691,52.400551],"type":"Point"}
}
