{
  "type": "Feature",
  "properties": {
    "iso:country": "GB",
    "wof:name": "NR12 9QE",
    "wof:placetype": "postalcode"
  },
  "geometry": {"coordinates":[1.529638,52.766288],"type":"Point"}
}
