{
  "type": "Feature",
  "properties": {
    "iso:country": "GB",
    "wof:name": "GL15 4BQ",
    "wof:placetype": "postalcode"
  },
  "geometry": {"coordinates":[-2.513921,51.73377],"type":"Point"}
}
