{
  "type": "Feature",
  "properties": {
    "iso:country": "GB",
    "wof:name": "SO52 9AG",
    "wof:placetype": "postalcode"
  },
  "geometry": {"coordinates":[-1.401213,50.993847],"type":"Point"}
}
