{
  "type": "Feature",
  "properties": {
    "iso:country": "GB",
    "wof:name": "BH8 9DN",
    "wof:placetype": "postalcode"
  },
  "geometry": {"coordinates":[-1.856143,50.738887],"type":"Point"}
}
