{
  "type": "Feature",
  "properties": {
    "iso:country": "GB",
    "wof:name": "PE11 2PN",
    "wof:placetype": "postalcode"
  },
  "geometry": {"coordinates":[-0.141168,52.782188],"type":"Point"}
}
