{
  "type": "Feature",
  "properties": {
    "iso:country": "GB",
    "wof:name": "CW1 4PY",
    "wof:placetype": "postalcode"
  },
  "geometry": {"coordinates":[-2.452788,53.118502],"type":"Point"}
}
