{
  "type": "Feature",
  "properties": {
    "iso:country": "GB",
    "wof:name": "SO41 8QX",
    "wof:placetype": "postalcode"
  },
  "geometry": {"coordinates":[-1.563661,50.753899],"type":"Point"}
}
