{
  "type": "Feature",
  "properties": {
    "iso:country": "GB",
    "wof:name": "IP23 7EE",
    "wof:placetype": "postalcode"
  },
  "geometry": {"coordinates":[1.094699,52.271417],"type":"Point"}
}
