{
  "type": "Feature",
  "properties": {
    "iso:country": "GB",
    "wof:name": "SO14 3SG",
    "wof:placetype": "postalcode"
  },
  "geometry": {"coordinates":[-1.399459,50.897879],"type":"Point"}
}
