{
  "type": "Feature",
  "properties": {
    "iso:country": "GB",
    "wof:name": "CA13 0DS",
    "wof:placetype": "postalcode"
  },
  "geometry": {"coordinates":[-3.366976,54.656384],"type":"Point"}
}
