{
  "type": "Feature",
  "properties": {
    "iso:country": "GB",
    "wof:name": "DE22 4NN",
    "wof:placetype": "postalcode"
  },
  "geometry": {"coordinates":[-1.526506,52.923898],"type":"Point"}
}
