{
  "type": "Feature",
  "properties": {
    "iso:country": "GB",
    "wof:name": "WV10 6GX",
    "wof:placetype": "postalcode"
  },
  "geometry": {"coordinates":[-2.128991,52.609981],"type":"Point"}
}
