{
  "type": "Feature",
  "properties": {
    "iso:country": "GB",
    "wof:name": "MK18 3DS",
    "wof:placetype": "postalcode"
  },
  "geometry": {"coordinates":[-0.8825,51.944113],"type":"Point"}
}
