{
  "type": "Feature",
  "properties": {
    "iso:country": "GB",
    "wof:name": "RG27 9PY",
    "wof:placetype": "postalcode"
  },
  "geometry": {"coordinates":[-0.949403,51.288151],"type":"Point"}
}
