{
  "type": "Feature",
  "properties": {
    "iso:country": "GB",
    "wof:name": "MK45 2NS",
    "wof:placetype": "postalcode"
  },
  "geometry": {"coordinates":[-0.496771,52.023442],"type":"Point"}
}
