{
  "type": "Feature",
  "properties": {
    "iso:country": "GB",
    "wof:name": "PO8 9AX",
    "wof:placetype": "postalcode"
  },
  "geometry": {"coordinates":[-1.028729,50.904575],"type":"Point"}
}
