{
  "type": "Feature",
  "properties": {
    "iso:country": "GB",
    "wof:name": "OX16 9FN",
    "wof:placetype": "postalcode"
  },
  "geometry": {"coordinates":[-1.320087,52.050273],"type":"Point"}
}
