{
  "type": "Feature",
  "properties": {
    "iso:country": "GB",
    "wof:name": "S44 6GB",
    "wof:placetype": "postalcode"
  },
  "geometry": {"coordinates":[-1.272768,53.226795],"type":"Point"}
}
