{
  "type": "Feature",
  "properties": {
    "iso:country": "GB",
    "wof:name": "TQ12 6EN",
    "wof:placetype": "postalcode"
  },
  "geometry": {"coordinates":[-3.651844,50.55839],"type":"Point"}
}
