{
  "type": "Feature",
  "properties": {
    "iso:country": "GB",
    "wof:name": "MK10 7GU",
    "wof:placetype": "postalcode"
  },
  "geometry": {"coordinates":[-0.680663,52.048213],"type":"Point"}
}
