{
  "type": "Feature",
  "properties": {
    "iso:country": "GB",
    "wof:name": "CA5 6DZ",
    "wof:placetype": "postalcode"
  },
  "geometry": {"coordinates":[-3.051995,54.920546],"type":"Point"}
}
