{
  "type": "Feature",
  "properties": {
    "iso:country": "GB",
    "wof:name": "B77 4QZ",
    "wof:placetype": "postalcode"
  },
  "geometry": {"coordinates":[-1.640927,52.634079],"type":"Point"}
}
