{
  "type": "Feature",
  "properties": {
    "iso:country": "GB",
    "wof:name": "S41 7FB",
    "wof:placetype": "postalcode"
  },
  "geometry": {"coordinates":[-1.424944,53.244552],"type":"Point"}
}
