{
  "type": "Feature",
  "properties": {
    "iso:country": "GB",
    "wof:name": "CF64 1FP",
    "wof:placetype": "postalcode"
  },
  "geometry": {"coordinates":[-3.168166,51.444466],"type":"Point"}
}
