{
  "type": "Feature",
  "properties": {
    "iso:country": "GB",
    "wof:name": "PA4 0YW",
    "wof:placetype": "postalcode"
  },
  "geometry": {"coordinates":[-4.377532,55.867889],"type":"Point"}
}
