{
  "type": "Feature",
  "properties": {
    "iso:country": "GB",
    "wof:name": "SY12 0FJ",
    "wof:placetype": "postalcode"
  },
  "geometry": {"coordinates":[-2.898604,52.902811],"type":"Point"}
}
