{
  "type": "Feature",
  "properties": {
    "iso:country": "GB",
    "wof:name": "DE6 1TW",
    "wof:placetype": "postalcode"
  },
  "geometry": {"coordinates":[-1.730085,53.006211],"type":"Point"}
}
