{
  "type": "Feature",
  "properties": {
    "iso:country": "GB",
    "wof:name": "WV14 0SU",
    "wof:placetype": "postalcode"
  },
  "geometry": {"coordinates":[-2.081318,52.56094],"type":"Point"}
}
