{
  "type": "Feature",
  "properties": {
    "iso:country": "GB",
    "wof:name": "NE36 0AR",
    "wof:placetype": "postalcode"
  },
  "geometry": {"coordinates":[-1.417406,54.947612],"type":"Point"}
}
