{
  "type": "Feature",
  "properties": {
    "iso:country": "GB",
    "wof:name": "G4 0HZ",
    "wof:placetype": "postalcode"
  },
  "geometry": {"coordinates":[-4.254777,55.869553],"type":"Point"}
}
