{
  "type": "Feature",
  "properties": {
    "iso:country": "GB",
    "wof:name": "BB3 2UQ",
    "wof:placetype": "postalcode"
  },
  "geometry": {"coordinates":[-2.468431,53.693488],"type":"Point"}
}
