{
  "type": "Feature",
  "properties": {
    "iso:country": "GB",
    "wof:name": "SL6 3ED",
    "wof:placetype": "postalcode"
  },
  "geometry": {"coordinates":[-0.740986,51.508366],"type":"Point"}
}
