{
  "type": "Feature",
  "properties": {
    "iso:country": "GB",
    "wof:name": "BS3 4EU",
    "wof:placetype": "postalcode"
  },
  "geometry": {"coordinates":[-2.592836,51.444101],"type":"Point"}
}
