{
  "type": "Feature",
  "properties": {
    "iso:country": "GB",
    "wof:name": "SY21 7FB",
    "wof:placetype": "postalcode"
  },
  "geometry": {"coordinates":[-3.130991,52.66696],"type":"Point"}
}
