{
  "type": "Feature",
  "properties": {
    "iso:country": "GB",
    "wof:name": "PE15 0WJ",
    "wof:placetype": "postalcode"
  },
  "geometry": {"coordinates":[0.059394,52.490236],"type":"Point"}
}
