{
  "type": "Feature",
  "properties": {
    "iso:country": "GB",
    "wof:name": "SO31 8NF",
    "wof:placetype": "postalcode"
  },
  "geometry": {"coordinates":[-1.322467,50.894283],"type":"Point"}
}
