{
  "type": "Feature",
  "properties": {
    "iso:country": "GB",
    "wof:name": "IP11 4HQ",
    "wof:placetype": "postalcode"
  },
  "geometry": {"coordinates":[1.313818,51.959641],"type":"Point"}
}
