{
  "type": "Feature",
  "properties": {
    "iso:country": "GB",
    "wof:name": "PE12 8JW",
    "wof:placetype": "postalcode"
  },
  "geometry": {"coordinates":[0.043043,52.817965],"type":"Point"}
}
