{
  "type": "Feature",
  "properties": {
    "iso:country": "GB",
    "wof:name": "PH20 1AH",
    "wof:placetype": "postalcode"
  },
  "geometry": {"coordinates":[-4.285769,57.020191],"type":"Point"}
}
