{
  "type": "Feature",
  "properties": {
    "iso:country": "GB",
    "wof:name": "CW1 4SJ",
    "wof:placetype": "postalcode"
  },
  "geometry": {"coordinates":[-2.436378,53.112244],"type":"Point"}
}
