{
  "type": "Feature",
  "properties": {
    "iso:country": "GB",
    "wof:name": "PR4 0FE",
    "wof:placetype": "postalcode"
  },
  "geometry": {"coordinates":[-2.740289,53.795328],"type":"Point"}
}
