{
  "type": "Feature",
  "properties": {
    "iso:country": "GB",
    "wof:name": "S5 8NL",
    "wof:placetype": "postalcode"
  },
  "geometry": {"coordinates":[-1.485004,53.42692],"type":"Point"}
}
