{
  "type": "Feature",
  "properties": {
    "iso:country": "GB",
    "wof:name": "HD9 4JG",
    "wof:placetype": "postalcode"
  },
  "geometry": {"coordinates":[-1.833922,53.585578],"type":"Point"}
}
