{
  "type": "Feature",
  "properties": {
    "iso:country": "GB",
    "wof:name": "HG4 3NX",
    "wof:placetype": "postalcode"
  },
  "geometry": {"coordinates":[-1.65026,54.151022],"type":"Point"}
}
