{
  "type": "Feature",
  "properties": {
    "iso:country": "GB",
    "wof:name": "NG15 6XB",
    "wof:placetype": "postalcode"
  },
  "geometry": {"coordinates":[-1.223911,53.018981],"type":"Point"}
}
