{
  "type": "Feature",
  "properties": {
    "iso:country": "GB",
    "wof:name": "BB11 1EX",
    "wof:placetype": "postalcode"
  },
  "geometry": {"coordinates":[-2.245327,53.789372],"type":"Point"}
}
