{
  "type": "Feature",
  "properties": {
    "iso:country": "GB",
    "wof:name": "ST7 3DJ",
    "wof:placetype": "postalcode"
  },
  "geometry": {"coordinates":[-2.282847,53.098604],"type":"Point"}
}
