{
  "type": "Feature",
  "properties": {
    "iso:country": "GB",
    "wof:name": "LE10 2HU",
    "wof:placetype": "postalcode"
  },
  "geometry": {"coordinates":[-1.35238,52.524885],"type":"Point"}
}
