{
  "type": "Feature",
  "properties": {
    "iso:country": "GB",
    "wof:name": "AB45 3WB",
    "wof:placetype": "postalcode"
  },
  "geometry": {"coordinates":[-2.520704,57.664652],"type":"Point"}
}
