{
  "type": "Feature",
  "properties": {
    "iso:country": "GB",
    "wof:name": "SY2 6HD",
    "wof:placetype": "postalcode"
  },
  "geometry": {"coordinates":[-2.732242,52.691293],"type":"Point"}
}
