{
  "type": "Feature",
  "properties": {
    "iso:country": "GB",
    "wof:name": "YO12 7BD",
    "wof:placetype": "postalcode"
  },
  "geometry": {"coordinates":[-0.404845,54.289728],"type":"Point"}
}
