{
  "type": "Feature",
  "properties": {
    "iso:country": "GB",
    "wof:name": "KT10 0SS",
    "wof:placetype": "postalcode"
  },
  "geometry": {"coordinates":[-0.33905,51.37421],"type":"Point"}
}
