{
  "type": "Feature",
  "properties": {
    "iso:country": "GB",
    "wof:name": "TS13 5HU",
    "wof:placetype": "postalcode"
  },
  "geometry": {"coordinates":[-0.749846,54.533955],"type":"Point"}
}
