{
  "type": "Feature",
  "properties": {
    "iso:country": "GB",
    "wof:name": "S60 8DR",
    "wof:placetype": "postalcode"
  },
  "geometry": {"coordinates":[-1.3708,53.386734],"type":"Point"}
}
