{
  "type": "Feature",
  "properties": {
    "iso:country": "GB",
    "wof:name": "LN4 4AJ",
    "wof:placetype": "postalcode"
  },
  "geometry": {"coordinates":[-0.213979,53.009959],"type":"Point"}
}
