{
  "type": "Feature",
  "properties": {
    "iso:country": "GB",
    "wof:name": "SS17 9FA",
    "wof:placetype": "postalcode"
  },
  "geometry": {"coordinates":[0.463599,51.508788],"type":"Point"}
}
