{
  "type": "Feature",
  "properties": {
    "iso:country": "GB",
    "wof:name": "NG15 6XE",
    "wof:placetype": "postalcode"
  },
  "geometry": {"coordinates":[-1.222996,53.019245],"type":"Point"}
}
