{
  "type": "Feature",
  "properties": {
    "iso:country": "GB",
    "wof:name": "KY15 7RD",
    "wof:placetype": "postalcode"
  },
  "geometry": {"coordinates":[-3.131954,56.28487],"type":"Point"}
}
