{
  "type": "Feature",
  "properties": {
    "iso:country": "GB",
    "wof:name": "SS9 3JP",
    "wof:placetype": "postalcode"
  },
  "geometry": {"coordinates":[0.6633,51.547693],"type":"Point"}
}
