{
  "type": "Feature",
  "properties": {
    "iso:country": "GB",
    "wof:name": "M30 0ZB",
    "wof:placetype": "postalcode"
  },
  "geometry": {"coordinates":[-2.345122,53.477892],"type":"Point"}
}
