{
  "type": "Feature",
  "properties": {
    "iso:country": "GB",
    "wof:name": "DN18 5SW",
    "wof:placetype": "postalcode"
  },
  "geometry": {"coordinates":[-0.439707,53.691638],"type":"Point"}
}
