{
  "type": "Feature",
  "properties": {
    "iso:country": "GB",
    "wof:name": "BA12 8GH",
    "wof:placetype": "postalcode"
  },
  "geometry": {"coordinates":[-2.191601,51.213437],"type":"Point"}
}
