{
  "type": "Feature",
  "properties": {
    "iso:country": "GB",
    "wof:name": "CF31 2DB",
    "wof:placetype": "postalcode"
  },
  "geometry": {"coordinates":[-3.561451,51.519837],"type":"Point"}
}
