{
  "type": "Feature",
  "properties": {
    "iso:country": "GB",
    "wof:name": "BB9 8LS",
    "wof:placetype": "postalcode"
  },
  "geometry": {"coordinates":[-2.2052,53.84297],"type":"Point"}
}
