{
  "type": "Feature",
  "properties": {
    "iso:country": "GB",
    "wof:name": "YO21 2NN",
    "wof:placetype": "postalcode"
  },
  "geometry": {"coordinates":[-0.938731,54.440402],"type":"Point"}
}
