{
  "type": "Feature",
  "properties": {
    "iso:country": "GB",
    "wof:name": "SG8 6FW",
    "wof:placetype": "postalcode"
  },
  "geometry": {"coordinates":[0.02371,52.080313],"type":"Point"}
}
