{
  "type": "Feature",
  "properties": {
    "iso:country": "GB",
    "wof:name": "SP4 6RQ",
    "wof:placetype": "postalcode"
  },
  "geometry": {"coordinates":[-1.760537,51.116766],"type":"Point"}
}
