{
  "type": "Feature",
  "properties": {
    "iso:country": "GB",
    "wof:name": "TA2 8GT",
    "wof:placetype": "postalcode"
  },
  "geometry": {"coordinates":[-3.059616,51.039476],"type":"Point"}
}
