{
  "type": "Feature",
  "properties": {
    "iso:country": "GB",
    "wof:name": "DY5 3EA",
    "wof:placetype": "postalcode"
  },
  "geometry": {"coordinates":[-2.121999,52.480228],"type":"Point"}
}
