{
  "type": "Feature",
  "properties": {
    "iso:country": "GB",
    "wof:name": "M38 9AT",
    "wof:placetype": "postalcode"
  },
  "geometry": {"coordinates":[-2.422432,53.535493],"type":"Point"}
}
