{
  "type": "Feature",
  "properties": {
    "iso:country": "GB",
    "wof:name": "WN2 5DZ",
    "wof:placetype": "postalcode"
  },
  "geometry": {"coordinates":[-2.605017,53.518932],"type":"Point"}
}
