{
  "type": "Feature",
  "properties": {
    "iso:country": "GB",
    "wof:name": "DN20 8EU",
    "wof:placetype": "postalcode"
  },
  "geometry": {"coordinates":[-0.492087,53.552224],"type":"Point"}
}
