{
  "type": "Feature",
  "properties": {
    "iso:country": "GB",
    "wof:name": "LU7 4FE",
    "wof:placetype": "postalcode"
  },
  "geometry": {"coordinates":[-0.639769,51.91071],"type":"Point"}
}
