{
  "type": "Feature",
  "properties": {
    "iso:country": "GB",
    "wof:name": "WN6 7GA",
    "wof:placetype": "postalcode"
  },
  "geometry": {"coordinates":[-2.659457,53.554427],"type":"Point"}
}
