{
  "type": "Feature",
  "properties": {
    "iso:country": "GB",
    "wof:name": "CH66 4AN",
    "wof:placetype": "postalcode"
  },
  "geometry": {"coordinates":[-2.951601,53.28007],"type":"Point"}
}
