{
  "type": "Feature",
  "properties": {
    "iso:country": "GB",
    "wof:name": "SA44 4DD",
    "wof:placetype": "postalcode"
  },
  "geometry": {"coordinates":[-4.309597,52.042494],"type":"Point"}
}
