{
  "type": "Feature",
  "properties": {
    "iso:country": "GB",
    "wof:name": "HP27 9FW",
    "wof:placetype": "postalcode"
  },
  "geometry": {"coordinates":[-0.851003,51.734109],"type":"Point"}
}
