{
  "type": "Feature",
  "properties": {
    "iso:country": "GB",
    "wof:name": "DE15 9PB",
    "wof:placetype": "postalcode"
  },
  "geometry": {"coordinates":[-1.607898,52.795187],"type":"Point"}
}
