{
  "type": "Feature",
  "properties": {
    "iso:country": "GB",
    "wof:name": "NE20 9AB",
    "wof:placetype": "postalcode"
  },
  "geometry": {"coordinates":[-1.760935,55.044697],"type":"Point"}
}
