{
  "type": "Feature",
  "properties": {
    "iso:country": "GB",
    "wof:name": "SY3 8EZ",
    "wof:placetype": "postalcode"
  },
  "geometry": {"coordinates":[-2.816328,52.719198],"type":"Point"}
}
