{
  "type": "Feature",
  "properties": {
    "iso:country": "GB",
    "wof:name": "LE7 9WG",
    "wof:placetype": "postalcode"
  },
  "geometry": {"coordinates":[-1.039762,52.638188],"type":"Point"}
}
