{
  "type": "Feature",
  "properties": {
    "iso:country": "GB",
    "wof:name": "TN17 3NU",
    "wof:placetype": "postalcode"
  },
  "geometry": {"coordinates":[0.56632,51.101603],"type":"Point"}
}
