{
  "type": "Feature",
  "properties": {
    "iso:country": "GB",
    "wof:name": "DN16 1ED",
    "wof:placetype": "postalcode"
  },
  "geometry": {"coordinates":[-0.642522,53.575888],"type":"Point"}
}
