{
  "type": "Feature",
  "properties": {
    "iso:country": "GB",
    "wof:name": "SA4 3JW",
    "wof:placetype": "postalcode"
  },
  "geometry": {"coordinates":[-4.103215,51.641177],"type":"Point"}
}
