{
  "type": "Feature",
  "properties": {
    "iso:country": "GB",
    "wof:name": "MK41 0LR",
    "wof:placetype": "postalcode"
  },
  "geometry": {"coordinates":[-0.401354,52.163021],"type":"Point"}
}
