{
  "type": "Feature",
  "properties": {
    "iso:country": "GB",
    "wof:name": "BB1 4AY",
    "wof:placetype": "postalcode"
  },
  "geometry": {"coordinates":[-2.411748,53.769475],"type":"Point"}
}
