{
  "type": "Feature",
  "properties": {
    "iso:country": "GB",
    "wof:name": "SG8 5SR",
    "wof:placetype": "postalcode"
  },
  "geometry": {"coordinates":[-0.043204,52.095695],"type":"Point"}
}
