{
  "type": "Feature",
  "properties": {
    "iso:country": "GB",
    "wof:name": "ST7 2UU",
    "wof:placetype": "postalcode"
  },
  "geometry": {"coordinates":[-2.311145,53.091954],"type":"Point"}
}
