{
  "type": "Feature",
  "properties": {
    "iso:country": "GB",
    "wof:name": "CM8 1YX",
    "wof:placetype": "postalcode"
  },
  "geometry": {"coordinates":[0.619691,51.786517],"type":"Point"}
}
