{
  "type": "Feature",
  "properties": {
    "iso:country": "GB",
    "wof:name": "HU7 3LG",
    "wof:placetype": "postalcode"
  },
  "geometry": {"coordinates":[-0.3429,53.804951],"type":"Point"}
}
