{
  "type": "Feature",
  "properties": {
    "iso:country": "GB",
    "wof:name": "KA13 7BF",
    "wof:placetype": "postalcode"
  },
  "geometry": {"coordinates":[-4.68583,55.650357],"type":"Point"}
}
