{
  "type": "Feature",
  "properties": {
    "iso:country": "GB",
    "wof:name": "SY5 7EY",
    "wof:placetype": "postalcode"
  },
  "geometry": {"coordinates":[-2.724062,52.610777],"type":"Point"}
}
