{
  "type": "Feature",
  "properties": {
    "iso:country": "GB",
    "wof:name": "SK3 9AG",
    "wof:placetype": "postalcode"
  },
  "geometry": {"coordinates":[-2.165855,53.401729],"type":"Point"}
}
