{
  "type": "Feature",
  "properties": {
    "iso:country": "GB",
    "wof:name": "NG24 3JP",
    "wof:placetype": "postalcode"
  },
  "geometry": {"coordinates":[-0.776556,53.042939],"type":"Point"}
}
