{
  "type": "Feature",
  "properties": {
    "iso:country": "GB",
    "wof:name": "KY11 8ZH",
    "wof:placetype": "postalcode"
  },
  "geometry": {"coordinates":[-3.406354,56.053057],"type":"Point"}
}
