{
  "type": "Feature",
  "properties": {
    "iso:country": "GB",
    "wof:name": "HP22 7BX",
    "wof:placetype": "postalcode"
  },
  "geometry": {"coordinates":[-0.766253,51.831045],"type":"Point"}
}
