{
  "type": "Feature",
  "properties": {
    "iso:country": "GB",
    "wof:name": "CA2 4QX",
    "wof:placetype": "postalcode"
  },
  "geometry": {"coordinates":[-2.926633,54.868276],"type":"Point"}
}
