{
  "type": "Feature",
  "properties": {
    "iso:country": "GB",
    "wof:name": "IP22 1RX",
    "wof:placetype": "postalcode"
  },
  "geometry": {"coordinates":[1.007009,52.359141],"type":"Point"}
}
