{
  "type": "Feature",
  "properties": {
    "iso:country": "GB",
    "wof:name": "PL21 0FY",
    "wof:placetype": "postalcode"
  },
  "geometry": {"coordinates":[-3.891399,50.351718],"type":"Point"}
}
