{
  "type": "Feature",
  "properties": {
    "iso:country": "GB",
    "wof:name": "SN6 7AH",
    "wof:placetype": "postalcode"
  },
  "geometry": {"coordinates":[-1.711673,51.629782],"type":"Point"}
}
