{
  "type": "Feature",
  "properties": {
    "iso:country": "GB",
    "wof:name": "N2 8FA",
    "wof:placetype": "postalcode"
  },
  "geometry": {"coordinates":[-0.164891,51.589856],"type":"Point"}
}
