{
  "type": "Feature",
  "properties": {
    "iso:country": "GB",
    "wof:name": "L17 1AR",
    "wof:placetype": "postalcode"
  },
  "geometry": {"coordinates":[-2.934247,53.389271],"type":"Point"}
}
