{
  "type": "Feature",
  "properties": {
    "iso:country": "GB",
    "wof:name": "WR11 8UF",
    "wof:placetype": "postalcode"
  },
  "geometry": {"coordinates":[-1.892673,52.155766],"type":"Point"}
}
