{
  "type": "Feature",
  "properties": {
    "iso:country": "GB",
    "wof:name": "DA10 1EL",
    "wof:placetype": "postalcode"
  },
  "geometry": {"coordinates":[0.305744,51.436499],"type":"Point"}
}
