{
  "type": "Feature",
  "properties": {
    "iso:country": "GB",
    "wof:name": "EH1 2RU",
    "wof:placetype": "postalcode"
  },
  "geometry": {"coordinates":[-3.199548,55.946598],"type":"Point"}
}
