{
  "type": "Feature",
  "properties": {
    "iso:country": "GB",
    "wof:name": "NN9 5GW",
    "wof:placetype": "postalcode"
  },
  "geometry": {"coordinates":[-0.598429,52.330379],"type":"Point"}
}
