{
  "type": "Feature",
  "properties": {
    "iso:country": "GB",
    "wof:name": "WF16 9FE",
    "wof:placetype": "postalcode"
  },
  "geometry": {"coordinates":[-1.666283,53.710236],"type":"Point"}
}
