{
  "type": "Feature",
  "properties": {
    "iso:country": "GB",
    "wof:name": "IP21 5TX",
    "wof:placetype": "postalcode"
  },
  "geometry": {"coordinates":[1.297153,52.379215],"type":"Point"}
}
