{
  "type": "Feature",
  "properties": {
    "iso:country": "GB",
    "wof:name": "YO7 3GB",
    "wof:placetype": "postalcode"
  },
  "geometry": {"coordinates":[-1.423639,54.153711],"type":"Point"}
}
