{
  "type": "Feature",
  "properties": {
    "iso:country": "GB",
    "wof:name": "CH66 3ST",
    "wof:placetype": "postalcode"
  },
  "geometry": {"coordinates":[-2.944517,53.283928],"type":"Point"}
}
