{
  "type": "Feature",
  "properties": {
    "iso:country": "GB",
    "wof:name": "HA2 8TF",
    "wof:placetype": "postalcode"
  },
  "geometry": {"coordinates":[-0.366061,51.558477],"type":"Point"}
}
