{
  "type": "Feature",
  "properties": {
    "iso:country": "GB",
    "wof:name": "BD22 8DJ",
    "wof:placetype": "postalcode"
  },
  "geometry": {"coordinates":[-1.954901,53.831193],"type":"Point"}
}
