{
  "type": "Feature",
  "properties": {
    "iso:country": "GB",
    "wof:name": "SP6 3FE",
    "wof:placetype": "postalcode"
  },
  "geometry": {"coordinates":[-1.83627,50.911215],"type":"Point"}
}
