{
  "type": "Feature",
  "properties": {
    "iso:country": "GB",
    "wof:name": "BA1 7BY",
    "wof:placetype": "postalcode"
  },
  "geometry": {"coordinates":[-2.317752,51.413321],"type":"Point"}
}
