{
  "type": "Feature",
  "properties": {
    "iso:country": "GB",
    "wof:name": "NR12 9EG",
    "wof:placetype": "postalcode"
  },
  "geometry": {"coordinates":[1.510729,52.773424],"type":"Point"}
}
