{
  "type": "Feature",
  "properties": {
    "iso:country": "GB",
    "wof:name": "BN13 3XU",
    "wof:placetype": "postalcode"
  },
  "geometry": {"coordinates":[-0.451216,50.840868],"type":"Point"}
}
