{
  "type": "Feature",
  "properties": {
    "iso:country": "GB",
    "wof:name": "DE23 3BA",
    "wof:placetype": "postalcode"
  },
  "geometry": {"coordinates":[-1.529989,52.889348],"type":"Point"}
}
