{
  "type": "Feature",
  "properties": {
    "iso:country": "GB",
    "wof:name": "G78 3RA",
    "wof:placetype": "postalcode"
  },
  "geometry": {"coordinates":[-4.420895,55.787969],"type":"Point"}
}
