{
  "type": "Feature",
  "properties": {
    "iso:country": "GB",
    "wof:name": "CO9 2TH",
    "wof:placetype": "postalcode"
  },
  "geometry": {"coordinates":[0.650024,51.949192],"type":"Point"}
}
