{
  "type": "Feature",
  "properties": {
    "iso:country": "GB",
    "wof:name": "M23 2TG",
    "wof:placetype": "postalcode"
  },
  "geometry": {"coordinates":[-2.285748,53.386743],"type":"Point"}
}
