{
  "type": "Feature",
  "properties": {
    "iso:country": "GB",
    "wof:name": "S73 8TX",
    "wof:placetype": "postalcode"
  },
  "geometry": {"coordinates":[-1.405432,53.522308],"type":"Point"}
}
