{
  "type": "Feature",
  "properties": {
    "iso:country": "GB",
    "wof:name": "SN11 8HZ",
    "wof:placetype": "postalcode"
  },
  "geometry": {"coordinates":[-1.98934,51.440422],"type":"Point"}
}
