{
  "type": "Feature",
  "properties": {
    "iso:country": "GB",
    "wof:name": "LE17 5SJ",
    "wof:placetype": "postalcode"
  },
  "geometry": {"coordinates":[-1.156025,52.486178],"type":"Point"}
}
