{
  "type": "Feature",
  "properties": {
    "iso:country": "GB",
    "wof:name": "BA9 9GE",
    "wof:placetype": "postalcode"
  },
  "geometry": {"coordinates":[-2.420204,51.053507],"type":"Point"}
}
