{
  "type": "Feature",
  "properties": {
    "iso:country": "GB",
    "wof:name": "TS6 0FF",
    "wof:placetype": "postalcode"
  },
  "geometry": {"coordinates":[-1.146733,54.553805],"type":"Point"}
}
