{
  "type": "Feature",
  "properties": {
    "iso:country": "GB",
    "wof:name": "SE7 8FN",
    "wof:placetype": "postalcode"
  },
  "geometry": {"coordinates":[0.048664,51.486051],"type":"Point"}
}
