{
  "type": "Feature",
  "properties": {
    "iso:country": "GB",
    "wof:name": "LN2 2GN",
    "wof:placetype": "postalcode"
  },
  "geometry": {"coordinates":[-0.493193,53.270233],"type":"Point"}
}
