{
  "type": "Feature",
  "properties": {
    "iso:country": "GB",
    "wof:name": "BS34 7PQ",
    "wof:placetype": "postalcode"
  },
  "geometry": {"coordinates":[-2.577821,51.50621],"type":"Point"}
}
