{
  "type": "Feature",
  "properties": {
    "iso:country": "GB",
    "wof:name": "ML12 6ZT",
    "wof:placetype": "postalcode"
  },
  "geometry": {"coordinates":[-3.520662,55.626798],"type":"Point"}
}
