{
  "type": "Feature",
  "properties": {
    "iso:country": "GB",
    "wof:name": "ME8 7GF",
    "wof:placetype": "postalcode"
  },
  "geometry": {"coordinates":[0.60547,51.371274],"type":"Point"}
}
