{
  "type": "Feature",
  "properties": {
    "iso:country": "GB",
    "wof:name": "PE33 0FF",
    "wof:placetype": "postalcode"
  },
  "geometry": {"coordinates":[0.413208,52.728093],"type":"Point"}
}
