{
  "type": "Feature",
  "properties": {
    "iso:country": "GB",
    "wof:name": "IP3 9SY",
    "wof:placetype": "postalcode"
  },
  "geometry": {"coordinates":[1.221841,52.029472],"type":"Point"}
}
