{
  "type": "Feature",
  "properties": {
    "iso:country": "GB",
    "wof:name": "KY16 9BT",
    "wof:placetype": "postalcode"
  },
  "geometry": {"coordinates":[-2.801935,56.338354],"type":"Point"}
}
