{
  "type": "Feature",
  "properties": {
    "iso:country": "GB",
    "wof:name": "TA6 4AA",
    "wof:placetype": "postalcode"
  },
  "geometry": {"coordinates":[-2.992806,51.135473],"type":"Point"}
}
