{
  "type": "Feature",
  "properties": {
    "iso:country": "GB",
    "wof:name": "L23 1TE",
    "wof:placetype": "postalcode"
  },
  "geometry": {"coordinates":[-3.003519,53.49973],"type":"Point"}
}
