{
  "type": "Feature",
  "properties": {
    "iso:country": "GB",
    "wof:name": "SY12 9FE",
    "wof:placetype": "postalcode"
  },
  "geometry": {"coordinates":[-2.906024,52.909272],"type":"Point"}
}
