{
  "type": "Feature",
  "properties": {
    "iso:country": "GB",
    "wof:name": "RM13 7DF",
    "wof:placetype": "postalcode"
  },
  "geometry": {"coordinates":[0.1897,51.531813],"type":"Point"}
}
