{
  "type": "Feature",
  "properties": {
    "iso:country": "GB",
    "wof:name": "CB4 2ZF",
    "wof:placetype": "postalcode"
  },
  "geometry": {"coordinates":[0.136861,52.232612],"type":"Point"}
}
