{
  "type": "Feature",
  "properties": {
    "iso:country": "GB",
    "wof:name": "S73 9LX",
    "wof:placetype": "postalcode"
  },
  "geometry": {"coordinates":[-1.381348,53.53352],"type":"Point"}
}
