{
  "type": "Feature",
  "properties": {
    "iso:country": "GB",
    "wof:name": "HR4 7BX",
    "wof:placetype": "postalcode"
  },
  "geometry": {"coordinates":[-2.90715,52.127804],"type":"Point"}
}
