{
  "type": "Feature",
  "properties": {
    "iso:country": "GB",
    "wof:name": "LA2 8JU",
    "wof:placetype": "postalcode"
  },
  "geometry": {"coordinates":[-2.632369,54.11139],"type":"Point"}
}
