{
  "type": "Feature",
  "properties": {
    "iso:country": "GB",
    "wof:name": "GL15 4QT",
    "wof:placetype": "postalcode"
  },
  "geometry": {"coordinates":[-2.543792,51.755313],"type":"Point"}
}
