{
  "type": "Feature",
  "properties": {
    "iso:country": "GB",
    "wof:name": "EX16 8FD",
    "wof:placetype": "postalcode"
  },
  "geometry": {"coordinates":[-3.698467,50.911337],"type":"Point"}
}
