{
  "type": "Feature",
  "properties": {
    "iso:country": "GB",
    "wof:name": "L9 0HR",
    "wof:placetype": "postalcode"
  },
  "geometry": {"coordinates":[-2.950199,53.467483],"type":"Point"}
}
