{
  "type": "Feature",
  "properties": {
    "iso:country": "GB",
    "wof:name": "LE1 3AX",
    "wof:placetype": "postalcode"
  },
  "geometry": {"coordinates":[-1.128735,52.637652],"type":"Point"}
}
