{
  "type": "Feature",
  "properties": {
    "iso:country": "GB",
    "wof:name": "OX11 9FT",
    "wof:placetype": "postalcode"
  },
  "geometry": {"coordinates":[-1.228256,51.617127],"type":"Point"}
}
