{
  "type": "Feature",
  "properties": {
    "iso:country": "GB",
    "wof:name": "EN10 7JJ",
    "wof:placetype": "postalcode"
  },
  "geometry": {"coordinates":[-0.015335,51.747876],"type":"Point"}
}
