{
  "type": "Feature",
  "properties": {
    "iso:country": "GB",
    "wof:name": "G52 4PX",
    "wof:placetype": "postalcode"
  },
  "geometry": {"coordinates":[-4.364065,55.857237],"type":"Point"}
}
