{
  "type": "Feature",
  "properties": {
    "iso:country": "GB",
    "wof:name": "TD10 6AD",
    "wof:placetype": "postalcode"
  },
  "geometry": {"coordinates":[-2.462774,55.707214],"type":"Point"}
}
