{
  "type": "Feature",
  "properties": {
    "iso:country": "GB",
    "wof:name": "NR18 0ZP",
    "wof:placetype": "postalcode"
  },
  "geometry": {"coordinates":[1.11206,52.57195],"type":"Point"}
}
