{
  "type": "Feature",
  "properties": {
    "iso:country": "GB",
    "wof:name": "MK45 2FD",
    "wof:placetype": "postalcode"
  },
  "geometry": {"coordinates":[-0.489798,52.021879],"type":"Point"}
}
