{
  "type": "Feature",
  "properties": {
    "iso:country": "GB",
    "wof:name": "IP33 3TA",
    "wof:placetype": "postalcode"
  },
  "geometry": {"coordinates":[0.693142,52.250374],"type":"Point"}
}
