{
  "type": "Feature",
  "properties": {
    "iso:country": "GB",
    "wof:name": "B65 8FG",
    "wof:placetype": "postalcode"
  },
  "geometry": {"coordinates":[-2.056772,52.48089],"type":"Point"}
}
