{
  "type": "Feature",
  "properties": {
    "iso:country": "GB",
    "wof:name": "G77 5GS",
    "wof:placetype": "postalcode"
  },
  "geometry": {"coordinates":[-4.34895,55.76375],"type":"Point"}
}
