{
  "type": "Feature",
  "properties": {
    "iso:country": "GB",
    "wof:name": "BS29 6AT",
    "wof:placetype": "postalcode"
  },
  "geometry": {"coordinates":[-2.899391,51.345792],"type":"Point"}
}
