{
  "type": "Feature",
  "properties": {
    "iso:country": "GB",
    "wof:name": "GU9 7GU",
    "wof:placetype": "postalcode"
  },
  "geometry": {"coordinates":[-0.810747,51.215344],"type":"Point"}
}
