{
  "type": "Feature",
  "properties": {
    "iso:country": "GB",
    "wof:name": "TQ7 2NL",
    "wof:placetype": "postalcode"
  },
  "geometry": {"coordinates":[-3.70907,50.229727],"type":"Point"}
}
