{
  "type": "Feature",
  "properties": {
    "iso:country": "GB",
    "wof:name": "EX17 5EQ",
    "wof:placetype": "postalcode"
  },
  "geometry": {"coordinates":[-3.754109,50.814985],"type":"Point"}
}
