{
  "type": "Feature",
  "properties": {
    "iso:country": "GB",
    "wof:name": "TF11 8GS",
    "wof:placetype": "postalcode"
  },
  "geometry": {"coordinates":[-2.361664,52.666053],"type":"Point"}
}
