{
  "type": "Feature",
  "properties": {
    "iso:country": "GB",
    "wof:name": "EX24 6RU",
    "wof:placetype": "postalcode"
  },
  "geometry": {"coordinates":[-3.09833,50.74104],"type":"Point"}
}
