{
  "type": "Feature",
  "properties": {
    "iso:country": "GB",
    "wof:name": "SO31 8LX",
    "wof:placetype": "postalcode"
  },
  "geometry": {"coordinates":[-1.323887,50.893419],"type":"Point"}
}
