{
  "type": "Feature",
  "properties": {
    "iso:country": "GB",
    "wof:name": "PE12 9PJ",
    "wof:placetype": "postalcode"
  },
  "geometry": {"coordinates":[0.174272,52.839487],"type":"Point"}
}
