{
  "type": "Feature",
  "properties": {
    "iso:country": "GB",
    "wof:name": "PO30 2HQ",
    "wof:placetype": "postalcode"
  },
  "geometry": {"coordinates":[-1.281582,50.694767],"type":"Point"}
}
