{
  "type": "Feature",
  "properties": {
    "iso:country": "GB",
    "wof:name": "BA5 1GG",
    "wof:placetype": "postalcode"
  },
  "geometry": {"coordinates":[-2.663003,51.226632],"type":"Point"}
}
