{
  "type": "Feature",
  "properties": {
    "iso:country": "GB",
    "wof:name": "SN8 4YU",
    "wof:placetype": "postalcode"
  },
  "geometry": {"coordinates":[-1.726481,51.41357],"type":"Point"}
}
