{
  "type": "Feature",
  "properties": {
    "iso:country": "GB",
    "wof:name": "SY23 1BZ",
    "wof:placetype": "postalcode"
  },
  "geometry": {"coordinates":[-4.083493,52.410326],"type":"Point"}
}
