{
  "type": "Feature",
  "properties": {
    "iso:country": "GB",
    "wof:name": "DN11 0ZA",
    "wof:placetype": "postalcode"
  },
  "geometry": {"coordinates":[-1.090562,53.480194],"type":"Point"}
}
