{
  "type": "Feature",
  "properties": {
    "iso:country": "GB",
    "wof:name": "BS3 5PD",
    "wof:placetype": "postalcode"
  },
  "geometry": {"coordinates":[-2.599849,51.435641],"type":"Point"}
}
