{
  "type": "Feature",
  "properties": {
    "iso:country": "GB",
    "wof:name": "WR14 1YL",
    "wof:placetype": "postalcode"
  },
  "geometry": {"coordinates":[-2.312823,52.134567],"type":"Point"}
}
