{
  "type": "Feature",
  "properties": {
    "iso:country": "GB",
    "wof:name": "PH2 7ES",
    "wof:placetype": "postalcode"
  },
  "geometry": {"coordinates":[-3.41767,56.402688],"type":"Point"}
}
