{
  "type": "Feature",
  "properties": {
    "iso:country": "GB",
    "wof:name": "BS24 7NF",
    "wof:placetype": "postalcode"
  },
  "geometry": {"coordinates":[-2.906181,51.358095],"type":"Point"}
}
