{
  "type": "Feature",
  "properties": {
    "iso:country": "GB",
    "wof:name": "SO30 2BP",
    "wof:placetype": "postalcode"
  },
  "geometry": {"coordinates":[-1.247099,50.905251],"type":"Point"}
}
