{
  "type": "Feature",
  "properties": {
    "iso:country": "GB",
    "wof:name": "EX6 7RE",
    "wof:placetype": "postalcode"
  },
  "geometry": {"coordinates":[-3.621724,50.664659],"type":"Point"}
}
