{
  "type": "Feature",
  "properties": {
    "iso:country": "GB",
    "wof:name": "CH66 1UQ",
    "wof:placetype": "postalcode"
  },
  "geometry": {"coordinates":[-2.910382,53.292572],"type":"Point"}
}
