{
  "type": "Feature",
  "properties": {
    "iso:country": "GB",
    "wof:name": "EX39 2BY",
    "wof:placetype": "postalcode"
  },
  "geometry": {"coordinates":[-4.209687,51.015074],"type":"Point"}
}
