{
  "type": "Feature",
  "properties": {
    "iso:country": "GB",
    "wof:name": "BD11 2DW",
    "wof:placetype": "postalcode"
  },
  "geometry": {"coordinates":[-1.694977,53.748081],"type":"Point"}
}
