{
  "type": "Feature",
  "properties": {
    "iso:country": "GB",
    "wof:name": "HP7 0LE",
    "wof:placetype": "postalcode"
  },
  "geometry": {"coordinates":[-0.628087,51.653012],"type":"Point"}
}
