{
  "type": "Feature",
  "properties": {
    "iso:country": "GB",
    "wof:name": "PE14 8ET",
    "wof:placetype": "postalcode"
  },
  "geometry": {"coordinates":[0.245829,52.661174],"type":"Point"}
}
