{
  "type": "Feature",
  "properties": {
    "iso:country": "GB",
    "wof:name": "MK17 0FP",
    "wof:placetype": "postalcode"
  },
  "geometry": {"coordinates":[-0.869638,51.973105],"type":"Point"}
}
