{
  "type": "Feature",
  "properties": {
    "iso:country": "GB",
    "wof:name": "CM16 6FJ",
    "wof:placetype": "postalcode"
  },
  "geometry": {"coordinates":[0.151033,51.722224],"type":"Point"}
}
