{
  "type": "Feature",
  "properties": {
    "iso:country": "GB",
    "wof:name": "CV35 0FH",
    "wof:placetype": "postalcode"
  },
  "geometry": {"coordinates":[-1.506553,52.197743],"type":"Point"}
}
