{
  "type": "Feature",
  "properties": {
    "iso:country": "GB",
    "wof:name": "WV2 2FF",
    "wof:placetype": "postalcode"
  },
  "geometry": {"coordinates":[-2.114151,52.576752],"type":"Point"}
}
