{
  "type": "Feature",
  "properties": {
    "iso:country": "GB",
    "wof:name": "PO9 5FH",
    "wof:placetype": "postalcode"
  },
  "geometry": {"coordinates":[-0.960171,50.865315],"type":"Point"}
}
