{
  "type": "Feature",
  "properties": {
    "iso:country": "GB",
    "wof:name": "N17 9BF",
    "wof:placetype": "postalcode"
  },
  "geometry": {"coordinates":[-0.069065,51.592544],"type":"Point"}
}
