{
  "type": "Feature",
  "properties": {
    "iso:country": "GB",
    "wof:name": "CA14 5DX",
    "wof:placetype": "postalcode"
  },
  "geometry": {"coordinates":[-3.553715,54.62326],"type":"Point"}
}
