{
  "type": "Feature",
  "properties": {
    "iso:country": "GB",
    "wof:name": "SW8 4FB",
    "wof:placetype": "postalcode"
  },
  "geometry": {"coordinates":[-0.135356,51.475498],"type":"Point"}
}
