{
  "type": "Feature",
  "properties": {
    "iso:country": "GB",
    "wof:name": "PE14 7NX",
    "wof:placetype": "postalcode"
  },
  "geometry": {"coordinates":[0.217294,52.728761],"type":"Point"}
}
