{
  "type": "Feature",
  "properties": {
    "iso:country": "GB",
    "wof:name": "PL4 8LS",
    "wof:placetype": "postalcode"
  },
  "geometry": {"coordinates":[-4.135623,50.376452],"type":"Point"}
}
