{
  "type": "Feature",
  "properties": {
    "iso:country": "GB",
    "wof:name": "WA4 4GF",
    "wof:placetype": "postalcode"
  },
  "geometry": {"coordinates":[-2.544887,53.348528],"type":"Point"}
}
