{
  "type": "Feature",
  "properties": {
    "iso:country": "GB",
    "wof:name": "HG4 2RF",
    "wof:placetype": "postalcode"
  },
  "geometry": {"coordinates":[-1.543965,54.144754],"type":"Point"}
}
