{
  "type": "Feature",
  "properties": {
    "iso:country": "GB",
    "wof:name": "PR4 6FN",
    "wof:placetype": "postalcode"
  },
  "geometry": {"coordinates":[-2.836437,53.697092],"type":"Point"}
}
