{
  "type": "Feature",
  "properties": {
    "iso:country": "GB",
    "wof:name": "S44 6LP",
    "wof:placetype": "postalcode"
  },
  "geometry": {"coordinates":[-1.281852,53.222832],"type":"Point"}
}
