{
  "type": "Feature",
  "properties": {
    "iso:country": "GB",
    "wof:name": "WA7 4QZ",
    "wof:placetype": "postalcode"
  },
  "geometry": {"coordinates":[-2.737558,53.320645],"type":"Point"}
}
