{
  "type": "Feature",
  "properties": {
    "iso:country": "GB",
    "wof:name": "WR5 3RS",
    "wof:placetype": "postalcode"
  },
  "geometry": {"coordinates":[-2.213374,52.168396],"type":"Point"}
}
