{
  "type": "Feature",
  "properties": {
    "iso:country": "GB",
    "wof:name": "NN2 7FL",
    "wof:placetype": "postalcode"
  },
  "geometry": {"coordinates":[-0.885066,52.273194],"type":"Point"}
}
