{
  "type": "Feature",
  "properties": {
    "iso:country": "GB",
    "wof:name": "BD13 5FJ",
    "wof:placetype": "postalcode"
  },
  "geometry": {"coordinates":[-1.89804,53.821208],"type":"Point"}
}
