{
  "type": "Feature",
  "properties": {
    "iso:country": "GB",
    "wof:name": "GL2 4ED",
    "wof:placetype": "postalcode"
  },
  "geometry": {"coordinates":[-2.267279,51.806152],"type":"Point"}
}
