{
  "type": "Feature",
  "properties": {
    "iso:country": "GB",
    "wof:name": "CF33 6NG",
    "wof:placetype": "postalcode"
  },
  "geometry": {"coordinates":[-3.684997,51.528964],"type":"Point"}
}
