{
  "type": "Feature",
  "properties": {
    "iso:country": "GB",
    "wof:name": "OX10 6FE",
    "wof:placetype": "postalcode"
  },
  "geometry": {"coordinates":[-1.113438,51.624059],"type":"Point"}
}
