{
  "type": "Feature",
  "properties": {
    "iso:country": "GB",
    "wof:name": "S25 1AD",
    "wof:placetype": "postalcode"
  },
  "geometry": {"coordinates":[-1.217345,53.386952],"type":"Point"}
}
