{
  "type": "Feature",
  "properties": {
    "iso:country": "GB",
    "wof:name": "GL11 5FJ",
    "wof:placetype": "postalcode"
  },
  "geometry": {"coordinates":[-2.360221,51.715244],"type":"Point"}
}
