{
  "type": "Feature",
  "properties": {
    "iso:country": "GB",
    "wof:name": "DN39 6AH",
    "wof:placetype": "postalcode"
  },
  "geometry": {"coordinates":[-0.359826,53.628233],"type":"Point"}
}
