{
  "type": "Feature",
  "properties": {
    "iso:country": "GB",
    "wof:name": "S75 1GA",
    "wof:placetype": "postalcode"
  },
  "geometry": {"coordinates":[-1.521534,53.574016],"type":"Point"}
}
