{
  "type": "Feature",
  "properties": {
    "iso:country": "GB",
    "wof:name": "MK19 6EA",
    "wof:placetype": "postalcode"
  },
  "geometry": {"coordinates":[-0.8649,52.014338],"type":"Point"}
}
