{
  "type": "Feature",
  "properties": {
    "iso:country": "GB",
    "wof:name": "TF1 5FF",
    "wof:placetype": "postalcode"
  },
  "geometry": {"coordinates":[-2.470709,52.697071],"type":"Point"}
}
