{
  "type": "Feature",
  "properties": {
    "iso:country": "GB",
    "wof:name": "BS25 5AF",
    "wof:placetype": "postalcode"
  },
  "geometry": {"coordinates":[-2.827946,51.333855],"type":"Point"}
}
