{
  "type": "Feature",
  "properties": {
    "iso:country": "GB",
    "wof:name": "DN3 3FW",
    "wof:placetype": "postalcode"
  },
  "geometry": {"coordinates":[-1.033871,53.509548],"type":"Point"}
}
