{
  "type": "Feature",
  "properties": {
    "iso:country": "GB",
    "wof:name": "WA12 8TE",
    "wof:placetype": "postalcode"
  },
  "geometry": {"coordinates":[-2.623954,53.4405],"type":"Point"}
}
