{
  "type": "Feature",
  "properties": {
    "iso:country": "GB",
    "wof:name": "NR14 8XR",
    "wof:placetype": "postalcode"
  },
  "geometry": {"coordinates":[1.331849,52.585508],"type":"Point"}
}
