{
  "type": "Feature",
  "properties": {
    "iso:country": "GB",
    "wof:name": "ST11 9FG",
    "wof:placetype": "postalcode"
  },
  "geometry": {"coordinates":[-2.027617,52.938743],"type":"Point"}
}
