{
  "type": "Feature",
  "properties": {
    "iso:country": "GB",
    "wof:name": "FK7 7GW",
    "wof:placetype": "postalcode"
  },
  "geometry": {"coordinates":[-3.843397,56.10083],"type":"Point"}
}
