{
  "type": "Feature",
  "properties": {
    "iso:country": "GB",
    "wof:name": "SK12 2GH",
    "wof:placetype": "postalcode"
  },
  "geometry": {"coordinates":[-2.037208,53.359017],"type":"Point"}
}
