{
  "type": "Feature",
  "properties": {
    "iso:country": "GB",
    "wof:name": "NR23 1DT",
    "wof:placetype": "postalcode"
  },
  "geometry": {"coordinates":[0.851473,52.955844],"type":"Point"}
}
