{
  "type": "Feature",
  "properties": {
    "iso:country": "GB",
    "wof:name": "M24 6TR",
    "wof:placetype": "postalcode"
  },
  "geometry": {"coordinates":[-2.199467,53.564764],"type":"Point"}
}
