{
  "type": "Feature",
  "properties": {
    "iso:country": "GB",
    "wof:name": "CV10 9TN",
    "wof:placetype": "postalcode"
  },
  "geometry": {"coordinates":[-1.554055,52.51955],"type":"Point"}
}
