{
  "type": "Feature",
  "properties": {
    "iso:country": "GB",
    "wof:name": "SP9 7BE",
    "wof:placetype": "postalcode"
  },
  "geometry": {"coordinates":[-1.677165,51.222538],"type":"Point"}
}
