{
  "type": "Feature",
  "properties": {
    "iso:country": "GB",
    "wof:name": "SK9 2TS",
    "wof:placetype": "postalcode"
  },
  "geometry": {"coordinates":[-2.202207,53.335014],"type":"Point"}
}
