{
  "type": "Feature",
  "properties": {
    "iso:country": "GB",
    "wof:name": "BA22 8FX",
    "wof:placetype": "postalcode"
  },
  "geometry": {"coordinates":[-2.682869,50.946839],"type":"Point"}
}
