{
  "type": "Feature",
  "properties": {
    "iso:country": "GB",
    "wof:name": "B60 4FY",
    "wof:placetype": "postalcode"
  },
  "geometry": {"coordinates":[-2.081183,52.296685],"type":"Point"}
}
