{
  "type": "Feature",
  "properties": {
    "iso:country": "GB",
    "wof:name": "AB34 5DF",
    "wof:placetype": "postalcode"
  },
  "geometry": {"coordinates":[-2.680165,57.084947],"type":"Point"}
}
