{
  "type": "Feature",
  "properties": {
    "iso:country": "GB",
    "wof:name": "BD6 3FJ",
    "wof:placetype": "postalcode"
  },
  "geometry": {"coordinates":[-1.785069,53.768067],"type":"Point"}
}
