{
  "type": "Feature",
  "properties": {
    "iso:country": "GB",
    "wof:name": "WF9 4FS",
    "wof:placetype": "postalcode"
  },
  "geometry": {"coordinates":[-1.361124,53.615108],"type":"Point"}
}
