{
  "type": "Feature",
  "properties": {
    "iso:country": "GB",
    "wof:name": "SY21 8FF",
    "wof:placetype": "postalcode"
  },
  "geometry": {"coordinates":[-3.007894,52.705901],"type":"Point"}
}
