{
  "type": "Feature",
  "properties": {
    "iso:country": "GB",
    "wof:name": "NR15 1YR",
    "wof:placetype": "postalcode"
  },
  "geometry": {"coordinates":[1.3202,52.54843],"type":"Point"}
}
