{
  "type": "Feature",
  "properties": {
    "iso:country": "GB",
    "wof:name": "CH66 7PH",
    "wof:placetype": "postalcode"
  },
  "geometry": {"coordinates":[-2.981223,53.295165],"type":"Point"}
}
