{
  "type": "Feature",
  "properties": {
    "iso:country": "GB",
    "wof:name": "NR24 2ES",
    "wof:placetype": "postalcode"
  },
  "geometry": {"coordinates":[1.064994,52.866992],"type":"Point"}
}
