{
  "type": "Feature",
  "properties": {
    "iso:country": "GB",
    "wof:name": "SA73 1PQ",
    "wof:placetype": "postalcode"
  },
  "geometry": {"coordinates":[-4.923146,51.728041],"type":"Point"}
}
