{
  "type": "Feature",
  "properties": {
    "iso:country": "GB",
    "wof:name": "OL16 4SX",
    "wof:placetype": "postalcode"
  },
  "geometry": {"coordinates":[-2.145098,53.599735],"type":"Point"}
}
