{
  "type": "Feature",
  "properties": {
    "iso:country": "GB",
    "wof:name": "RH13 9FU",
    "wof:placetype": "postalcode"
  },
  "geometry": {"coordinates":[-0.347185,51.012059],"type":"Point"}
}
