{
  "type": "Feature",
  "properties": {
    "iso:country": "GB",
    "wof:name": "KY11 1FF",
    "wof:placetype": "postalcode"
  },
  "geometry": {"coordinates":[-3.385059,56.035012],"type":"Point"}
}
