{
  "type": "Feature",
  "properties": {
    "iso:country": "GB",
    "wof:name": "LL15 1BF",
    "wof:placetype": "postalcode"
  },
  "geometry": {"coordinates":[-3.284549,53.127838],"type":"Point"}
}
