{
  "type": "Feature",
  "properties": {
    "iso:country": "GB",
    "wof:name": "CO3 9AR",
    "wof:placetype": "postalcode"
  },
  "geometry": {"coordinates":[0.850289,51.889436],"type":"Point"}
}
