{
  "type": "Feature",
  "properties": {
    "iso:country": "GB",
    "wof:name": "DY1 1RN",
    "wof:placetype": "postalcode"
  },
  "geometry": {"coordinates":[-2.089137,52.510285],"type":"Point"}
}
