{
  "type": "Feature",
  "properties": {
    "iso:country": "GB",
    "wof:name": "M45 0GQ",
    "wof:placetype": "postalcode"
  },
  "geometry": {"coordinates":[-2.286951,53.534367],"type":"Point"}
}
