{
  "type": "Feature",
  "properties": {
    "iso:country": "GB",
    "wof:name": "KT19 9BE",
    "wof:placetype": "postalcode"
  },
  "geometry": {"coordinates":[-0.263808,51.34179],"type":"Point"}
}
