{
  "type": "Feature",
  "properties": {
    "iso:country": "GB",
    "wof:name": "GU47 8AD",
    "wof:placetype": "postalcode"
  },
  "geometry": {"coordinates":[-0.807584,51.344937],"type":"Point"}
}
