{
  "type": "Feature",
  "properties": {
    "iso:country": "GB",
    "wof:name": "SY2 6FX",
    "wof:placetype": "postalcode"
  },
  "geometry": {"coordinates":[-2.73333,52.687349],"type":"Point"}
}
