{
  "type": "Feature",
  "properties": {
    "iso:country": "GB",
    "wof:name": "BB8 7AQ",
    "wof:placetype": "postalcode"
  },
  "geometry": {"coordinates":[-2.152243,53.861933],"type":"Point"}
}
