{
  "type": "Feature",
  "properties": {
    "iso:country": "GB",
    "wof:name": "L9 1BR",
    "wof:placetype": "postalcode"
  },
  "geometry": {"coordinates":[-2.969172,53.448616],"type":"Point"}
}
