{
  "type": "Feature",
  "properties": {
    "iso:country": "GB",
    "wof:name": "LN11 0NF",
    "wof:placetype": "postalcode"
  },
  "geometry": {"coordinates":[0.000951,53.369185],"type":"Point"}
}
