{
  "type": "Feature",
  "properties": {
    "iso:country": "GB",
    "wof:name": "IP14 5DN",
    "wof:placetype": "postalcode"
  },
  "geometry": {"coordinates":[1.097664,52.189667],"type":"Point"}
}
