{
  "type": "Feature",
  "properties": {
    "iso:country": "GB",
    "wof:name": "BN9 0FB",
    "wof:placetype": "postalcode"
  },
  "geometry": {"coordinates":[0.062336,50.78836],"type":"Point"}
}
