{
  "type": "Feature",
  "properties": {
    "iso:country": "GB",
    "wof:name": "NP19 0GG",
    "wof:placetype": "postalcode"
  },
  "geometry": {"coordinates":[-2.973599,51.58202],"type":"Point"}
}
