{
  "type": "Feature",
  "properties": {
    "iso:country": "GB",
    "wof:name": "WA10 6NJ",
    "wof:placetype": "postalcode"
  },
  "geometry": {"coordinates":[-2.746415,53.467599],"type":"Point"}
}
