{
  "type": "Feature",
  "properties": {
    "iso:country": "GB",
    "wof:name": "HR8 2GS",
    "wof:placetype": "postalcode"
  },
  "geometry": {"coordinates":[-2.431955,52.025726],"type":"Point"}
}
