{
  "type": "Feature",
  "properties": {
    "iso:country": "GB",
    "wof:name": "GU3 3EN",
    "wof:placetype": "postalcode"
  },
  "geometry": {"coordinates":[-0.581439,51.270412],"type":"Point"}
}
