{
  "type": "Feature",
  "properties": {
    "iso:country": "GB",
    "wof:name": "DD2 1ED",
    "wof:placetype": "postalcode"
  },
  "geometry": {"coordinates":[-2.994003,56.456394],"type":"Point"}
}
