{
  "type": "Feature",
  "properties": {
    "iso:country": "GB",
    "wof:name": "PO12 3FE",
    "wof:placetype": "postalcode"
  },
  "geometry": {"coordinates":[-1.152549,50.80812],"type":"Point"}
}
