{
  "type": "Feature",
  "properties": {
    "iso:country": "GB",
    "wof:name": "CF24 3RQ",
    "wof:placetype": "postalcode"
  },
  "geometry": {"coordinates":[-3.169421,51.493028],"type":"Point"}
}
