{
  "type": "Feature",
  "properties": {
    "iso:country": "GB",
    "wof:name": "EH26 8PS",
    "wof:placetype": "postalcode"
  },
  "geometry": {"coordinates":[-3.222972,55.798124],"type":"Point"}
}
