{
  "type": "Feature",
  "properties": {
    "iso:country": "GB",
    "wof:name": "CF15 7RB",
    "wof:placetype": "postalcode"
  },
  "geometry": {"coordinates":[-3.266447,51.541692],"type":"Point"}
}
