{
  "type": "Feature",
  "properties": {
    "iso:country": "GB",
    "wof:name": "DH3 4DS",
    "wof:placetype": "postalcode"
  },
  "geometry": {"coordinates":[-1.5163,54.859826],"type":"Point"}
}
