{
  "type": "Feature",
  "properties": {
    "iso:country": "GB",
    "wof:name": "NE3 1DG",
    "wof:placetype": "postalcode"
  },
  "geometry": {"coordinates":[-1.622819,55.009015],"type":"Point"}
}
