{
  "type": "Feature",
  "properties": {
    "iso:country": "GB",
    "wof:name": "IP22 1TG",
    "wof:placetype": "postalcode"
  },
  "geometry": {"coordinates":[1.111523,52.363979],"type":"Point"}
}
