{
  "type": "Feature",
  "properties": {
    "iso:country": "GB",
    "wof:name": "NE68 7AB",
    "wof:placetype": "postalcode"
  },
  "geometry": {"coordinates":[-1.651999,55.580031],"type":"Point"}
}
