{
  "type": "Feature",
  "properties": {
    "iso:country": "GB",
    "wof:name": "KA21 6FH",
    "wof:placetype": "postalcode"
  },
  "geometry": {"coordinates":[-4.779177,55.653967],"type":"Point"}
}
