{
  "type": "Feature",
  "properties": {
    "iso:country": "GB",
    "wof:name": "N22 5HF",
    "wof:placetype": "postalcode"
  },
  "geometry": {"coordinates":[-0.108097,51.596507],"type":"Point"}
}
