{
  "type": "Feature",
  "properties": {
    "iso:country": "GB",
    "wof:name": "NR16 1FH",
    "wof:placetype": "postalcode"
  },
  "geometry": {"coordinates":[1.149935,52.53322],"type":"Point"}
}
