{
  "type": "Feature",
  "properties": {
    "iso:country": "GB",
    "wof:name": "PL16 0HE",
    "wof:placetype": "postalcode"
  },
  "geometry": {"coordinates":[-4.228464,50.622633],"type":"Point"}
}
