{
  "type": "Feature",
  "properties": {
    "iso:country": "GB",
    "wof:name": "HX2 8UH",
    "wof:placetype": "postalcode"
  },
  "geometry": {"coordinates":[-1.903972,53.757435],"type":"Point"}
}
