{
  "type": "Feature",
  "properties": {
    "iso:country": "GB",
    "wof:name": "WA11 0JN",
    "wof:placetype": "postalcode"
  },
  "geometry": {"coordinates":[-2.671991,53.465192],"type":"Point"}
}
