{
  "type": "Feature",
  "properties": {
    "iso:country": "GB",
    "wof:name": "GL19 3LH",
    "wof:placetype": "postalcode"
  },
  "geometry": {"coordinates":[-2.360518,51.981434],"type":"Point"}
}
