{
  "type": "Feature",
  "properties": {
    "iso:country": "GB",
    "wof:name": "TN5 6LU",
    "wof:placetype": "postalcode"
  },
  "geometry": {"coordinates":[0.34066,51.047565],"type":"Point"}
}
