{
  "type": "Feature",
  "properties": {
    "iso:country": "GB",
    "wof:name": "EX2 6FW",
    "wof:placetype": "postalcode"
  },
  "geometry": {"coordinates":[-3.500605,50.713668],"type":"Point"}
}
