{
  "type": "Feature",
  "properties": {
    "iso:country": "GB",
    "wof:name": "TA9 4DN",
    "wof:placetype": "postalcode"
  },
  "geometry": {"coordinates":[-2.946489,51.243971],"type":"Point"}
}
