{
  "type": "Feature",
  "properties": {
    "iso:country": "GB",
    "wof:name": "ME8 8FX",
    "wof:placetype": "postalcode"
  },
  "geometry": {"coordinates":[0.62927,51.368593],"type":"Point"}
}
