{
  "type": "Feature",
  "properties": {
    "iso:country": "GB",
    "wof:name": "PE25 2SR",
    "wof:placetype": "postalcode"
  },
  "geometry": {"coordinates":[0.315502,53.149786],"type":"Point"}
}
