{
  "type": "Feature",
  "properties": {
    "iso:country": "GB",
    "wof:name": "DN21 1ZS",
    "wof:placetype": "postalcode"
  },
  "geometry": {"coordinates":[-0.757278,53.4077],"type":"Point"}
}
