{
  "type": "Feature",
  "properties": {
    "iso:country": "GB",
    "wof:name": "FY6 0FH",
    "wof:placetype": "postalcode"
  },
  "geometry": {"coordinates":[-2.951844,53.900767],"type":"Point"}
}
