{
  "type": "Feature",
  "properties": {
    "iso:country": "GB",
    "wof:name": "SG5 4TE",
    "wof:placetype": "postalcode"
  },
  "geometry": {"coordinates":[-0.226005,52.025314],"type":"Point"}
}
