{
  "type": "Feature",
  "properties": {
    "iso:country": "GB",
    "wof:name": "WA7 1HL",
    "wof:placetype": "postalcode"
  },
  "geometry": {"coordinates":[-2.738678,53.342876],"type":"Point"}
}
