{
  "type": "Feature",
  "properties": {
    "iso:country": "GB",
    "wof:name": "ME9 7FW",
    "wof:placetype": "postalcode"
  },
  "geometry": {"coordinates":[0.672921,51.352801],"type":"Point"}
}
