{
  "type": "Feature",
  "properties": {
    "iso:country": "GB",
    "wof:name": "PO33 1DN",
    "wof:placetype": "postalcode"
  },
  "geometry": {"coordinates":[-1.150467,50.721782],"type":"Point"}
}
