{
  "type": "Feature",
  "properties": {
    "iso:country": "GB",
    "wof:name": "HU15 2AH",
    "wof:placetype": "postalcode"
  },
  "geometry": {"coordinates":[-0.607222,53.795863],"type":"Point"}
}
