{
  "type": "Feature",
  "properties": {
    "iso:country": "GB",
    "wof:name": "CH62 4SW",
    "wof:placetype": "postalcode"
  },
  "geometry": {"coordinates":[-2.987856,53.352407],"type":"Point"}
}
