{
  "type": "Feature",
  "properties": {
    "iso:country": "GB",
    "wof:name": "OX12 7FR",
    "wof:placetype": "postalcode"
  },
  "geometry": {"coordinates":[-1.414799,51.615668],"type":"Point"}
}
