{
  "type": "Feature",
  "properties": {
    "iso:country": "GB",
    "wof:name": "EX14 1JA",
    "wof:placetype": "postalcode"
  },
  "geometry": {"coordinates":[-3.191816,50.79856],"type":"Point"}
}
