{
  "type": "Feature",
  "properties": {
    "iso:country": "GB",
    "wof:name": "LN1 2ZU",
    "wof:placetype": "postalcode"
  },
  "geometry": {"coordinates":[-0.742963,53.291454],"type":"Point"}
}
