{
  "type": "Feature",
  "properties": {
    "iso:country": "GB",
    "wof:name": "AB21 9GY",
    "wof:placetype": "postalcode"
  },
  "geometry": {"coordinates":[-2.14251,57.176721],"type":"Point"}
}
