{
  "type": "Feature",
  "properties": {
    "iso:country": "GB",
    "wof:name": "AL6 0SF",
    "wof:placetype": "postalcode"
  },
  "geometry": {"coordinates":[-0.183412,51.842432],"type":"Point"}
}
