{
  "type": "Feature",
  "properties": {
    "iso:country": "GB",
    "wof:name": "BH1 3FE",
    "wof:placetype": "postalcode"
  },
  "geometry": {"coordinates":[-1.853153,50.724981],"type":"Point"}
}
