{
  "type": "Feature",
  "properties": {
    "iso:country": "GB",
    "wof:name": "SP4 8FP",
    "wof:placetype": "postalcode"
  },
  "geometry": {"coordinates":[-1.79398,51.200897],"type":"Point"}
}
