{
  "type": "Feature",
  "properties": {
    "iso:country": "GB",
    "wof:name": "CF31 1JX",
    "wof:placetype": "postalcode"
  },
  "geometry": {"coordinates":[-3.583593,51.514468],"type":"Point"}
}
