{
  "type": "Feature",
  "properties": {
    "iso:country": "GB",
    "wof:name": "PR4 5SW",
    "wof:placetype": "postalcode"
  },
  "geometry": {"coordinates":[-2.767496,53.718937],"type":"Point"}
}
