{
  "type": "Feature",
  "properties": {
    "iso:country": "GB",
    "wof:name": "PL31 2UD",
    "wof:placetype": "postalcode"
  },
  "geometry": {"coordinates":[-4.703303,50.467938],"type":"Point"}
}
