{
  "type": "Feature",
  "properties": {
    "iso:country": "GB",
    "wof:name": "CH5 3SS",
    "wof:placetype": "postalcode"
  },
  "geometry": {"coordinates":[-3.052533,53.185176],"type":"Point"}
}
