{
  "type": "Feature",
  "properties": {
    "iso:country": "GB",
    "wof:name": "OX11 6HR",
    "wof:placetype": "postalcode"
  },
  "geometry": {"coordinates":[-1.260952,51.598725],"type":"Point"}
}
