{
  "type": "Feature",
  "properties": {
    "iso:country": "GB",
    "wof:name": "WD3 4FF",
    "wof:placetype": "postalcode"
  },
  "geometry": {"coordinates":[-0.507159,51.697173],"type":"Point"}
}
