{
  "type": "Feature",
  "properties": {
    "iso:country": "GB",
    "wof:name": "LE67 4UD",
    "wof:placetype": "postalcode"
  },
  "geometry": {"coordinates":[-1.320481,52.723672],"type":"Point"}
}
