{
  "type": "Feature",
  "properties": {
    "iso:country": "GB",
    "wof:name": "L31 1LS",
    "wof:placetype": "postalcode"
  },
  "geometry": {"coordinates":[-2.917212,53.51654],"type":"Point"}
}
