{
  "type": "Feature",
  "properties": {
    "iso:country": "GB",
    "wof:name": "CW3 9TL",
    "wof:placetype": "postalcode"
  },
  "geometry": {"coordinates":[-2.403083,52.978431],"type":"Point"}
}
