{
  "type": "Feature",
  "properties": {
    "iso:country": "GB",
    "wof:name": "BR2 6ER",
    "wof:placetype": "postalcode"
  },
  "geometry": {"coordinates":[0.037193,51.362654],"type":"Point"}
}
