{
  "type": "Feature",
  "properties": {
    "iso:country": "GB",
    "wof:name": "MK18 1YD",
    "wof:placetype": "postalcode"
  },
  "geometry": {"coordinates":[-1.0007,51.996246],"type":"Point"}
}
