{
  "type": "Feature",
  "properties": {
    "iso:country": "GB",
    "wof:name": "SA11 5BT",
    "wof:placetype": "postalcode"
  },
  "geometry": {"coordinates":[-3.622409,51.746315],"type":"Point"}
}
