{
  "type": "Feature",
  "properties": {
    "iso:country": "GB",
    "wof:name": "M30 9NU",
    "wof:placetype": "postalcode"
  },
  "geometry": {"coordinates":[-2.348931,53.494087],"type":"Point"}
}
