{
  "type": "Feature",
  "properties": {
    "iso:country": "GB",
    "wof:name": "KW10 6UE",
    "wof:placetype": "postalcode"
  },
  "geometry": {"coordinates":[-3.994973,57.972566],"type":"Point"}
}
