{
  "type": "Feature",
  "properties": {
    "iso:country": "GB",
    "wof:name": "NR6 6FE",
    "wof:placetype": "postalcode"
  },
  "geometry": {"coordinates":[1.284308,52.661342],"type":"Point"}
}
