{
  "type": "Feature",
  "properties": {
    "iso:country": "GB",
    "wof:name": "CM8 3GB",
    "wof:placetype": "postalcode"
  },
  "geometry": {"coordinates":[0.677559,51.77711],"type":"Point"}
}
