{
  "type": "Feature",
  "properties": {
    "iso:country": "GB",
    "wof:name": "DE15 9RY",
    "wof:placetype": "postalcode"
  },
  "geometry": {"coordinates":[-1.622289,52.789399],"type":"Point"}
}
