{
  "type": "Feature",
  "properties": {
    "iso:country": "GB",
    "wof:name": "SL6 1NQ",
    "wof:placetype": "postalcode"
  },
  "geometry": {"coordinates":[-0.70784,51.523255],"type":"Point"}
}
