{
  "type": "Feature",
  "properties": {
    "iso:country": "GB",
    "wof:name": "BS16 1YL",
    "wof:placetype": "postalcode"
  },
  "geometry": {"coordinates":[-2.539204,51.498706],"type":"Point"}
}
