{
  "type": "Feature",
  "properties": {
    "iso:country": "GB",
    "wof:name": "NN11 6JP",
    "wof:placetype": "postalcode"
  },
  "geometry": {"coordinates":[-1.213652,52.242601],"type":"Point"}
}
