{
  "type": "Feature",
  "properties": {
    "iso:country": "GB",
    "wof:name": "EH26 0FY",
    "wof:placetype": "postalcode"
  },
  "geometry": {"coordinates":[-3.224712,55.844868],"type":"Point"}
}
