{
  "type": "Feature",
  "properties": {
    "iso:country": "GB",
    "wof:name": "DN17 1PS",
    "wof:placetype": "postalcode"
  },
  "geometry": {"coordinates":[-0.677287,53.572097],"type":"Point"}
}
