{
  "type": "Feature",
  "properties": {
    "iso:country": "GB",
    "wof:name": "YO32 9YA",
    "wof:placetype": "postalcode"
  },
  "geometry": {"coordinates":[-1.054035,54.002575],"type":"Point"}
}
