{
  "type": "Feature",
  "properties": {
    "iso:country": "GB",
    "wof:name": "BL8 3DP",
    "wof:placetype": "postalcode"
  },
  "geometry": {"coordinates":[-2.327651,53.605773],"type":"Point"}
}
