{
  "type": "Feature",
  "properties": {
    "iso:country": "GB",
    "wof:name": "WN8 6EU",
    "wof:placetype": "postalcode"
  },
  "geometry": {"coordinates":[-2.770477,53.566744],"type":"Point"}
}
