{
  "type": "Feature",
  "properties": {
    "iso:country": "GB",
    "wof:name": "BL2 1DB",
    "wof:placetype": "postalcode"
  },
  "geometry": {"coordinates":[-2.421938,53.575358],"type":"Point"}
}
