{
  "type": "Feature",
  "properties": {
    "iso:country": "GB",
    "wof:name": "RG42 4GL",
    "wof:placetype": "postalcode"
  },
  "geometry": {"coordinates":[-0.791129,51.417479],"type":"Point"}
}
