{
  "type": "Feature",
  "properties": {
    "iso:country": "GB",
    "wof:name": "TS24 9BW",
    "wof:placetype": "postalcode"
  },
  "geometry": {"coordinates":[-1.22725,54.704669],"type":"Point"}
}
