{
  "type": "Feature",
  "properties": {
    "iso:country": "GB",
    "wof:name": "MK18 1XZ",
    "wof:placetype": "postalcode"
  },
  "geometry": {"coordinates":[-1.002065,51.996428],"type":"Point"}
}
