{
  "type": "Feature",
  "properties": {
    "iso:country": "GB",
    "wof:name": "OL13 8RX",
    "wof:placetype": "postalcode"
  },
  "geometry": {"coordinates":[-2.199389,53.724177],"type":"Point"}
}
