{
  "type": "Feature",
  "properties": {
    "iso:country": "GB",
    "wof:name": "TF1 1PS",
    "wof:placetype": "postalcode"
  },
  "geometry": {"coordinates":[-2.515778,52.700633],"type":"Point"}
}
