{
  "type": "Feature",
  "properties": {
    "iso:country": "GB",
    "wof:name": "CV31 3NY",
    "wof:placetype": "postalcode"
  },
  "geometry": {"coordinates":[-1.5503,52.283146],"type":"Point"}
}
