{
  "type": "Feature",
  "properties": {
    "iso:country": "GB",
    "wof:name": "CM2 8TG",
    "wof:placetype": "postalcode"
  },
  "geometry": {"coordinates":[0.442654,51.709202],"type":"Point"}
}
