{
  "type": "Feature",
  "properties": {
    "iso:country": "GB",
    "wof:name": "TR8 4JG",
    "wof:placetype": "postalcode"
  },
  "geometry": {"coordinates":[-4.9653,50.430006],"type":"Point"}
}
