{
  "type": "Feature",
  "properties": {
    "iso:country": "GB",
    "wof:name": "N17 6FF",
    "wof:placetype": "postalcode"
  },
  "geometry": {"coordinates":[-0.07041,51.590776],"type":"Point"}
}
