{
  "type": "Feature",
  "properties": {
    "iso:country": "GB",
    "wof:name": "DN22 6UN",
    "wof:placetype": "postalcode"
  },
  "geometry": {"coordinates":[-0.937202,53.334863],"type":"Point"}
}
