{
  "type": "Feature",
  "properties": {
    "iso:country": "GB",
    "wof:name": "DA11 9QY",
    "wof:placetype": "postalcode"
  },
  "geometry": {"coordinates":[0.336541,51.440251],"type":"Point"}
}
