{
  "type": "Feature",
  "properties": {
    "iso:country": "GB",
    "wof:name": "DE73 6WE",
    "wof:placetype": "postalcode"
  },
  "geometry": {"coordinates":[-1.432688,52.877543],"type":"Point"}
}
