{
  "type": "Feature",
  "properties": {
    "iso:country": "GB",
    "wof:name": "B90 1GQ",
    "wof:placetype": "postalcode"
  },
  "geometry": {"coordinates":[-1.865759,52.405598],"type":"Point"}
}
