{
  "type": "Feature",
  "properties": {
    "iso:country": "GB",
    "wof:name": "CT13 0EB",
    "wof:placetype": "postalcode"
  },
  "geometry": {"coordinates":[1.305396,51.250079],"type":"Point"}
}
