{
  "type": "Feature",
  "properties": {
    "iso:country": "GB",
    "wof:name": "RG45 6HZ",
    "wof:placetype": "postalcode"
  },
  "geometry": {"coordinates":[-0.789213,51.377327],"type":"Point"}
}
