{
  "type": "Feature",
  "properties": {
    "iso:country": "GB",
    "wof:name": "S44 6FS",
    "wof:placetype": "postalcode"
  },
  "geometry": {"coordinates":[-1.272807,53.226274],"type":"Point"}
}
