{
  "type": "Feature",
  "properties": {
    "iso:country": "GB",
    "wof:name": "SO45 1FT",
    "wof:placetype": "postalcode"
  },
  "geometry": {"coordinates":[-1.354112,50.82575],"type":"Point"}
}
