{
  "type": "Feature",
  "properties": {
    "iso:country": "GB",
    "wof:name": "IP22 1LP",
    "wof:placetype": "postalcode"
  },
  "geometry": {"coordinates":[1.00154,52.325914],"type":"Point"}
}
