{
  "type": "Feature",
  "properties": {
    "iso:country": "GB",
    "wof:name": "WV3 7BD",
    "wof:placetype": "postalcode"
  },
  "geometry": {"coordinates":[-2.156322,52.571598],"type":"Point"}
}
