{
  "type": "Feature",
  "properties": {
    "iso:country": "GB",
    "wof:name": "RH15 9HS",
    "wof:placetype": "postalcode"
  },
  "geometry": {"coordinates":[-0.150763,50.956199],"type":"Point"}
}
