{
  "type": "Feature",
  "properties": {
    "iso:country": "GB",
    "wof:name": "RM20 4BY",
    "wof:placetype": "postalcode"
  },
  "geometry": {"coordinates":[0.305459,51.478845],"type":"Point"}
}
