{
  "type": "Feature",
  "properties": {
    "iso:country": "GB",
    "wof:name": "NN3 7DZ",
    "wof:placetype": "postalcode"
  },
  "geometry": {"coordinates":[-0.842589,52.291324],"type":"Point"}
}
