{
  "type": "Feature",
  "properties": {
    "iso:country": "GB",
    "wof:name": "SE25 6PN",
    "wof:placetype": "postalcode"
  },
  "geometry": {"coordinates":[-0.078627,51.39987],"type":"Point"}
}
