{
  "type": "Feature",
  "properties": {
    "iso:country": "GB",
    "wof:name": "BS16 7LY",
    "wof:placetype": "postalcode"
  },
  "geometry": {"coordinates":[-2.465379,51.496441],"type":"Point"}
}
