{
  "type": "Feature",
  "properties": {
    "iso:country": "GB",
    "wof:name": "CM7 2DB",
    "wof:placetype": "postalcode"
  },
  "geometry": {"coordinates":[0.531109,51.878669],"type":"Point"}
}
