{
  "type": "Feature",
  "properties": {
    "iso:country": "GB",
    "wof:name": "RH10 3GD",
    "wof:placetype": "postalcode"
  },
  "geometry": {"coordinates":[-0.132979,51.135024],"type":"Point"}
}
