{
  "type": "Feature",
  "properties": {
    "iso:country": "GB",
    "wof:name": "CV36 4RL",
    "wof:placetype": "postalcode"
  },
  "geometry": {"coordinates":[-1.629844,52.083293],"type":"Point"}
}
