{
  "type": "Feature",
  "properties": {
    "iso:country": "GB",
    "wof:name": "LA16 7FA",
    "wof:placetype": "postalcode"
  },
  "geometry": {"coordinates":[-3.205616,54.189537],"type":"Point"}
}
