{
  "type": "Feature",
  "properties": {
    "iso:country": "GB",
    "wof:name": "CA24 3AB",
    "wof:placetype": "postalcode"
  },
  "geometry": {"coordinates":[-3.545379,54.51484],"type":"Point"}
}
