{
  "type": "Feature",
  "properties": {
    "iso:country": "GB",
    "wof:name": "TF11 8FY",
    "wof:placetype": "postalcode"
  },
  "geometry": {"coordinates":[-2.376564,52.675796],"type":"Point"}
}
