{
  "type": "Feature",
  "properties": {
    "iso:country": "GB",
    "wof:name": "SK10 4DW",
    "wof:placetype": "postalcode"
  },
  "geometry": {"coordinates":[-2.150155,53.291622],"type":"Point"}
}
