{
  "type": "Feature",
  "properties": {
    "iso:country": "GB",
    "wof:name": "CO11 2QH",
    "wof:placetype": "postalcode"
  },
  "geometry": {"coordinates":[1.096013,51.936252],"type":"Point"}
}
