{
  "type": "Feature",
  "properties": {
    "iso:country": "GB",
    "wof:name": "CW1 3FX",
    "wof:placetype": "postalcode"
  },
  "geometry": {"coordinates":[-2.455804,53.104207],"type":"Point"}
}
