{
  "type": "Feature",
  "properties": {
    "iso:country": "GB",
    "wof:name": "DY4 8ER",
    "wof:placetype": "postalcode"
  },
  "geometry": {"coordinates":[-2.076436,52.527285],"type":"Point"}
}
