{
  "type": "Feature",
  "properties": {
    "iso:country": "GB",
    "wof:name": "NN12 8GB",
    "wof:placetype": "postalcode"
  },
  "geometry": {"coordinates":[-1.122562,52.156016],"type":"Point"}
}
