{
  "type": "Feature",
  "properties": {
    "iso:country": "GB",
    "wof:name": "LE9 7NU",
    "wof:placetype": "postalcode"
  },
  "geometry": {"coordinates":[-1.269858,52.575334],"type":"Point"}
}
