{
  "type": "Feature",
  "properties": {
    "iso:country": "GB",
    "wof:name": "LN9 5GB",
    "wof:placetype": "postalcode"
  },
  "geometry": {"coordinates":[-0.129331,53.209656],"type":"Point"}
}
