{
  "type": "Feature",
  "properties": {
    "iso:country": "GB",
    "wof:name": "TR14 0GL",
    "wof:placetype": "postalcode"
  },
  "geometry": {"coordinates":[-5.284898,50.231616],"type":"Point"}
}
