{
  "type": "Feature",
  "properties": {
    "iso:country": "GB",
    "wof:name": "G76 9AY",
    "wof:placetype": "postalcode"
  },
  "geometry": {"coordinates":[-4.231616,55.790114],"type":"Point"}
}
