{
  "type": "Feature",
  "properties": {
    "iso:country": "GB",
    "wof:name": "PL31 2TA",
    "wof:placetype": "postalcode"
  },
  "geometry": {"coordinates":[-4.749235,50.471602],"type":"Point"}
}
