{
  "type": "Feature",
  "properties": {
    "iso:country": "GB",
    "wof:name": "NR20 4WF",
    "wof:placetype": "postalcode"
  },
  "geometry": {"coordinates":[1.029033,52.744478],"type":"Point"}
}
