{
  "type": "Feature",
  "properties": {
    "iso:country": "GB",
    "wof:name": "SE14 5SJ",
    "wof:placetype": "postalcode"
  },
  "geometry": {"coordinates":[-0.046893,51.466441],"type":"Point"}
}
