{
  "type": "Feature",
  "properties": {
    "iso:country": "GB",
    "wof:name": "SG15 6AQ",
    "wof:placetype": "postalcode"
  },
  "geometry": {"coordinates":[-0.264544,52.017004],"type":"Point"}
}
