{
  "type": "Feature",
  "properties": {
    "iso:country": "GB",
    "wof:name": "YO42 4SW",
    "wof:placetype": "postalcode"
  },
  "geometry": {"coordinates":[-0.890068,53.876814],"type":"Point"}
}
