{
  "type": "Feature",
  "properties": {
    "iso:country": "GB",
    "wof:name": "SO16 0BH",
    "wof:placetype": "postalcode"
  },
  "geometry": {"coordinates":[-1.462632,50.941576],"type":"Point"}
}
