{
  "type": "Feature",
  "properties": {
    "iso:country": "GB",
    "wof:name": "HP18 9NR",
    "wof:placetype": "postalcode"
  },
  "geometry": {"coordinates":[-1.024525,51.825799],"type":"Point"}
}
