{
  "type": "Feature",
  "properties": {
    "iso:country": "GB",
    "wof:name": "TR2 4FU",
    "wof:placetype": "postalcode"
  },
  "geometry": {"coordinates":[-4.95607,50.320891],"type":"Point"}
}
