{
  "type": "Feature",
  "properties": {
    "iso:country": "GB",
    "wof:name": "CM20 1SB",
    "wof:placetype": "postalcode"
  },
  "geometry": {"coordinates":[0.076684,51.770557],"type":"Point"}
}
