{
  "type": "Feature",
  "properties": {
    "iso:country": "GB",
    "wof:name": "OX29 8FX",
    "wof:placetype": "postalcode"
  },
  "geometry": {"coordinates":[-1.373837,51.824445],"type":"Point"}
}
