{
  "type": "Feature",
  "properties": {
    "iso:country": "GB",
    "wof:name": "CA28 9BQ",
    "wof:placetype": "postalcode"
  },
  "geometry": {"coordinates":[-3.588845,54.524657],"type":"Point"}
}
