{
  "type": "Feature",
  "properties": {
    "iso:country": "GB",
    "wof:name": "MK17 8HB",
    "wof:placetype": "postalcode"
  },
  "geometry": {"coordinates":[-0.662301,52.03362],"type":"Point"}
}
