{
  "type": "Feature",
  "properties": {
    "iso:country": "GB",
    "wof:name": "CV10 9HL",
    "wof:placetype": "postalcode"
  },
  "geometry": {"coordinates":[-1.506142,52.528889],"type":"Point"}
}
