{
  "type": "Feature",
  "properties": {
    "iso:country": "GB",
    "wof:name": "MK45 3NT",
    "wof:placetype": "postalcode"
  },
  "geometry": {"coordinates":[-0.484229,52.081025],"type":"Point"}
}
