{
  "type": "Feature",
  "properties": {
    "iso:country": "GB",
    "wof:name": "SY23 4LF",
    "wof:placetype": "postalcode"
  },
  "geometry": {"coordinates":[-3.952154,52.370488],"type":"Point"}
}
