{
  "type": "Feature",
  "properties": {
    "iso:country": "GB",
    "wof:name": "BS10 7UD",
    "wof:placetype": "postalcode"
  },
  "geometry": {"coordinates":[-2.605753,51.526381],"type":"Point"}
}
