{
  "type": "Feature",
  "properties": {
    "iso:country": "GB",
    "wof:name": "BS40 8SP",
    "wof:placetype": "postalcode"
  },
  "geometry": {"coordinates":[-2.609464,51.364762],"type":"Point"}
}
