{
  "type": "Feature",
  "properties": {
    "iso:country": "GB",
    "wof:name": "BH21 2FT",
    "wof:placetype": "postalcode"
  },
  "geometry": {"coordinates":[-1.964711,50.795653],"type":"Point"}
}
