{
  "type": "Feature",
  "properties": {
    "iso:country": "GB",
    "wof:name": "HU3 5DF",
    "wof:placetype": "postalcode"
  },
  "geometry": {"coordinates":[-0.376945,53.734187],"type":"Point"}
}
