{
  "type": "Feature",
  "properties": {
    "iso:country": "GB",
    "wof:name": "DE55 7SP",
    "wof:placetype": "postalcode"
  },
  "geometry": {"coordinates":[-1.367735,53.096493],"type":"Point"}
}
