{
  "type": "Feature",
  "properties": {
    "iso:country": "GB",
    "wof:name": "IP13 9TF",
    "wof:placetype": "postalcode"
  },
  "geometry": {"coordinates":[1.326407,52.226923],"type":"Point"}
}
