{
  "type": "Feature",
  "properties": {
    "iso:country": "GB",
    "wof:name": "NP44 3FR",
    "wof:placetype": "postalcode"
  },
  "geometry": {"coordinates":[-3.034506,51.65061],"type":"Point"}
}
