{
  "type": "Feature",
  "properties": {
    "iso:country": "GB",
    "wof:name": "OX11 0GG",
    "wof:placetype": "postalcode"
  },
  "geometry": {"coordinates":[-1.32513,51.574222],"type":"Point"}
}
