{
  "type": "Feature",
  "properties": {
    "iso:country": "GB",
    "wof:name": "N19 4JU",
    "wof:placetype": "postalcode"
  },
  "geometry": {"coordinates":[-0.123231,51.562777],"type":"Point"}
}
