{
  "type": "Feature",
  "properties": {
    "iso:country": "GB",
    "wof:name": "B60 4FQ",
    "wof:placetype": "postalcode"
  },
  "geometry": {"coordinates":[-2.080259,52.296308],"type":"Point"}
}
