{
  "type": "Feature",
  "properties": {
    "iso:country": "GB",
    "wof:name": "PL9 7BG",
    "wof:placetype": "postalcode"
  },
  "geometry": {"coordinates":[-4.095667,50.36822],"type":"Point"}
}
