{
  "type": "Feature",
  "properties": {
    "iso:country": "GB",
    "wof:name": "ME8 7FB",
    "wof:placetype": "postalcode"
  },
  "geometry": {"coordinates":[0.605235,51.370668],"type":"Point"}
}
