{
  "type": "Feature",
  "properties": {
    "iso:country": "GB",
    "wof:name": "BB7 2RW",
    "wof:placetype": "postalcode"
  },
  "geometry": {"coordinates":[-2.402525,53.872427],"type":"Point"}
}
