{
  "type": "Feature",
  "properties": {
    "iso:country": "GB",
    "wof:name": "BN3 3EQ",
    "wof:placetype": "postalcode"
  },
  "geometry": {"coordinates":[-0.161395,50.832806],"type":"Point"}
}
