{
  "type": "Feature",
  "properties": {
    "iso:country": "GB",
    "wof:name": "IP14 5TY",
    "wof:placetype": "postalcode"
  },
  "geometry": {"coordinates":[1.080445,52.249585],"type":"Point"}
}
