{
  "type": "Feature",
  "properties": {
    "iso:country": "GB",
    "wof:name": "PE12 6JH",
    "wof:placetype": "postalcode"
  },
  "geometry": {"coordinates":[-0.083411,52.805536],"type":"Point"}
}
