{
  "type": "Feature",
  "properties": {
    "iso:country": "GB",
    "wof:name": "BS24 7NL",
    "wof:placetype": "postalcode"
  },
  "geometry": {"coordinates":[-2.908178,51.337011],"type":"Point"}
}
