{
  "type": "Feature",
  "properties": {
    "iso:country": "GB",
    "wof:name": "L25 7BH",
    "wof:placetype": "postalcode"
  },
  "geometry": {"coordinates":[-2.881136,53.370241],"type":"Point"}
}
