{
  "type": "Feature",
  "properties": {
    "iso:country": "GB",
    "wof:name": "NN6 7XP",
    "wof:placetype": "postalcode"
  },
  "geometry": {"coordinates":[-1.08465,52.296074],"type":"Point"}
}
