{
  "type": "Feature",
  "properties": {
    "iso:country": "GB",
    "wof:name": "SW11 2FU",
    "wof:placetype": "postalcode"
  },
  "geometry": {"coordinates":[-0.169284,51.466483],"type":"Point"}
}
