{
  "type": "Feature",
  "properties": {
    "iso:country": "GB",
    "wof:name": "BS5 8QX",
    "wof:placetype": "postalcode"
  },
  "geometry": {"coordinates":[-2.525813,51.45299],"type":"Point"}
}
