{
  "type": "Feature",
  "properties": {
    "iso:country": "GB",
    "wof:name": "YO61 4SL",
    "wof:placetype": "postalcode"
  },
  "geometry": {"coordinates":[-1.103917,54.162697],"type":"Point"}
}
