{
  "type": "Feature",
  "properties": {
    "iso:country": "GB",
    "wof:name": "EH11 4FW",
    "wof:placetype": "postalcode"
  },
  "geometry": {"coordinates":[-3.305653,55.924888],"type":"Point"}
}
