{
  "type": "Feature",
  "properties": {
    "iso:country": "GB",
    "wof:name": "DE65 5QU",
    "wof:placetype": "postalcode"
  },
  "geometry": {"coordinates":[-1.624936,52.864506],"type":"Point"}
}
