{
  "type": "Feature",
  "properties": {
    "iso:country": "GB",
    "wof:name": "FY6 7XN",
    "wof:placetype": "postalcode"
  },
  "geometry": {"coordinates":[-2.973922,53.846194],"type":"Point"}
}
