{
  "type": "Feature",
  "properties": {
    "iso:country": "GB",
    "wof:name": "NE15 6BW",
    "wof:placetype": "postalcode"
  },
  "geometry": {"coordinates":[-1.675878,54.969053],"type":"Point"}
}
