{
  "type": "Feature",
  "properties": {
    "iso:country": "GB",
    "wof:name": "KT16 0BP",
    "wof:placetype": "postalcode"
  },
  "geometry": {"coordinates":[-0.540029,51.384207],"type":"Point"}
}
