{
  "type": "Feature",
  "properties": {
    "iso:country": "GB",
    "wof:name": "CB25 9HY",
    "wof:placetype": "postalcode"
  },
  "geometry": {"coordinates":[0.188135,52.266013],"type":"Point"}
}
