{
  "type": "Feature",
  "properties": {
    "iso:country": "GB",
    "wof:name": "SA15 5HB",
    "wof:placetype": "postalcode"
  },
  "geometry": {"coordinates":[-4.19138,51.729528],"type":"Point"}
}
