{
  "type": "Feature",
  "properties": {
    "iso:country": "GB",
    "wof:name": "OX26 6GQ",
    "wof:placetype": "postalcode"
  },
  "geometry": {"coordinates":[-1.141877,51.899561],"type":"Point"}
}
