{
  "type": "Feature",
  "properties": {
    "iso:country": "GB",
    "wof:name": "PO18 9AW",
    "wof:placetype": "postalcode"
  },
  "geometry": {"coordinates":[-0.814549,50.861086],"type":"Point"}
}
