{
  "type": "Feature",
  "properties": {
    "iso:country": "GB",
    "wof:name": "ST10 2PH",
    "wof:placetype": "postalcode"
  },
  "geometry": {"coordinates":[-2.047773,52.986766],"type":"Point"}
}
