{
  "type": "Feature",
  "properties": {
    "iso:country": "GB",
    "wof:name": "BA4 4GB",
    "wof:placetype": "postalcode"
  },
  "geometry": {"coordinates":[-2.620977,51.171839],"type":"Point"}
}
