{
  "type": "Feature",
  "properties": {
    "iso:country": "GB",
    "wof:name": "HP11 1FD",
    "wof:placetype": "postalcode"
  },
  "geometry": {"coordinates":[-0.743417,51.619442],"type":"Point"}
}
