{
  "type": "Feature",
  "properties": {
    "iso:country": "GB",
    "wof:name": "IG7 5PT",
    "wof:placetype": "postalcode"
  },
  "geometry": {"coordinates":[0.086461,51.612165],"type":"Point"}
}
