{
  "type": "Feature",
  "properties": {
    "iso:country": "GB",
    "wof:name": "YO32 9RX",
    "wof:placetype": "postalcode"
  },
  "geometry": {"coordinates":[-1.053485,53.996558],"type":"Point"}
}
