{
  "type": "Feature",
  "properties": {
    "iso:country": "GB",
    "wof:name": "ME13 8GX",
    "wof:placetype": "postalcode"
  },
  "geometry": {"coordinates":[0.911433,51.311156],"type":"Point"}
}
