{
  "type": "Feature",
  "properties": {
    "iso:country": "GB",
    "wof:name": "PE7 3HH",
    "wof:placetype": "postalcode"
  },
  "geometry": {"coordinates":[-0.305105,52.528981],"type":"Point"}
}
