{
  "type": "Feature",
  "properties": {
    "iso:country": "GB",
    "wof:name": "NG23 6HH",
    "wof:placetype": "postalcode"
  },
  "geometry": {"coordinates":[-0.808755,53.114552],"type":"Point"}
}
