{
  "type": "Feature",
  "properties": {
    "iso:country": "GB",
    "wof:name": "RG42 6DT",
    "wof:placetype": "postalcode"
  },
  "geometry": {"coordinates":[-0.746051,51.430916],"type":"Point"}
}
