{
  "type": "Feature",
  "properties": {
    "iso:country": "GB",
    "wof:name": "TF10 8FA",
    "wof:placetype": "postalcode"
  },
  "geometry": {"coordinates":[-2.475121,52.776207],"type":"Point"}
}
