{
  "type": "Feature",
  "properties": {
    "iso:country": "GB",
    "wof:name": "SK10 2HD",
    "wof:placetype": "postalcode"
  },
  "geometry": {"coordinates":[-2.126523,53.275101],"type":"Point"}
}
