{
  "type": "Feature",
  "properties": {
    "iso:country": "GB",
    "wof:name": "PH33 6EE",
    "wof:placetype": "postalcode"
  },
  "geometry": {"coordinates":[-5.114939,56.815379],"type":"Point"}
}
