{
  "type": "Feature",
  "properties": {
    "iso:country": "GB",
    "wof:name": "CB25 0FR",
    "wof:placetype": "postalcode"
  },
  "geometry": {"coordinates":[0.324992,52.288171],"type":"Point"}
}
