{
  "type": "Feature",
  "properties": {
    "iso:country": "GB",
    "wof:name": "CA13 9GW",
    "wof:placetype": "postalcode"
  },
  "geometry": {"coordinates":[-3.358979,54.666665],"type":"Point"}
}
