{
  "type": "Feature",
  "properties": {
    "iso:country": "GB",
    "wof:name": "LE9 2ES",
    "wof:placetype": "postalcode"
  },
  "geometry": {"coordinates":[-1.23183,52.628737],"type":"Point"}
}
