{
  "type": "Feature",
  "properties": {
    "iso:country": "GB",
    "wof:name": "DT10 2AU",
    "wof:placetype": "postalcode"
  },
  "geometry": {"coordinates":[-2.38361,50.889746],"type":"Point"}
}
