{
  "type": "Feature",
  "properties": {
    "iso:country": "GB",
    "wof:name": "TN23 1LQ",
    "wof:placetype": "postalcode"
  },
  "geometry": {"coordinates":[0.869418,51.149627],"type":"Point"}
}
