{
  "type": "Feature",
  "properties": {
    "iso:country": "GB",
    "wof:name": "MK17 8TT",
    "wof:placetype": "postalcode"
  },
  "geometry": {"coordinates":[-0.648348,52.007062],"type":"Point"}
}
