{
  "type": "Feature",
  "properties": {
    "iso:country": "GB",
    "wof:name": "BL6 5WG",
    "wof:placetype": "postalcode"
  },
  "geometry": {"coordinates":[-2.55136,53.594749],"type":"Point"}
}
