{
  "type": "Feature",
  "properties": {
    "iso:country": "GB",
    "wof:name": "LE16 7BZ",
    "wof:placetype": "postalcode"
  },
  "geometry": {"coordinates":[-0.939883,52.488538],"type":"Point"}
}
