{
  "type": "Feature",
  "properties": {
    "iso:country": "GB",
    "wof:name": "CM23 1BZ",
    "wof:placetype": "postalcode"
  },
  "geometry": {"coordinates":[0.157361,51.920557],"type":"Point"}
}
