{
  "type": "Feature",
  "properties": {
    "iso:country": "GB",
    "wof:name": "NP7 6PR",
    "wof:placetype": "postalcode"
  },
  "geometry": {"coordinates":[-3.005736,51.840814],"type":"Point"}
}
