{
  "type": "Feature",
  "properties": {
    "iso:country": "GB",
    "wof:name": "IP31 3QR",
    "wof:placetype": "postalcode"
  },
  "geometry": {"coordinates":[0.872771,52.25496],"type":"Point"}
}
