{
  "type": "Feature",
  "properties": {
    "iso:country": "GB",
    "wof:name": "CM17 0FP",
    "wof:placetype": "postalcode"
  },
  "geometry": {"coordinates":[0.150939,51.786704],"type":"Point"}
}
