{
  "type": "Feature",
  "properties": {
    "iso:country": "GB",
    "wof:name": "DD5 1DQ",
    "wof:placetype": "postalcode"
  },
  "geometry": {"coordinates":[-2.87888,56.46763],"type":"Point"}
}
