{
  "type": "Feature",
  "properties": {
    "iso:country": "GB",
    "wof:name": "GL9 1ES",
    "wof:placetype": "postalcode"
  },
  "geometry": {"coordinates":[-2.278118,51.538181],"type":"Point"}
}
