{
  "type": "Feature",
  "properties": {
    "iso:country": "GB",
    "wof:name": "YO21 3RT",
    "wof:placetype": "postalcode"
  },
  "geometry": {"coordinates":[-0.695194,54.505975],"type":"Point"}
}
