{
  "type": "Feature",
  "properties": {
    "iso:country": "GB",
    "wof:name": "WF1 5RB",
    "wof:placetype": "postalcode"
  },
  "geometry": {"coordinates":[-1.49096,53.674046],"type":"Point"}
}
