{
  "type": "Feature",
  "properties": {
    "iso:country": "GB",
    "wof:name": "SY15 6UF",
    "wof:placetype": "postalcode"
  },
  "geometry": {"coordinates":[-3.110213,52.57463],"type":"Point"}
}
