{
  "type": "Feature",
  "properties": {
    "iso:country": "GB",
    "wof:name": "MK10 7LB",
    "wof:placetype": "postalcode"
  },
  "geometry": {"coordinates":[-0.679922,52.04861],"type":"Point"}
}
