{
  "type": "Feature",
  "properties": {
    "iso:country": "GB",
    "wof:name": "BS15 3FW",
    "wof:placetype": "postalcode"
  },
  "geometry": {"coordinates":[-2.505401,51.449888],"type":"Point"}
}
