{
  "type": "Feature",
  "properties": {
    "iso:country": "GB",
    "wof:name": "DT1 1TU",
    "wof:placetype": "postalcode"
  },
  "geometry": {"coordinates":[-2.437838,50.71257],"type":"Point"}
}
