{
  "type": "Feature",
  "properties": {
    "iso:country": "GB",
    "wof:name": "WD25 7FF",
    "wof:placetype": "postalcode"
  },
  "geometry": {"coordinates":[-0.398818,51.696844],"type":"Point"}
}
