{
  "type": "Feature",
  "properties": {
    "iso:country": "GB",
    "wof:name": "HP18 9GG",
    "wof:placetype": "postalcode"
  },
  "geometry": {"coordinates":[-1.072726,51.770091],"type":"Point"}
}
