{
  "type": "Feature",
  "properties": {
    "iso:country": "GB",
    "wof:name": "SP7 8BP",
    "wof:placetype": "postalcode"
  },
  "geometry": {"coordinates":[-2.197221,51.007507],"type":"Point"}
}
