{
  "type": "Feature",
  "properties": {
    "iso:country": "GB",
    "wof:name": "BD14 6FB",
    "wof:placetype": "postalcode"
  },
  "geometry": {"coordinates":[-1.828368,53.782589],"type":"Point"}
}
