{
  "type": "Feature",
  "properties": {
    "iso:country": "GB",
    "wof:name": "DT2 8GD",
    "wof:placetype": "postalcode"
  },
  "geometry": {"coordinates":[-2.34677,50.747715],"type":"Point"}
}
