{
  "type": "Feature",
  "properties": {
    "iso:country": "GB",
    "wof:name": "EX20 1GU",
    "wof:placetype": "postalcode"
  },
  "geometry": {"coordinates":[-3.988786,50.747833],"type":"Point"}
}
