{
  "type": "Feature",
  "properties": {
    "iso:country": "GB",
    "wof:name": "MK19 7FG",
    "wof:placetype": "postalcode"
  },
  "geometry": {"coordinates":[-0.833846,52.115285],"type":"Point"}
}
