{
  "type": "Feature",
  "properties": {
    "iso:country": "GB",
    "wof:name": "EX15 2FN",
    "wof:placetype": "postalcode"
  },
  "geometry": {"coordinates":[-3.369281,50.894637],"type":"Point"}
}
