{
  "type": "Feature",
  "properties": {
    "iso:country": "GB",
    "wof:name": "DE6 5PZ",
    "wof:placetype": "postalcode"
  },
  "geometry": {"coordinates":[-1.644207,52.909242],"type":"Point"}
}
