{
  "type": "Feature",
  "properties": {
    "iso:country": "GB",
    "wof:name": "YO42 2ST",
    "wof:placetype": "postalcode"
  },
  "geometry": {"coordinates":[-0.773898,53.937712],"type":"Point"}
}
