{
  "type": "Feature",
  "properties": {
    "iso:country": "GB",
    "wof:name": "GL18 1UG",
    "wof:placetype": "postalcode"
  },
  "geometry": {"coordinates":[-2.415278,51.933944],"type":"Point"}
}
