{
  "type": "Feature",
  "properties": {
    "iso:country": "GB",
    "wof:name": "CB6 3UL",
    "wof:placetype": "postalcode"
  },
  "geometry": {"coordinates":[0.149409,52.349846],"type":"Point"}
}
