{
  "type": "Feature",
  "properties": {
    "iso:country": "GB",
    "wof:name": "PO22 9SB",
    "wof:placetype": "postalcode"
  },
  "geometry": {"coordinates":[-0.66253,50.802742],"type":"Point"}
}
