{
  "type": "Feature",
  "properties": {
    "iso:country": "GB",
    "wof:name": "BD11 2PR",
    "wof:placetype": "postalcode"
  },
  "geometry": {"coordinates":[-1.694433,53.743585],"type":"Point"}
}
