{
  "type": "Feature",
  "properties": {
    "iso:country": "GB",
    "wof:name": "DE24 0RN",
    "wof:placetype": "postalcode"
  },
  "geometry": {"coordinates":[-1.41399,52.892294],"type":"Point"}
}
