{
  "type": "Feature",
  "properties": {
    "iso:country": "GB",
    "wof:name": "SN12 8PN",
    "wof:placetype": "postalcode"
  },
  "geometry": {"coordinates":[-2.174692,51.371622],"type":"Point"}
}
