{
  "type": "Feature",
  "properties": {
    "iso:country": "GB",
    "wof:name": "CM77 6DJ",
    "wof:placetype": "postalcode"
  },
  "geometry": {"coordinates":[0.496476,51.882457],"type":"Point"}
}
