{
  "type": "Feature",
  "properties": {
    "iso:country": "GB",
    "wof:name": "CV47 2SH",
    "wof:placetype": "postalcode"
  },
  "geometry": {"coordinates":[-1.418393,52.187192],"type":"Point"}
}
