{
  "type": "Feature",
  "properties": {
    "iso:country": "GB",
    "wof:name": "NE1 2DS",
    "wof:placetype": "postalcode"
  },
  "geometry": {"coordinates":[-1.607576,54.970093],"type":"Point"}
}
