{
  "type": "Feature",
  "properties": {
    "iso:country": "GB",
    "wof:name": "S35 2US",
    "wof:placetype": "postalcode"
  },
  "geometry": {"coordinates":[-1.470062,53.464275],"type":"Point"}
}
