{
  "type": "Feature",
  "properties": {
    "iso:country": "GB",
    "wof:name": "NG21 9NP",
    "wof:placetype": "postalcode"
  },
  "geometry": {"coordinates":[-1.075679,53.193574],"type":"Point"}
}
