{
  "type": "Feature",
  "properties": {
    "iso:country": "GB",
    "wof:name": "SK17 7BR",
    "wof:placetype": "postalcode"
  },
  "geometry": {"coordinates":[-1.910707,53.266118],"type":"Point"}
}
