{
  "type": "Feature",
  "properties": {
    "iso:country": "GB",
    "wof:name": "NP13 9AN",
    "wof:placetype": "postalcode"
  },
  "geometry": {"coordinates":[-3.135492,51.741616],"type":"Point"}
}
