{
  "type": "Feature",
  "properties": {
    "iso:country": "GB",
    "wof:name": "ME18 5HY",
    "wof:placetype": "postalcode"
  },
  "geometry": {"coordinates":[0.398262,51.252497],"type":"Point"}
}
