{
  "type": "Feature",
  "properties": {
    "iso:country": "GB",
    "wof:name": "BS35 1AQ",
    "wof:placetype": "postalcode"
  },
  "geometry": {"coordinates":[-2.525547,51.618753],"type":"Point"}
}
