{
  "type": "Feature",
  "properties": {
    "iso:country": "GB",
    "wof:name": "PR26 7SN",
    "wof:placetype": "postalcode"
  },
  "geometry": {"coordinates":[-2.73308,53.692718],"type":"Point"}
}
