{
  "type": "Feature",
  "properties": {
    "iso:country": "GB",
    "wof:name": "WR12 7RJ",
    "wof:placetype": "postalcode"
  },
  "geometry": {"coordinates":[-1.851855,52.05624],"type":"Point"}
}
