{
  "type": "Feature",
  "properties": {
    "iso:country": "GB",
    "wof:name": "HP22 0AQ",
    "wof:placetype": "postalcode"
  },
  "geometry": {"coordinates":[-0.733867,51.803879],"type":"Point"}
}
