{
  "type": "Feature",
  "properties": {
    "iso:country": "GB",
    "wof:name": "FY4 5GS",
    "wof:placetype": "postalcode"
  },
  "geometry": {"coordinates":[-3.018118,53.783861],"type":"Point"}
}
