{
  "type": "Feature",
  "properties": {
    "iso:country": "GB",
    "wof:name": "NE6 3ES",
    "wof:placetype": "postalcode"
  },
  "geometry": {"coordinates":[-1.552901,54.967496],"type":"Point"}
}
