{
  "type": "Feature",
  "properties": {
    "iso:country": "GB",
    "wof:name": "WN7 2ET",
    "wof:placetype": "postalcode"
  },
  "geometry": {"coordinates":[-2.489297,53.503634],"type":"Point"}
}
