{
  "type": "Feature",
  "properties": {
    "iso:country": "GB",
    "wof:name": "G71 7FP",
    "wof:placetype": "postalcode"
  },
  "geometry": {"coordinates":[-4.09907,55.844485],"type":"Point"}
}
