{
  "type": "Feature",
  "properties": {
    "iso:country": "GB",
    "wof:name": "SP11 6QN",
    "wof:placetype": "postalcode"
  },
  "geometry": {"coordinates":[-1.444951,51.221991],"type":"Point"}
}
