{
  "type": "Feature",
  "properties": {
    "iso:country": "GB",
    "wof:name": "MK43 9SX",
    "wof:placetype": "postalcode"
  },
  "geometry": {"coordinates":[-0.504233,52.071525],"type":"Point"}
}
