{
  "type": "Feature",
  "properties": {
    "iso:country": "GB",
    "wof:name": "PL1 4TN",
    "wof:placetype": "postalcode"
  },
  "geometry": {"coordinates":[-4.174152,50.369487],"type":"Point"}
}
