{
  "type": "Feature",
  "properties": {
    "iso:country": "GB",
    "wof:name": "OL15 9AR",
    "wof:placetype": "postalcode"
  },
  "geometry": {"coordinates":[-2.082968,53.663062],"type":"Point"}
}
