{
  "type": "Feature",
  "properties": {
    "iso:country": "GB",
    "wof:name": "TR13 0EJ",
    "wof:placetype": "postalcode"
  },
  "geometry": {"coordinates":[-5.205213,50.150926],"type":"Point"}
}
