{
  "type": "Feature",
  "properties": {
    "iso:country": "GB",
    "wof:name": "DE4 2AD",
    "wof:placetype": "postalcode"
  },
  "geometry": {"coordinates":[-1.583832,53.11774],"type":"Point"}
}
