{
  "type": "Feature",
  "properties": {
    "iso:country": "GB",
    "wof:name": "CT20 3TU",
    "wof:placetype": "postalcode"
  },
  "geometry": {"coordinates":[1.138338,51.074421],"type":"Point"}
}
