{
  "type": "Feature",
  "properties": {
    "iso:country": "GB",
    "wof:name": "NR6 7RB",
    "wof:placetype": "postalcode"
  },
  "geometry": {"coordinates":[1.304314,52.652825],"type":"Point"}
}
