{
  "type": "Feature",
  "properties": {
    "iso:country": "GB",
    "wof:name": "CF71 7HY",
    "wof:placetype": "postalcode"
  },
  "geometry": {"coordinates":[-3.443201,51.45239],"type":"Point"}
}
