{
  "type": "Feature",
  "properties": {
    "iso:country": "GB",
    "wof:name": "PE19 5WD",
    "wof:placetype": "postalcode"
  },
  "geometry": {"coordinates":[-0.252004,52.288617],"type":"Point"}
}
