{
  "type": "Feature",
  "properties": {
    "iso:country": "GB",
    "wof:name": "YO21 3FR",
    "wof:placetype": "postalcode"
  },
  "geometry": {"coordinates":[-0.618198,54.49011],"type":"Point"}
}
