{
  "type": "Feature",
  "properties": {
    "iso:country": "GB",
    "wof:name": "SO50 7QL",
    "wof:placetype": "postalcode"
  },
  "geometry": {"coordinates":[-1.28252,50.967713],"type":"Point"}
}
