{
  "type": "Feature",
  "properties": {
    "iso:country": "GB",
    "wof:name": "IV30 8BD",
    "wof:placetype": "postalcode"
  },
  "geometry": {"coordinates":[-3.311422,57.627431],"type":"Point"}
}
