{
  "type": "Feature",
  "properties": {
    "iso:country": "GB",
    "wof:name": "RH19 1BA",
    "wof:placetype": "postalcode"
  },
  "geometry": {"coordinates":[-0.015778,51.127114],"type":"Point"}
}
