{
  "type": "Feature",
  "properties": {
    "iso:country": "GB",
    "wof:name": "TA11 6FA",
    "wof:placetype": "postalcode"
  },
  "geometry": {"coordinates":[-2.749283,51.051589],"type":"Point"}
}
