{
  "type": "Feature",
  "properties": {
    "iso:country": "GB",
    "wof:name": "SN12 6YW",
    "wof:placetype": "postalcode"
  },
  "geometry": {"coordinates":[-2.120194,51.368534],"type":"Point"}
}
