{
  "type": "Feature",
  "properties": {
    "iso:country": "GB",
    "wof:name": "SK10 5JW",
    "wof:placetype": "postalcode"
  },
  "geometry": {"coordinates":[-2.105731,53.29602],"type":"Point"}
}
