{
  "type": "Feature",
  "properties": {
    "iso:country": "GB",
    "wof:name": "DE23 2AB",
    "wof:placetype": "postalcode"
  },
  "geometry": {"coordinates":[-1.5106,52.88606],"type":"Point"}
}
