{
  "type": "Feature",
  "properties": {
    "iso:country": "GB",
    "wof:name": "NR14 6GG",
    "wof:placetype": "postalcode"
  },
  "geometry": {"coordinates":[1.472499,52.536232],"type":"Point"}
}
