{
  "type": "Feature",
  "properties": {
    "iso:country": "GB",
    "wof:name": "EX17 3FP",
    "wof:placetype": "postalcode"
  },
  "geometry": {"coordinates":[-3.645048,50.785286],"type":"Point"}
}
