{
  "type": "Feature",
  "properties": {
    "iso:country": "GB",
    "wof:name": "S44 6GF",
    "wof:placetype": "postalcode"
  },
  "geometry": {"coordinates":[-1.304255,53.223055],"type":"Point"}
}
