{
  "type": "Feature",
  "properties": {
    "iso:country": "GB",
    "wof:name": "SO51 0JH",
    "wof:placetype": "postalcode"
  },
  "geometry": {"coordinates":[-1.565559,51.033512],"type":"Point"}
}
