{
  "type": "Feature",
  "properties": {
    "iso:country": "GB",
    "wof:name": "PE12 7NN",
    "wof:placetype": "postalcode"
  },
  "geometry": {"coordinates":[0.013854,52.799699],"type":"Point"}
}
