{
  "type": "Feature",
  "properties": {
    "iso:country": "GB",
    "wof:name": "FY1 5BB",
    "wof:placetype": "postalcode"
  },
  "geometry": {"coordinates":[-3.056076,53.81101],"type":"Point"}
}
