{
  "type": "Feature",
  "properties": {
    "iso:country": "GB",
    "wof:name": "M28 3ZQ",
    "wof:placetype": "postalcode"
  },
  "geometry": {"coordinates":[-2.398022,53.537302],"type":"Point"}
}
