{
  "type": "Feature",
  "properties": {
    "iso:country": "GB",
    "wof:name": "RH16 4TR",
    "wof:placetype": "postalcode"
  },
  "geometry": {"coordinates":[-0.114957,50.986698],"type":"Point"}
}
