{
  "type": "Feature",
  "properties": {
    "iso:country": "GB",
    "wof:name": "WN6 0ZP",
    "wof:placetype": "postalcode"
  },
  "geometry": {"coordinates":[-2.675781,53.58897],"type":"Point"}
}
