{
  "type": "Feature",
  "properties": {
    "iso:country": "GB",
    "wof:name": "G74 4GR",
    "wof:placetype": "postalcode"
  },
  "geometry": {"coordinates":[-4.169414,55.765866],"type":"Point"}
}
