{
  "type": "Feature",
  "properties": {
    "iso:country": "GB",
    "wof:name": "TS20 1BF",
    "wof:placetype": "postalcode"
  },
  "geometry": {"coordinates":[-1.323299,54.593367],"type":"Point"}
}
