{
  "type": "Feature",
  "properties": {
    "iso:country": "GB",
    "wof:name": "SN12 6XZ",
    "wof:placetype": "postalcode"
  },
  "geometry": {"coordinates":[-2.126556,51.362908],"type":"Point"}
}
