{
  "type": "Feature",
  "properties": {
    "iso:country": "GB",
    "wof:name": "DL5 6AN",
    "wof:placetype": "postalcode"
  },
  "geometry": {"coordinates":[-1.619964,54.592889],"type":"Point"}
}
