{
  "type": "Feature",
  "properties": {
    "iso:country": "GB",
    "wof:name": "EX34 8AR",
    "wof:placetype": "postalcode"
  },
  "geometry": {"coordinates":[-4.125994,51.20926],"type":"Point"}
}
