{
  "type": "Feature",
  "properties": {
    "iso:country": "GB",
    "wof:name": "EH52 6FH",
    "wof:placetype": "postalcode"
  },
  "geometry": {"coordinates":[-3.474774,55.962966],"type":"Point"}
}
