{
  "type": "Feature",
  "properties": {
    "iso:country": "GB",
    "wof:name": "CH48 2AA",
    "wof:placetype": "postalcode"
  },
  "geometry": {"coordinates":[-3.174598,53.365422],"type":"Point"}
}
