{
  "type": "Feature",
  "properties": {
    "iso:country": "GB",
    "wof:name": "WD6 4DF",
    "wof:placetype": "postalcode"
  },
  "geometry": {"coordinates":[-0.279978,51.654788],"type":"Point"}
}
