{
  "type": "Feature",
  "properties": {
    "iso:country": "GB",
    "wof:name": "DT1 3ER",
    "wof:placetype": "postalcode"
  },
  "geometry": {"coordinates":[-2.458635,50.717481],"type":"Point"}
}
