{
  "type": "Feature",
  "properties": {
    "iso:country": "GB",
    "wof:name": "SN10 3LH",
    "wof:placetype": "postalcode"
  },
  "geometry": {"coordinates":[-1.940396,51.361172],"type":"Point"}
}
