{
  "type": "Feature",
  "properties": {
    "iso:country": "GB",
    "wof:name": "BD1 1LH",
    "wof:placetype": "postalcode"
  },
  "geometry": {"coordinates":[-1.752436,53.793997],"type":"Point"}
}
