{
  "type": "Feature",
  "properties": {
    "iso:country": "GB",
    "wof:name": "LE1 5BH",
    "wof:placetype": "postalcode"
  },
  "geometry": {"coordinates":[-1.137934,52.632766],"type":"Point"}
}
