{
  "type": "Feature",
  "properties": {
    "iso:country": "GB",
    "wof:name": "DL10 6RT",
    "wof:placetype": "postalcode"
  },
  "geometry": {"coordinates":[-1.615565,54.463284],"type":"Point"}
}
