{
  "type": "Feature",
  "properties": {
    "iso:country": "GB",
    "wof:name": "IP25 6YQ",
    "wof:placetype": "postalcode"
  },
  "geometry": {"coordinates":[0.74371,52.587527],"type":"Point"}
}
