{
  "type": "Feature",
  "properties": {
    "iso:country": "GB",
    "wof:name": "KY15 4NW",
    "wof:placetype": "postalcode"
  },
  "geometry": {"coordinates":[-3.056799,56.35708],"type":"Point"}
}
