{
  "type": "Feature",
  "properties": {
    "iso:country": "GB",
    "wof:name": "BN16 4QA",
    "wof:placetype": "postalcode"
  },
  "geometry": {"coordinates":[-0.472195,50.821288],"type":"Point"}
}
