{
  "type": "Feature",
  "properties": {
    "iso:country": "GB",
    "wof:name": "NE61 6FU",
    "wof:placetype": "postalcode"
  },
  "geometry": {"coordinates":[-1.655663,55.18282],"type":"Point"}
}
