{
  "type": "Feature",
  "properties": {
    "iso:country": "GB",
    "wof:name": "OX44 7LN",
    "wof:placetype": "postalcode"
  },
  "geometry": {"coordinates":[-1.073211,51.699683],"type":"Point"}
}
