{
  "type": "Feature",
  "properties": {
    "iso:country": "GB",
    "wof:name": "DL5 6RT",
    "wof:placetype": "postalcode"
  },
  "geometry": {"coordinates":[-1.611835,54.598255],"type":"Point"}
}
