{
  "type": "Feature",
  "properties": {
    "iso:country": "GB",
    "wof:name": "CV47 2UY",
    "wof:placetype": "postalcode"
  },
  "geometry": {"coordinates":[-1.426825,52.169584],"type":"Point"}
}
