{
  "type": "Feature",
  "properties": {
    "iso:country": "GB",
    "wof:name": "N22 6SR",
    "wof:placetype": "postalcode"
  },
  "geometry": {"coordinates":[-0.109987,51.59411],"type":"Point"}
}
