{
  "type": "Feature",
  "properties": {
    "iso:country": "GB",
    "wof:name": "SE7 7GB",
    "wof:placetype": "postalcode"
  },
  "geometry": {"coordinates":[0.024744,51.48519],"type":"Point"}
}
