{
  "type": "Feature",
  "properties": {
    "iso:country": "GB",
    "wof:name": "S64 0LB",
    "wof:placetype": "postalcode"
  },
  "geometry": {"coordinates":[-1.258148,53.49354],"type":"Point"}
}
