{
  "type": "Feature",
  "properties": {
    "iso:country": "GB",
    "wof:name": "CV23 9FU",
    "wof:placetype": "postalcode"
  },
  "geometry": {"coordinates":[-1.315338,52.354042],"type":"Point"}
}
