{
  "type": "Feature",
  "properties": {
    "iso:country": "GB",
    "wof:name": "G51 3AX",
    "wof:placetype": "postalcode"
  },
  "geometry": {"coordinates":[-4.316886,55.861937],"type":"Point"}
}
