{
  "type": "Feature",
  "properties": {
    "iso:country": "GB",
    "wof:name": "WF3 2GA",
    "wof:placetype": "postalcode"
  },
  "geometry": {"coordinates":[-1.549092,53.724756],"type":"Point"}
}
