{
  "type": "Feature",
  "properties": {
    "iso:country": "GB",
    "wof:name": "SK1 3GH",
    "wof:placetype": "postalcode"
  },
  "geometry": {"coordinates":[-2.160923,53.406042],"type":"Point"}
}
