{
  "type": "Feature",
  "properties": {
    "iso:country": "GB",
    "wof:name": "AB55 4BX",
    "wof:placetype": "postalcode"
  },
  "geometry": {"coordinates":[-3.140353,57.425773],"type":"Point"}
}
