{
  "type": "Feature",
  "properties": {
    "iso:country": "GB",
    "wof:name": "DL8 5LW",
    "wof:placetype": "postalcode"
  },
  "geometry": {"coordinates":[-1.746504,54.328814],"type":"Point"}
}
