{
  "type": "Feature",
  "properties": {
    "iso:country": "GB",
    "wof:name": "PR3 2FX",
    "wof:placetype": "postalcode"
  },
  "geometry": {"coordinates":[-2.69041,53.854793],"type":"Point"}
}
