{
  "type": "Feature",
  "properties": {
    "iso:country": "GB",
    "wof:name": "DH5 9FB",
    "wof:placetype": "postalcode"
  },
  "geometry": {"coordinates":[-1.45743,54.831936],"type":"Point"}
}
