{
  "type": "Feature",
  "properties": {
    "iso:country": "GB",
    "wof:name": "CF31 3TQ",
    "wof:placetype": "postalcode"
  },
  "geometry": {"coordinates":[-3.553523,51.501625],"type":"Point"}
}
