{
  "type": "Feature",
  "properties": {
    "iso:country": "GB",
    "wof:name": "CB5 8AD",
    "wof:placetype": "postalcode"
  },
  "geometry": {"coordinates":[0.118749,52.208696],"type":"Point"}
}
