{
  "type": "Feature",
  "properties": {
    "iso:country": "GB",
    "wof:name": "SY1 2EU",
    "wof:placetype": "postalcode"
  },
  "geometry": {"coordinates":[-2.747715,52.715335],"type":"Point"}
}
