{
  "type": "Feature",
  "properties": {
    "iso:country": "GB",
    "wof:name": "BA9 8HJ",
    "wof:placetype": "postalcode"
  },
  "geometry": {"coordinates":[-2.390301,51.091063],"type":"Point"}
}
