{
  "type": "Feature",
  "properties": {
    "iso:country": "GB",
    "wof:name": "GU34 1GQ",
    "wof:placetype": "postalcode"
  },
  "geometry": {"coordinates":[-0.989154,51.150918],"type":"Point"}
}
