{
  "type": "Feature",
  "properties": {
    "iso:country": "GB",
    "wof:name": "BR4 0SQ",
    "wof:placetype": "postalcode"
  },
  "geometry": {"coordinates":[-0.007717,51.374801],"type":"Point"}
}
