{
  "type": "Feature",
  "properties": {
    "iso:country": "GB",
    "wof:name": "WR5 1TH",
    "wof:placetype": "postalcode"
  },
  "geometry": {"coordinates":[-2.202159,52.187683],"type":"Point"}
}
