{
  "type": "Feature",
  "properties": {
    "iso:country": "GB",
    "wof:name": "BB2 2BN",
    "wof:placetype": "postalcode"
  },
  "geometry": {"coordinates":[-2.497783,53.73858],"type":"Point"}
}
