{
  "type": "Feature",
  "properties": {
    "iso:country": "GB",
    "wof:name": "RM4 1RD",
    "wof:placetype": "postalcode"
  },
  "geometry": {"coordinates":[0.164657,51.655184],"type":"Point"}
}
