{
  "type": "Feature",
  "properties": {
    "iso:country": "GB",
    "wof:name": "YO32 9QX",
    "wof:placetype": "postalcode"
  },
  "geometry": {"coordinates":[-1.05876,54.002082],"type":"Point"}
}
