{
  "type": "Feature",
  "properties": {
    "iso:country": "GB",
    "wof:name": "TR2 5TY",
    "wof:placetype": "postalcode"
  },
  "geometry": {"coordinates":[-4.920087,50.266559],"type":"Point"}
}
