{
  "type": "Feature",
  "properties": {
    "iso:country": "GB",
    "wof:name": "NR7 8LP",
    "wof:placetype": "postalcode"
  },
  "geometry": {"coordinates":[1.344696,52.657394],"type":"Point"}
}
