{
  "type": "Feature",
  "properties": {
    "iso:country": "GB",
    "wof:name": "PE8 6TL",
    "wof:placetype": "postalcode"
  },
  "geometry": {"coordinates":[-0.414561,52.51149],"type":"Point"}
}
