{
  "type": "Feature",
  "properties": {
    "iso:country": "GB",
    "wof:name": "G72 9BU",
    "wof:placetype": "postalcode"
  },
  "geometry": {"coordinates":[-4.115198,55.784112],"type":"Point"}
}
