{
  "type": "Feature",
  "properties": {
    "iso:country": "GB",
    "wof:name": "SA37 0JX",
    "wof:placetype": "postalcode"
  },
  "geometry": {"coordinates":[-4.550788,52.009937],"type":"Point"}
}
