{
  "type": "Feature",
  "properties": {
    "iso:country": "GB",
    "wof:name": "WR5 1TA",
    "wof:placetype": "postalcode"
  },
  "geometry": {"coordinates":[-2.175125,52.183312],"type":"Point"}
}
