{
  "type": "Feature",
  "properties": {
    "iso:country": "GB",
    "wof:name": "CW12 4DF",
    "wof:placetype": "postalcode"
  },
  "geometry": {"coordinates":[-2.23897,53.17411],"type":"Point"}
}
