{
  "type": "Feature",
  "properties": {
    "iso:country": "GB",
    "wof:name": "FK9 4AS",
    "wof:placetype": "postalcode"
  },
  "geometry": {"coordinates":[-3.930044,56.169222],"type":"Point"}
}
