{
  "type": "Feature",
  "properties": {
    "iso:country": "GB",
    "wof:name": "SN11 8HT",
    "wof:placetype": "postalcode"
  },
  "geometry": {"coordinates":[-1.988276,51.440341],"type":"Point"}
}
