{
  "type": "Feature",
  "properties": {
    "iso:country": "GB",
    "wof:name": "LA9 7PT",
    "wof:placetype": "postalcode"
  },
  "geometry": {"coordinates":[-2.728081,54.289322],"type":"Point"}
}
