{
  "type": "Feature",
  "properties": {
    "iso:country": "GB",
    "wof:name": "PH23 3BF",
    "wof:placetype": "postalcode"
  },
  "geometry": {"coordinates":[-3.80928,57.277243],"type":"Point"}
}
