{
  "type": "Feature",
  "properties": {
    "iso:country": "GB",
    "wof:name": "FY3 8QB",
    "wof:placetype": "postalcode"
  },
  "geometry": {"coordinates":[-3.006064,53.825669],"type":"Point"}
}
