{
  "type": "Feature",
  "properties": {
    "iso:country": "GB",
    "wof:name": "NG16 2WY",
    "wof:placetype": "postalcode"
  },
  "geometry": {"coordinates":[-1.290351,53.003592],"type":"Point"}
}
