{
  "type": "Feature",
  "properties": {
    "iso:country": "GB",
    "wof:name": "LE7 9WQ",
    "wof:placetype": "postalcode"
  },
  "geometry": {"coordinates":[-1.039145,52.638003],"type":"Point"}
}
