{
  "type": "Feature",
  "properties": {
    "iso:country": "GB",
    "wof:name": "CA6 5FB",
    "wof:placetype": "postalcode"
  },
  "geometry": {"coordinates":[-2.962335,55.005718],"type":"Point"}
}
