{
  "type": "Feature",
  "properties": {
    "iso:country": "GB",
    "wof:name": "KT19 8AD",
    "wof:placetype": "postalcode"
  },
  "geometry": {"coordinates":[-0.263805,51.334272],"type":"Point"}
}
