{
  "type": "Feature",
  "properties": {
    "iso:country": "GB",
    "wof:name": "S60 5WP",
    "wof:placetype": "postalcode"
  },
  "geometry": {"coordinates":[-1.369376,53.39052],"type":"Point"}
}
