{
  "type": "Feature",
  "properties": {
    "iso:country": "GB",
    "wof:name": "YO16 6AA",
    "wof:placetype": "postalcode"
  },
  "geometry": {"coordinates":[-0.206974,54.105055],"type":"Point"}
}
