{
  "type": "Feature",
  "properties": {
    "iso:country": "GB",
    "wof:name": "S81 0JN",
    "wof:placetype": "postalcode"
  },
  "geometry": {"coordinates":[-1.113409,53.315726],"type":"Point"}
}
