{
  "type": "Feature",
  "properties": {
    "iso:country": "GB",
    "wof:name": "HU16 5SN",
    "wof:placetype": "postalcode"
  },
  "geometry": {"coordinates":[-0.424408,53.784566],"type":"Point"}
}
