{
  "type": "Feature",
  "properties": {
    "iso:country": "GB",
    "wof:name": "DL8 5PH",
    "wof:placetype": "postalcode"
  },
  "geometry": {"coordinates":[-1.801623,54.301129],"type":"Point"}
}
