{
  "type": "Feature",
  "properties": {
    "iso:country": "GB",
    "wof:name": "WF9 2GH",
    "wof:placetype": "postalcode"
  },
  "geometry": {"coordinates":[-1.295683,53.594374],"type":"Point"}
}
