{
  "type": "Feature",
  "properties": {
    "iso:country": "GB",
    "wof:name": "EH48 1HN",
    "wof:placetype": "postalcode"
  },
  "geometry": {"coordinates":[-3.610857,55.897254],"type":"Point"}
}
