{
  "type": "Feature",
  "properties": {
    "iso:country": "GB",
    "wof:name": "B49 6HT",
    "wof:placetype": "postalcode"
  },
  "geometry": {"coordinates":[-1.826852,52.235111],"type":"Point"}
}
