{
  "type": "Feature",
  "properties": {
    "iso:country": "GB",
    "wof:name": "YO7 3FG",
    "wof:placetype": "postalcode"
  },
  "geometry": {"coordinates":[-1.356709,54.222046],"type":"Point"}
}
