{
  "type": "Feature",
  "properties": {
    "iso:country": "GB",
    "wof:name": "DE56 1UU",
    "wof:placetype": "postalcode"
  },
  "geometry": {"coordinates":[-1.483736,53.017111],"type":"Point"}
}
