{
  "type": "Feature",
  "properties": {
    "iso:country": "GB",
    "wof:name": "NR6 6XA",
    "wof:placetype": "postalcode"
  },
  "geometry": {"coordinates":[1.273131,52.665374],"type":"Point"}
}
