{
  "type": "Feature",
  "properties": {
    "iso:country": "GB",
    "wof:name": "RM12 6EU",
    "wof:placetype": "postalcode"
  },
  "geometry": {"coordinates":[0.222282,51.56049],"type":"Point"}
}
