{
  "type": "Feature",
  "properties": {
    "iso:country": "GB",
    "wof:name": "ME1 1NF",
    "wof:placetype": "postalcode"
  },
  "geometry": {"coordinates":[0.510359,51.387759],"type":"Point"}
}
