{
  "type": "Feature",
  "properties": {
    "iso:country": "GB",
    "wof:name": "MK42 0DW",
    "wof:placetype": "postalcode"
  },
  "geometry": {"coordinates":[-0.425419,52.11578],"type":"Point"}
}
