{
  "type": "Feature",
  "properties": {
    "iso:country": "GB",
    "wof:name": "BL6 5EF",
    "wof:placetype": "postalcode"
  },
  "geometry": {"coordinates":[-2.584196,53.593991],"type":"Point"}
}
