{
  "type": "Feature",
  "properties": {
    "iso:country": "GB",
    "wof:name": "RH17 7ER",
    "wof:placetype": "postalcode"
  },
  "geometry": {"coordinates":[-0.001303,51.031341],"type":"Point"}
}
