{
  "type": "Feature",
  "properties": {
    "iso:country": "GB",
    "wof:name": "DG7 3RN",
    "wof:placetype": "postalcode"
  },
  "geometry": {"coordinates":[-4.141012,55.073066],"type":"Point"}
}
