{
  "type": "Feature",
  "properties": {
    "iso:country": "GB",
    "wof:name": "TA24 5EE",
    "wof:placetype": "postalcode"
  },
  "geometry": {"coordinates":[-3.470146,51.20336],"type":"Point"}
}
