{
  "type": "Feature",
  "properties": {
    "iso:country": "GB",
    "wof:name": "HR1 4HW",
    "wof:placetype": "postalcode"
  },
  "geometry": {"coordinates":[-2.592055,52.056381],"type":"Point"}
}
