{
  "type": "Feature",
  "properties": {
    "iso:country": "GB",
    "wof:name": "TA10 9FJ",
    "wof:placetype": "postalcode"
  },
  "geometry": {"coordinates":[-2.82269,51.046176],"type":"Point"}
}
