{
  "type": "Feature",
  "properties": {
    "iso:country": "GB",
    "wof:name": "L34 9GJ",
    "wof:placetype": "postalcode"
  },
  "geometry": {"coordinates":[-2.871772,53.463622],"type":"Point"}
}
