{
  "type": "Feature",
  "properties": {
    "iso:country": "GB",
    "wof:name": "TN6 2GG",
    "wof:placetype": "postalcode"
  },
  "geometry": {"coordinates":[0.192173,51.048683],"type":"Point"}
}
