{
  "type": "Feature",
  "properties": {
    "iso:country": "GB",
    "wof:name": "CW2 5UU",
    "wof:placetype": "postalcode"
  },
  "geometry": {"coordinates":[-2.43408,53.075343],"type":"Point"}
}
