{
  "type": "Feature",
  "properties": {
    "iso:country": "GB",
    "wof:name": "IP12 2RB",
    "wof:placetype": "postalcode"
  },
  "geometry": {"coordinates":[1.397658,52.13],"type":"Point"}
}
