{
  "type": "Feature",
  "properties": {
    "iso:country": "GB",
    "wof:name": "ST15 0FQ",
    "wof:placetype": "postalcode"
  },
  "geometry": {"coordinates":[-2.157306,52.893721],"type":"Point"}
}
