{
  "type": "Feature",
  "properties": {
    "iso:country": "GB",
    "wof:name": "NR7 8GR",
    "wof:placetype": "postalcode"
  },
  "geometry": {"coordinates":[1.348949,52.656725],"type":"Point"}
}
