{
  "type": "Feature",
  "properties": {
    "iso:country": "GB",
    "wof:name": "YO30 6AL",
    "wof:placetype": "postalcode"
  },
  "geometry": {"coordinates":[-1.093936,53.967227],"type":"Point"}
}
