{
  "type": "Feature",
  "properties": {
    "iso:country": "GB",
    "wof:name": "YO51 9PW",
    "wof:placetype": "postalcode"
  },
  "geometry": {"coordinates":[-1.368493,54.057457],"type":"Point"}
}
