{
  "type": "Feature",
  "properties": {
    "iso:country": "GB",
    "wof:name": "WV14 6HQ",
    "wof:placetype": "postalcode"
  },
  "geometry": {"coordinates":[-2.082119,52.578721],"type":"Point"}
}
