{
  "type": "Feature",
  "properties": {
    "iso:country": "GB",
    "wof:name": "BH25 5WH",
    "wof:placetype": "postalcode"
  },
  "geometry": {"coordinates":[-1.662151,50.790205],"type":"Point"}
}
