{
  "type": "Feature",
  "properties": {
    "iso:country": "GB",
    "wof:name": "FK2 8FN",
    "wof:placetype": "postalcode"
  },
  "geometry": {"coordinates":[-3.816768,56.042393],"type":"Point"}
}
