{
  "type": "Feature",
  "properties": {
    "iso:country": "GB",
    "wof:name": "HU17 8GS",
    "wof:placetype": "postalcode"
  },
  "geometry": {"coordinates":[-0.491878,53.820084],"type":"Point"}
}
