{
  "type": "Feature",
  "properties": {
    "iso:country": "GB",
    "wof:name": "RG5 4FJ",
    "wof:placetype": "postalcode"
  },
  "geometry": {"coordinates":[-0.878868,51.460847],"type":"Point"}
}
