{
  "type": "Feature",
  "properties": {
    "iso:country": "GB",
    "wof:name": "DE23 3BD",
    "wof:placetype": "postalcode"
  },
  "geometry": {"coordinates":[-1.52722,52.889786],"type":"Point"}
}
