{
  "type": "Feature",
  "properties": {
    "iso:country": "GB",
    "wof:name": "SG4 7NT",
    "wof:placetype": "postalcode"
  },
  "geometry": {"coordinates":[-0.245765,51.910314],"type":"Point"}
}
