{
  "type": "Feature",
  "properties": {
    "iso:country": "GB",
    "wof:name": "HU1 1AR",
    "wof:placetype": "postalcode"
  },
  "geometry": {"coordinates":[-0.333817,53.739834],"type":"Point"}
}
