{
  "type": "Feature",
  "properties": {
    "iso:country": "GB",
    "wof:name": "HX7 5DN",
    "wof:placetype": "postalcode"
  },
  "geometry": {"coordinates":[-1.986884,53.728604],"type":"Point"}
}
