{
  "type": "Feature",
  "properties": {
    "iso:country": "GB",
    "wof:name": "HX2 9WB",
    "wof:placetype": "postalcode"
  },
  "geometry": {"coordinates":[-1.877959,53.75796],"type":"Point"}
}
