{
  "type": "Feature",
  "properties": {
    "iso:country": "GB",
    "wof:name": "B63 3PD",
    "wof:placetype": "postalcode"
  },
  "geometry": {"coordinates":[-2.063058,52.459598],"type":"Point"}
}
