{
  "type": "Feature",
  "properties": {
    "iso:country": "GB",
    "wof:name": "LN2 3FZ",
    "wof:placetype": "postalcode"
  },
  "geometry": {"coordinates":[-0.469869,53.303152],"type":"Point"}
}
