{
  "type": "Feature",
  "properties": {
    "iso:country": "GB",
    "wof:name": "DN10 4NX",
    "wof:placetype": "postalcode"
  },
  "geometry": {"coordinates":[-0.861991,53.397085],"type":"Point"}
}
