{
  "type": "Feature",
  "properties": {
    "iso:country": "GB",
    "wof:name": "BS30 6HX",
    "wof:placetype": "postalcode"
  },
  "geometry": {"coordinates":[-2.470013,51.428823],"type":"Point"}
}
