{
  "type": "Feature",
  "properties": {
    "iso:country": "GB",
    "wof:name": "CW6 0JD",
    "wof:placetype": "postalcode"
  },
  "geometry": {"coordinates":[-2.662598,53.166265],"type":"Point"}
}
