{
  "type": "Feature",
  "properties": {
    "iso:country": "GB",
    "wof:name": "BL1 8GB",
    "wof:placetype": "postalcode"
  },
  "geometry": {"coordinates":[-2.415148,53.594446],"type":"Point"}
}
