{
  "type": "Feature",
  "properties": {
    "iso:country": "GB",
    "wof:name": "LE12 9FY",
    "wof:placetype": "postalcode"
  },
  "geometry": {"coordinates":[-1.280858,52.77789],"type":"Point"}
}
