{
  "type": "Feature",
  "properties": {
    "iso:country": "GB",
    "wof:name": "TN23 3UB",
    "wof:placetype": "postalcode"
  },
  "geometry": {"coordinates":[0.838684,51.127001],"type":"Point"}
}
