{
  "type": "Feature",
  "properties": {
    "iso:country": "GB",
    "wof:name": "CV10 9GX",
    "wof:placetype": "postalcode"
  },
  "geometry": {"coordinates":[-1.527693,52.527449],"type":"Point"}
}
