{
  "type": "Feature",
  "properties": {
    "iso:country": "GB",
    "wof:name": "ME3 8GP",
    "wof:placetype": "postalcode"
  },
  "geometry": {"coordinates":[0.567028,51.453327],"type":"Point"}
}
