{
  "type": "Feature",
  "properties": {
    "iso:country": "GB",
    "wof:name": "SO31 8NJ",
    "wof:placetype": "postalcode"
  },
  "geometry": {"coordinates":[-1.322045,50.895899],"type":"Point"}
}
