{
  "type": "Feature",
  "properties": {
    "iso:country": "GB",
    "wof:name": "YO25 9BS",
    "wof:placetype": "postalcode"
  },
  "geometry": {"coordinates":[-0.549253,53.943731],"type":"Point"}
}
