{
  "type": "Feature",
  "properties": {
    "iso:country": "GB",
    "wof:name": "CO7 8GH",
    "wof:placetype": "postalcode"
  },
  "geometry": {"coordinates":[1.066333,51.857981],"type":"Point"}
}
