{
  "type": "Feature",
  "properties": {
    "iso:country": "GB",
    "wof:name": "CF33 6LD",
    "wof:placetype": "postalcode"
  },
  "geometry": {"coordinates":[-3.688351,51.53271],"type":"Point"}
}
