{
  "type": "Feature",
  "properties": {
    "iso:country": "GB",
    "wof:name": "DN16 1TR",
    "wof:placetype": "postalcode"
  },
  "geometry": {"coordinates":[-0.63888,53.584898],"type":"Point"}
}
