{
  "type": "Feature",
  "properties": {
    "iso:country": "GB",
    "wof:name": "CH5 3DT",
    "wof:placetype": "postalcode"
  },
  "geometry": {"coordinates":[-3.05195,53.189487],"type":"Point"}
}
