{
  "type": "Feature",
  "properties": {
    "iso:country": "GB",
    "wof:name": "PL26 7FN",
    "wof:placetype": "postalcode"
  },
  "geometry": {"coordinates":[-4.860396,50.343948],"type":"Point"}
}
