{
  "type": "Feature",
  "properties": {
    "iso:country": "GB",
    "wof:name": "DN14 8SB",
    "wof:placetype": "postalcode"
  },
  "geometry": {"coordinates":[-0.945658,53.707452],"type":"Point"}
}
