{
  "type": "Feature",
  "properties": {
    "iso:country": "GB",
    "wof:name": "LN5 9UN",
    "wof:placetype": "postalcode"
  },
  "geometry": {"coordinates":[-0.539071,53.16165],"type":"Point"}
}
