{
  "type": "Feature",
  "properties": {
    "iso:country": "GB",
    "wof:name": "SO31 8NG",
    "wof:placetype": "postalcode"
  },
  "geometry": {"coordinates":[-1.323282,50.893982],"type":"Point"}
}
