{
  "type": "Feature",
  "properties": {
    "iso:country": "GB",
    "wof:name": "SW4 9AY",
    "wof:placetype": "postalcode"
  },
  "geometry": {"coordinates":[-0.15635,51.458025],"type":"Point"}
}
