{
  "type": "Feature",
  "properties": {
    "iso:country": "GB",
    "wof:name": "LE12 6YS",
    "wof:placetype": "postalcode"
  },
  "geometry": {"coordinates":[-1.18508,52.823785],"type":"Point"}
}
