{
  "type": "Feature",
  "properties": {
    "iso:country": "GB",
    "wof:name": "S63 8GW",
    "wof:placetype": "postalcode"
  },
  "geometry": {"coordinates":[-1.306418,53.518116],"type":"Point"}
}
