{
  "type": "Feature",
  "properties": {
    "iso:country": "GB",
    "wof:name": "L5 3YX",
    "wof:placetype": "postalcode"
  },
  "geometry": {"coordinates":[-2.972351,53.420994],"type":"Point"}
}
