{
  "type": "Feature",
  "properties": {
    "iso:country": "GB",
    "wof:name": "DY6 7NG",
    "wof:placetype": "postalcode"
  },
  "geometry": {"coordinates":[-2.14289,52.506716],"type":"Point"}
}
