{
  "type": "Feature",
  "properties": {
    "iso:country": "GB",
    "wof:name": "PA20 9BZ",
    "wof:placetype": "postalcode"
  },
  "geometry": {"coordinates":[-5.056123,55.833004],"type":"Point"}
}
