{
  "type": "Feature",
  "properties": {
    "iso:country": "GB",
    "wof:name": "BS34 5TJ",
    "wof:placetype": "postalcode"
  },
  "geometry": {"coordinates":[-2.582282,51.526014],"type":"Point"}
}
