{
  "type": "Feature",
  "properties": {
    "iso:country": "GB",
    "wof:name": "CW12 4ZF",
    "wof:placetype": "postalcode"
  },
  "geometry": {"coordinates":[-2.253221,53.173028],"type":"Point"}
}
