{
  "type": "Feature",
  "properties": {
    "iso:country": "GB",
    "wof:name": "NE5 2BF",
    "wof:placetype": "postalcode"
  },
  "geometry": {"coordinates":[-1.691572,54.988253],"type":"Point"}
}
