{
  "type": "Feature",
  "properties": {
    "iso:country": "GB",
    "wof:name": "NE13 9EB",
    "wof:placetype": "postalcode"
  },
  "geometry": {"coordinates":[-1.658192,55.026661],"type":"Point"}
}
