{
  "type": "Feature",
  "properties": {
    "iso:country": "GB",
    "wof:name": "SA3 1NP",
    "wof:placetype": "postalcode"
  },
  "geometry": {"coordinates":[-4.21493,51.548419],"type":"Point"}
}
