{
  "type": "Feature",
  "properties": {
    "iso:country": "GB",
    "wof:name": "CA7 5HF",
    "wof:placetype": "postalcode"
  },
  "geometry": {"coordinates":[-3.258112,54.855309],"type":"Point"}
}
