{
  "type": "Feature",
  "properties": {
    "iso:country": "GB",
    "wof:name": "CT12 6FD",
    "wof:placetype": "postalcode"
  },
  "geometry": {"coordinates":[1.389082,51.341712],"type":"Point"}
}
