{
  "type": "Feature",
  "properties": {
    "iso:country": "GB",
    "wof:name": "CF81 9EF",
    "wof:placetype": "postalcode"
  },
  "geometry": {"coordinates":[-3.216155,51.681823],"type":"Point"}
}
