{
  "type": "Feature",
  "properties": {
    "iso:country": "GB",
    "wof:name": "DT5 2DJ",
    "wof:placetype": "postalcode"
  },
  "geometry": {"coordinates":[-2.443663,50.531421],"type":"Point"}
}
