{
  "type": "Feature",
  "properties": {
    "iso:country": "GB",
    "wof:name": "S81 0FD",
    "wof:placetype": "postalcode"
  },
  "geometry": {"coordinates":[-1.102614,53.326584],"type":"Point"}
}
