{
  "type": "Feature",
  "properties": {
    "iso:country": "GB",
    "wof:name": "HG3 3DY",
    "wof:placetype": "postalcode"
  },
  "geometry": {"coordinates":[-1.624978,54.036006],"type":"Point"}
}
