{
  "type": "Feature",
  "properties": {
    "iso:country": "GB",
    "wof:name": "IP31 3QB",
    "wof:placetype": "postalcode"
  },
  "geometry": {"coordinates":[0.810525,52.263626],"type":"Point"}
}
