{
  "type": "Feature",
  "properties": {
    "iso:country": "GB",
    "wof:name": "AL6 9BS",
    "wof:placetype": "postalcode"
  },
  "geometry": {"coordinates":[-0.265576,51.84361],"type":"Point"}
}
