{
  "type": "Feature",
  "properties": {
    "iso:country": "GB",
    "wof:name": "GL7 3FY",
    "wof:placetype": "postalcode"
  },
  "geometry": {"coordinates":[-1.72515,51.69245],"type":"Point"}
}
