{
  "type": "Feature",
  "properties": {
    "iso:country": "GB",
    "wof:name": "GL15 5FT",
    "wof:placetype": "postalcode"
  },
  "geometry": {"coordinates":[-2.516277,51.7309],"type":"Point"}
}
