{
  "type": "Feature",
  "properties": {
    "iso:country": "GB",
    "wof:name": "LA13 9HQ",
    "wof:placetype": "postalcode"
  },
  "geometry": {"coordinates":[-3.203012,54.120498],"type":"Point"}
}
