{
  "type": "Feature",
  "properties": {
    "iso:country": "GB",
    "wof:name": "SY5 0FF",
    "wof:placetype": "postalcode"
  },
  "geometry": {"coordinates":[-2.888634,52.65066],"type":"Point"}
}
