{
  "type": "Feature",
  "properties": {
    "iso:country": "GB",
    "wof:name": "BB10 4TA",
    "wof:placetype": "postalcode"
  },
  "geometry": {"coordinates":[-2.172292,53.742627],"type":"Point"}
}
