{
  "type": "Feature",
  "properties": {
    "iso:country": "GB",
    "wof:name": "TS22 5UE",
    "wof:placetype": "postalcode"
  },
  "geometry": {"coordinates":[-1.370294,54.642949],"type":"Point"}
}
