{
  "type": "Feature",
  "properties": {
    "iso:country": "GB",
    "wof:name": "IP14 3AA",
    "wof:placetype": "postalcode"
  },
  "geometry": {"coordinates":[0.942904,52.180762],"type":"Point"}
}
